Workbook
Name Summary: #REF!

Sheet Summary
B2: Swiggy Summary - July 2026
B4: Details | C4: 1st to 5th | D4: 6th to 12th | E4: 13th to 19th | F4: 20th to 26th | G4: 27th to 31st | H4: Total
B6: No.of orders | H6: =SUM(C6:G6) -> 0
B8: Total Income (Number that you see on Swiggy dashboard) | C8: =Cashflow!C10 -> 0 | D8: =Cashflow!D10 -> 0 | E8: =Cashflow!E10 -> 0 | F8: =Cashflow!F10 -> 0 | G8: =Cashflow!G10 -> 0 | H8: =SUM(C8:G8) -> 0
B10: Avg. order value | C10: =IFERROR(C8/C6,) -> 0 | D10: =IFERROR(D8/D6,) -> 0 | E10: =IFERROR(E8/E6,) -> 0 | F10: =IFERROR(F8/F6,) -> 0 | G10: =IFERROR(G8/G6,) -> 0 | H10: =IFERROR(H8/H6,) -> 0
B12: No of Disputed Orders | C12: 0 | D12: 0 | E12: 0 | F12: 0 | G12: 0 | H12: =SUM(C12:G12) -> 0
B14: Refund amount for disputed orders | C14: =Cashflow!C13 -> 0 | D14: =Cashflow!D13 -> 0 | E14: =Cashflow!E13 -> 0 | F14: =Cashflow!F13 -> 0 | G14: =Cashflow!G13 -> 0 | H14: =SUM(C14:G14) -> 0
B15: Discounts | C15: =Cashflow!C8 -> 0 | D15: =Cashflow!D8 -> 0 | E15: =Cashflow!E8 -> 0 | F15: =Cashflow!F8 -> 0 | G15: =Cashflow!G8 -> 0 | H15: =SUM(C15:G15) -> 0
C16: =IFERROR(C15/C8,0) -> 0 | D16: =IFERROR(D15/D8,0) -> 0 | E16: =IFERROR(E15/E8,0) -> 0 | F16: =IFERROR(F15/F8,0) -> 0 | G16: =IFERROR(G15/G8,0) -> 0 | H16: =IFERROR(H15/H8,0) -> 0
B17: Commission | C17: =Cashflow!C11 -> 0 | D17: =Cashflow!D11 -> 0 | E17: =Cashflow!E11 -> 0 | F17: =Cashflow!F11 -> 0 | G17: =Cashflow!G11 -> 0 | H17: =SUM(C17:G17) -> 0
B18: (Calculated on Sales + GST) | C18: =IFERROR(C17/C8,0) -> 0 | D18: =IFERROR(D17/D8,0) -> 0 | E18: =IFERROR(E17/E8,0) -> 0 | F18: =IFERROR(F17/F8,0) -> 0 | G18: =IFERROR(G17/G8,0) -> 0 | H18: =IFERROR(H17/H8,0) -> 0
B19: Marketing & Ads | C19: =Cashflow!C16 -> 0 | D19: =Cashflow!D16 -> 0 | E19: =Cashflow!E16 -> 0 | F19: =Cashflow!F16 -> 0 | G19: =Cashflow!G16 -> 0 | H19: =SUM(C19:G19) -> 0
C20: =IFERROR(C19/C8,0) -> 0 | D20: =IFERROR(D19/D8,0) -> 0 | E20: =IFERROR(E19/E8,0) -> 0 | F20: =IFERROR(F19/F8,0) -> 0 | G20: =IFERROR(G19/G8,0) -> 0 | H20: =IFERROR(H19/H8,0) -> 0
B21: Other charges & Tax Adjustments | C21: =Cashflow!C20+Cashflow!C26 -> 0 | D21: =Cashflow!D20+Cashflow!D26 -> 0 | E21: =Cashflow!E20+Cashflow!E26 -> 0 | F21: =Cashflow!F20+Cashflow!F26 -> 0 | G21: =Cashflow!G20+Cashflow!G26 -> 0 | H21: =SUM(C21:G21) -> 0
C22: =IFERROR(C21/C8,0) -> 0 | D22: =IFERROR(D21/D8,0) -> 0 | E22: =IFERROR(E21/E8,0) -> 0 | F22: =IFERROR(F21/F8,0) -> 0 | G22: =IFERROR(G21/G8,0) -> 0 | H22: =IFERROR(H21/H8,0) -> 0
B24: Money received | C24: =C8-C14-C17-C19-C21 -> 0 | D24: =D8-D14-D17-D19-D21 -> 0 | E24: =E8-E14-E17-E19-E21 -> 0 | F24: =F8-F14-F17-F19-F21 -> 0 | G24: =G8-G14-G17-G19-G21 -> 0 | H24: =H8-H14-H17-H19-H21 -> 0
C25: =IFERROR(C24/$C$8,0) -> 0 | D25: =IFERROR(D24/$D$8,0) -> 0 | E25: =IFERROR(E24/$E$8,0) -> 0 | F25: =IFERROR(F24/$F$8,0) -> 0 | G25: =IFERROR(G24/$G$8,0) -> 0 | H25: =IFERROR(H24/$H$8,0) -> 0

Sheet Cashflow
A1: =Summary!B1 -> 0 | K1: =H10+H8-H29 -> 0 | M1: =H12*100/118 -> 0
A2: Swiggy Cash Flow Statement - July 2026 | M2: =M1*0.02% -> 0
A4: S.No | B4: Details | C4: =Summary!C4 -> 1st to 5th | D4: =Summary!D4 -> 6th to 12th | E4: =Summary!E4 -> 13th to 19th | F4: =Summary!F4 -> 20th to 26th | G4: =Summary!G4 -> 27th to 31st | H4: Total
A5: 1 | B5: Item sales (Delivered orders) | H5: =SUM(C5:G5) -> 0
B6: Add:- Packing charges | H6: =SUM(C6:G6) -> 0 | J6: GST | K6: =H10-H29 -> 0
B7: Add:- Compensation paid for cancelled orders | H7: =SUM(C7:G7) -> 0 | J7: TDS | K7: =H12*100/118 -> 0
B8: Less:- Discount | H8: =SUM(C8:G8) -> 0
B9: Add:- GST 5% | H9: =SUM(C9:G9) -> 0 | N9: =AVERAGE(J12:L12) -> #DIV/0!
B10: Net Sales | C10: =C5+C6+C7-C8+C9 -> 0 | D10: =D5+D6+D7-D8+D9 -> 0 | E10: =E5+E6+E7-E8+E9 -> 0 | F10: =F5+F6+F7-F8+F9 -> 0 | G10: =G5+G6+G7-G8+G9 -> 0 | H10: =SUM(C10:G10) -> 0 | J10: =H10-H29 -> 0
A11: 2 | B11: Less:- Commission | C11: =SUM(C12) -> 0 | D11: =SUM(D12) -> 0 | E11: =SUM(E12) -> 0 | F11: =SUM(F12) -> 0 | G11: =SUM(G12) -> 0 | H11: =SUM(C11:G11) -> 0
B12: Platform Fee | H12: =SUM(C12:G12) -> 0 | J12: =C12/C10 -> #DIV/0! | K12: =D12/D10 -> #DIV/0! | L12: =E12/E10 -> #DIV/0! | M12: =F12/F10 -> #DIV/0! | N12: =AVERAGE(J12:M12) -> #DIV/0!
A13: 3 | B13: Less:- Refunds | C13: =SUM(C14:C15) -> 0 | D13: =SUM(D14:D15) -> 0 | E13: =SUM(E14:E15) -> 0 | F13: =SUM(F14:F15) -> 0 | G13: =SUM(G14:G15) -> 0 | H13: =SUM(C13:G13) -> 0
B14: Paid by Restaurant | H14: =SUM(C14:G14) -> 0
B15: Received by Restaurant | C15: 0 | D15: 0 | E15: 0 | F15: 0 | G15: 0 | H15: =SUM(C15:G15) -> 0 | J15: =C10+C8-C29 -> 0 | K15: =D10+D8-D29 -> 0 | L15: =E10+E8-E29 -> 0 | M15: =F10+F8-F29 -> 0 | N15: =G10+G8-G29 -> 0
A16: 4 | B16: Less:- Marketing Charges | C16: =SUM(C17:C19) -> 0 | D16: =SUM(D17:D19) -> 0 | E16: =E17+E18+E19 -> 0 | F16: =F17+F18+F19 -> 0 | G16: =G17+G18+G19 -> 0 | H16: =SUM(C16:G16) -> 0 | J16: =C12*100/118 -> 0 | K16: =D12*100/118 -> 0 | L16: =E12*100/118 -> 0 | M16: =F12*100/118 -> 0 | N16: =G12*100/118 -> 0
B17: High Priority | H17: =SUM(C17:G17) -> 0 | J17: =J16*2% -> 0 | K17: =K16*2% -> 0 | L17: =L16*2% -> 0 | M17: =M16*2% -> 0 | N17: =N16*2% -> 0
B18: Call Center Service Fees | H18: =SUM(C18:G18) -> 0
B19: PocketHero Fee | H19: =SUM(C19:G19) -> 0
A20: 5 | B20: Less:- Other Charges | C20: =SUM(C21:C24) -> 0 | D20: =SUM(D21:D24) -> 0 | E20: =SUM(E21:E24) -> 0 | F20: =SUM(F21:F24) -> 0 | G20: =SUM(G21:G24) -> 0 | H20: =SUM(C20:G20) -> 0
B21: Collection Charges | H21: =SUM(C21:G21) -> 0
B22: Long Distance Fee | H22: =SUM(C22:G22) -> 0
B23: Swiggy One Fees | H23: =SUM(C23:G23) -> 0
B24: Merchant Cancellation Charges | H24: =SUM(C24:G24) -> 0
B25: Profit from Swiggy | C25: =C5+C6+C7-C8+C9-C12-C13-C16-C20-C29 -> 0 | D25: =D5+D6+D7-D8+D9-D12-D13-D16-D20-D29 -> 0 | E25: =E5+E6+E7-E8+E9-E12-E13-E16-E20-E29 -> 0 | F25: =F5+F6+F7-F8+F9-F12-F13-F16-F20-F29 -> 0 | G25: =G5+G6+G7-G8+G9-G12-G13-G16-G20-G29 -> 0 | H25: =SUM(C25:G25) -> 0 | N25: 259885
A26: 6 | B26: Less:- Tax Adjustments | C26: =SUM(C27:C29) -> 0 | D26: =SUM(D27:D29) -> 0 | E26: =SUM(E27:E29) -> 0 | F26: =SUM(F27:F29) -> 0 | G26: =SUM(G27:G29) -> 0 | H26: =SUM(C26:G26) -> 0 | N26: 9643
B27: TDS deduction for aggrigators | H27: =SUM(C27:G27) -> 0
B28: TCS | H28: =SUM(C28:G28) -> 0 | N28: -23947.45
B29: GST collected and paid by swiggy | H29: =SUM(C29:G29) -> 0 | N29: 12289.68
A30: 7 | B30: Expected Receipts | C30: =C25-C27 -> 0 | D30: =D25-D27 -> 0 | E30: =E25-E27 -> 0 | F30: =F25-F27 -> 0 | G30: =G25-G27 -> 0 | H30: =SUM(C30:G30) -> 0
B31: Intriem payments | C31: 0 | D31: 0 | E31: 0 | F31: 0 | G31: 0 | H31: 0
B32: Previous week Adjustments | C32: 0 | D32: 0 | E32: 0 | F32: 0 | G32: 0 | H32: =SUM(C32:G32) -> 0
B33: EMI Loan deductions | C33: 0 | D33: 0 | E33: 0 | F33: 0 | G33: 0 | H33: =SUM(C33:G33) -> 0
B34: Actual Receipts | C34: 0 | D34: 0 | E34: 0 | F34: 0 | G34: 0 | H34: =SUM(C34:G34) -> 0
A35: 8 | B35: Difference | C35: =C30-C31-C33-C34-C32 -> 0 | D35: =D30-D31-D33-D34-D32 -> 0 | E35: =E30-E31-E33-E34-E32 -> 0 | F35: =F30-F31-F33-F34-F32 -> 0 | G35: =G30-G31-G33-G34-G32 -> 0 | H35: =SUM(C35:G35) -> 0
B37: Notes:-

Sheet Profit statement
B1: =Summary!B1 -> 0
B2: Swiggy Profit Statement - July 2026
B4: Details | C4: =Cashflow!C4 -> 1st to 5th | D4: =Cashflow!D4 -> 6th to 12th | E4: =Cashflow!E4 -> 13th to 19th | F4: =Cashflow!F4 -> 20th to 26th | G4: =Summary!G4 -> 27th to 31st | H4: Total
B5: A. Net Sales
B6: Total Income | C6: =Cashflow!C5+Cashflow!C6-Cashflow!C8+Cashflow!C9-Cashflow!C29 -> 0 | D6: =Cashflow!D5+Cashflow!D6-Cashflow!D8+Cashflow!D9-Cashflow!D29 -> 0 | E6: =Cashflow!E5+Cashflow!E6-Cashflow!E8+Cashflow!E9-Cashflow!E29 -> 0 | F6: =Cashflow!F5+Cashflow!F6-Cashflow!F8+Cashflow!F9-Cashflow!F29 -> 0 | G6: =Cashflow!G5+Cashflow!G6-Cashflow!G8+Cashflow!G9-Cashflow!G29 -> 0 | H6: =SUM(C6:G6) -> 0
B7: Add- Adjust: Cancelled orders (By Swiggy) | C7: =Cashflow!C7 -> 0 | D7: =Cashflow!D7 -> 0 | E7: =Cashflow!E7 -> 0 | F7: =Cashflow!F7 -> 0 | G7: =Cashflow!G7 -> 0 | H7: =SUM(C7:G7) -> 0
B8: Net Sales (Number that you see on Numerize app) | C8: =C6+C7 -> 0 | D8: =D6+D7 -> 0 | E8: =E6+E7 -> 0 | F8: =F6+F7 -> 0 | G8: =G6+G7 -> 0 | H8: =H6+H7 -> 0
B10: B. Less:- Commission | C10: =Cashflow!C11 -> 0 | D10: =Cashflow!D11 -> 0 | E10: =Cashflow!E11 -> 0 | F10: =Cashflow!F11 -> 0 | G10: =Cashflow!G11 -> 0 | H10: =SUM(C10:G10) -> 0
B12: C. Less:- Marketing & Ads | C12: =Cashflow!C16 -> 0 | D12: =Cashflow!D16 -> 0 | E12: =Cashflow!E16 -> 0 | F12: =Cashflow!F16 -> 0 | G12: =Cashflow!G16 -> 0 | H12: =SUM(C12:G12) -> 0
B14: D. Less:- Refund on disputed orders | C14: =Cashflow!C13 -> 0 | D14: =Cashflow!D13 -> 0 | E14: =Cashflow!E13 -> 0 | F14: =Cashflow!F13 -> 0 | G14: =Cashflow!G13 -> 0 | H14: =SUM(C14:G14) -> 0
B16: E. Other charges | C16: =Cashflow!C20 -> 0 | D16: =Cashflow!D20 -> 0 | E16: =Cashflow!E20 -> 0 | F16: =Cashflow!F20 -> 0 | G16: =Cashflow!G20 -> 0 | H16: =SUM(C16:G16) -> 0
B18: F. Profit | C18: =C8-C10-C12-C14-C16 -> 0 | D18: =D8-D10-D12-D14-D16 -> 0 | E18: =E8-E10-E12-E14-E16 -> 0 | F18: =F8-F10-F12-F14-F16 -> 0 | G18: =G8-G10-G12-G14-G16 -> 0 | H18: =H8-H10-H12-H14-H16 -> 0
B19: Percentage | C19: =IFERROR(C18/C8,) -> 0 | D19: =IFERROR(D18/D8,) -> 0 | E19: =IFERROR(E18/E8,0) -> 0 | F19: =IFERROR(F18/F8,0) -> 0 | G19: =IFERROR(G18/G8,0) -> 0 | H19: =IFERROR(H18/H8,) -> 0

Sheet Discrepancies
B1: =Summary!B1 -> 0
B2: Swiggy Discrepancies - July 2026
B4: Details | C4: =Summary!C4 -> 1st to 5th | D4: =Summary!D4 -> 6th to 12th | E4: =Summary!E4 -> 13th to 19th | F4: =Summary!F4 -> 20th to 26th | G4: =Summary!G4 -> 27th to 31st | H4: Total
B5: A. POS discrepancies
B6: Sales as per Swiggy | C6: =Cashflow!C10 -> 0 | D6: =Cashflow!D10 -> 0 | E6: =Cashflow!E10 -> 0 | F6: =Cashflow!F10 -> 0 | G6: =Cashflow!G10 -> 0 | H6: =SUM(C6:G6) -> 0
B7: Sale as per POS | H7: =SUM(C7:G7) -> 0
B8: Difference | C8: =C6-C7 -> 0 | D8: =D6-D7 -> 0 | E8: =E6-E7 -> 0 | F8: =F6-F7 -> 0 | G8: =G6-G7 -> 0 | H8: =SUM(C8:G8) -> 0
C9: =IFERROR(C8/C6,0) -> 0 | D9: =IFERROR(D8/D6,0) -> 0 | E9: =IFERROR(E8/E6,0) -> 0 | F9: =IFERROR(F8/F6,0) -> 0 | G9: =IFERROR(G8/G6,0) -> 0 | H9: =IFERROR(H8/H6,0) -> 0
B11: B. Order discrepancies
B12: No.of delivered orders for which payment isn't received | C12: 0 | D12: 0 | E12: 0 | F12: 0 | G12: 0 | H12: =SUM(C12:G12) -> 0
B13: Value of such orders | C13: 0 | D13: 0 | E13: 0 | F13: 0 | G13: 0 | H13: =SUM(C13:G13) -> 0
B16: C. Payment discrepancies
B17: Expected receipts in the bank account | C17: =Cashflow!C30 -> 0 | D17: =Cashflow!D30 -> 0 | E17: =Cashflow!E30 -> 0 | F17: =Cashflow!F30 -> 0 | G17: =Cashflow!G30 -> 0 | H17: =SUM(C17:G17) -> 0
B18: Interim Payments | C18: 0 | D18: 0 | E18: 0 | F18: 0 | G18: 0 | H18: =SUM(C18:G18) -> 0
B19: Previous Week Adjustments | C19: =Cashflow!C32 -> 0 | D19: =Cashflow!D32 -> 0 | E19: =Cashflow!E32 -> 0 | F19: =Cashflow!F32 -> 0 | G19: =Cashflow!G32 -> 0 | H19: =SUM(C19:G19) -> 0
B20: Actual receipts in the bank | C20: =Cashflow!C34 -> 0 | D20: =Cashflow!D34 -> 0 | E20: =Cashflow!E34 -> 0 | F20: =Cashflow!F34 -> 0 | G20: =Cashflow!G34 -> 0 | H20: =SUM(C20:G20) -> 0
B21: Difference | C21: =C17-C20-C18-C19 -> 0 | D21: =D17-D20-D18-D19 -> 0 | E21: =E17-E20-E18-E19 -> 0 | F21: =F17-F20-F18-F19 -> 0 | G21: =G17-G20-G18-G19 -> 0 | H21: =H17-H20-H18-H19 -> 0
B23: Notes:

Sheet BANK

Sheet POS
