Workbook

Sheet Summary
B1: adsf
B2: Zomato Summary - December - 2026
B4: Details | C4: 1st to 7th | D4: 8th to 14th | E4: 15th to 21st | F4: 22nd to 28th | G4: 29th to 31st | H4: Total
B6: No.of orders | C6: 345 | D6: 344 | E6: 346 | F6: 293 | G6: 115 | H6: =SUM(C6:G6)
B8: Total Income (Number that you see on Zomato dashboard) | C8: =Cashflow!C10 | D8: =Cashflow!D10 | E8: =Cashflow!E10 | F8: =Cashflow!F10 | G8: =Cashflow!G10 | H8: =SUM(C8:G8)
B10: Avg. order value | C10: =IFERROR(C8/C6,) | D10: =IFERROR(D8/D6,) | E10: =IFERROR(E8/E6,) | F10: =IFERROR(F8/F6,) | G10: =IFERROR(G8/G6,) | H10: =IFERROR(H8/H6,)
B12: No of disputed orders | C12: 0 | D12: 0 | E12: 0 | F12: 0 | G12: 0 | H12: =SUM(C12:G12)
B14: Refund amount for disputed orders | C14: =Cashflow!C18 | D14: =Cashflow!D18 | E14: =Cashflow!E18 | F14: =Cashflow!F18 | G14: =Cashflow!G18 | H14: =SUM(C14:G14)
B16: Discounts | C16: =Cashflow!C8 | D16: =Cashflow!D8 | E16: =Cashflow!E8 | F16: =Cashflow!F8 | G16: =Cashflow!G8 | H16: =SUM(C16:G16)
C17: =IFERROR(C16/C8,) | D17: =IFERROR(D16/D8,) | E17: =IFERROR(E16/E8,) | F17: =IFERROR(F16/F8,) | G17: =IFERROR(G16/G8,) | H17: =IFERROR(H16/H8,)
B19: Commisonable Amount | C19: 90777 | D19: 82452.3 | E19: 82294.7 | F19: 68186.2 | G19: 26778.2 | H19: =SUM(C19:G19)
B20: Commission | C20: =Cashflow!C11 | D20: =Cashflow!D11 | E20: =Cashflow!E11 | F20: =Cashflow!F11 | G20: =Cashflow!G11 | H20: =SUM(C20:G20)
B21: (Calculated on Sales + GST) | C21: =IFERROR(C20/C19,) | D21: =IFERROR(D20/D19,) | E21: =IFERROR(E20/E19,) | F21: =IFERROR(F20/F19,) | G21: =IFERROR(G20/G19,) | H21: =IFERROR(H20/H19,)
B23: Marketing & Ads | C23: =Cashflow!C21 | D23: =Cashflow!D21 | E23: =Cashflow!E21 | F23: =Cashflow!F21 | G23: =Cashflow!G21 | H23: =SUM(C23:G23)
C24: =IFERROR(C23/C8,) | D24: =IFERROR(D23/D8,) | E24: =IFERROR(E23/E8,) | F24: =IFERROR(F23/F8,) | G24: =IFERROR(G23/G8,) | H24: =IFERROR(H23/H8,)
B27: Other charges & Tax Adjustments | C27: =Cashflow!C13+Cashflow!C26 | D27: =Cashflow!D13+Cashflow!D26 | E27: =Cashflow!E13+Cashflow!E26 | F27: =Cashflow!F13+Cashflow!F26 | G27: =Cashflow!G13+Cashflow!G26 | H27: =SUM(C27:G27)
C28: =IFERROR(C27/C8,) | D28: =IFERROR(D27/D8,) | E28: =IFERROR(E27/E8,) | F28: =IFERROR(F27/F8,) | G28: =IFERROR(G27/G8,) | H28: =IFERROR(H27/H8,)
B32: Zomato Hyperpure Adjustments | C32: =Cashflow!C36 | D32: =Cashflow!D36 | E32: =Cashflow!E36 | F32: =Cashflow!F36 | G32: =Cashflow!G36 | H32: =SUM(C32:G32)
B35: Money received | C35: =C8-C14-C20-C23-C27-C32 | D35: =D8-D14-D20-D23-D27-D32 | E35: =E8-E14-E20-E23-E27-E32 | F35: =F8-F14-F20-F23-F27-F32+Cashflow!F31 | G35: =G8-G14-G20-G23-G27-G32 | H35: =SUM(C35:G35)
C36: =IFERROR(C35/$C$8,) | D36: =IFERROR(D35/$D$8,) | E36: =IFERROR(E35/$E$8,) | F36: =IFERROR(F35/F8,) | G36: =IFERROR(G35/G8,) | H36: =IFERROR(H35/H8,)

Sheet Cashflow
A1: =Summary!B1
A2: Zomato Cash Flow - December - 2026
A4: S.No | B4: Details | C4: =Summary!C4 | D4: =Summary!D4 | E4: =Summary!E4 | F4: =Summary!F4 | G4: =Summary!G4 | H4: Total
A5: 1 | B5: Item sales (Delivered orders) | C5: ='D1W1'!O2 | D5: ='D1W2'!O2 | E5: ='D1W3'!O2 | F5: ='D1W4'!O2 | G5: ='D1W5'!O2 | H5: =SUM(C5:G5)
B6: Add:- Packing charges | C6: ='D1W1'!P2 | D6: ='D1W2'!P2 | E6: ='D1W3'!P2 | F6: ='D1W4'!P2 | G6: ='D1W5'!P2 | H6: =SUM(C6:G6)
B7: Add:- Compensation paid for cancelled orders | C7: ='D1W1'!AV1 | D7: ='D1W2'!AV1 | E7: ='D1W3'!AV1 | F7: ='D1W4'!AV1 | G7: ='D1W5'!AV1 | H7: =SUM(C7:G7)
B8: Less:- Discount | C8: ='D1W1'!R2+'D1W1'!S2+'D1W1'!U2 | D8: ='D1W2'!R2+'D1W2'!S2+'D1W2'!U2 | E8: ='D1W3'!R2+'D1W3'!S2+'D1W3'!U2 | F8: ='D1W4'!R2+'D1W4'!S2+'D1W4'!U2 | G8: ='D1W5'!R2+'D1W5'!S2+'D1W5'!U2 | H8: =SUM(C8:G8)
B9: Add:- GST | C9: ='D1W1'!V2 | D9: ='D1W2'!V2 | E9: ='D1W3'!V2 | F9: ='D1W4'!V2 | G9: ='D1W5'!V2 | H9: =SUM(C9:G9) | M9: Gst | N9: Tds
B10: Net Sales | C10: =C5+C6+C9+C7-C8 | D10: =D5+D6+D9+D7-D8 | E10: =E5+E6+E9+E7-E8 | F10: =F5+F6+F9+F7-F8 | G10: =G5+G6+G9+G7-G8 | H10: =H5+H6+H9+H7-H8 | M10: =H10-H29 | N10: =H12*100/118
A11: 2 | B11: Less:- Commission | C11: =C12 | D11: =D12 | E11: =E12 | F11: =F12 | G11: =G12 | H11: =H12
B12: Platform Fee | C12: ='D1W1'!Z3 | D12: ='D1W2'!Z3 | E12: ='D1W3'!Z3 | F12: ='D1W4'!Z3 | G12: ='D1W5'!Z3 | H12: =SUM(C12:G12)
A13: 3 | B13: Less:- Other Charges | C13: =C14+C16-C15+C17 | D13: =D14+D16-D15+D17 | E13: =E14+E16-E15+E17 | F13: =F14+F16-F15+F17 | G13: =G14+G16-G15+G17 | H13: =H14+H16-H15+H17
B14: Convenience Fee | C14: ='D1W1'!AA3 | D14: ='D1W2'!AA3 | E14: ='D1W3'!AA3 | F14: ='D1W4'!AA3 | G14: ='D1W5'!AA3 | H14: =SUM(C14:G14)
B15: Discount on Service Fee | H15: =SUM(C15:G15) | L15: netsales | M15: =C10+C8-C29 | N15: =D10+D8-D29 | O15: =E10+E8-E29 | P15: =F10+F8-F29 | Q15: =G10+G8-G29
B16: Long Distance Fee | H16: =SUM(C16:G16) | L16: disc | M16: =C8 | N16: =D8 | O16: =E8 | P16: =F8 | Q16: =G8
A17: 4 | B17: Merchant Cancellation Charges | C17: 0 | D17: 0 | E17: 0 | F17: 0 | G17: 0 | H17: =SUM(C17:G17) | L17: comm | M17: =C12-C15 | N17: =D12-D15 | O17: =E12-E15 | P17: =F12-F15 | Q17: =G12-G15
B18: Less:- Refunds | C18: =SUM(C19:C20) | D18: =SUM(D19:D20) | E18: =SUM(E19:E20) | F18: =SUM(F19:F20) | G18: =SUM(G19:G20) | H18: =H19+H20 | L18: tds ecom | M18: =C27 | N18: =D27 | O18: =E27 | P18: =F27 | Q18: =G27
B19: Paid by Restaurant | C19: ='D1W1'!AL4 | D19: ='D1W2'!AL4 | E19: ='D1W3'!AL4 | F19: ='D1W4'!AL4 | G19: ='D1W5'!AL4 | H19: =SUM(C19:G19) | L19: conve | M19: =C14 | N19: =D14 | O19: =E14 | P19: =F14 | Q19: =G14
A20: 5 | B20: Received by Restaurant | C20: 0 | D20: 0 | E20: 0 | F20: 0 | G20: 0 | H20: =SUM(C20:G20) | L20: othe cha | M20: =C16 | N20: =D16 | O20: =E16 | P20: =F16 | Q20: =G16
B21: Less:- Marketing Charges | C21: =C22+C23+C24 | D21: =D22+D23+D24 | E21: =E22+E23+E24 | F21: =F22+F23+F24 | G21: =G22+G23+G24 | H21: =H22+H23+H24 | L21: tds | M21: =(C12*100/118)*2% | N21: =(D12*100/118)*2% | O21: =(E12*100/118)*2% | P21: =(F12*100/118)*2% | Q21: =(G12*100/118)*2%
B22: High Priority | C22: 5250.53 | D22: 4970.17 | E22: 4377.01 | F22: 0 | G22: 0 | H22: =SUM(C22:G22)
B23: Call Center Service Fees | C23: 0 | D23: 0 | E23: 0 | F23: 0 | G23: 0 | H23: =SUM(C23:G23)
B24: PocketHero Fee | C24: 0 | D24: 0 | E24: 0 | F24: 0 | G24: 0 | H24: =SUM(C24:G24)
A25: 6 | B25: Profit from Zomato | C25: =C10-C11-C18-C21-C13-C29 | D25: =D10-D11-D18-D21-D13-D29 | E25: =E10-E11-E18-E21-E13-E29 | F25: =F10-F11-F18-F21-F13-F29 | G25: =G10-G11-G18-G21-G13-G29 | H25: =H10-H11-H18-H21-H13-H29
B26: Less:- Tax Adjustments | C26: =SUM(C27:C29) | D26: =SUM(D27:D29) | E26: =SUM(E27:E29) | F26: =SUM(F27:F29) | G26: =SUM(G27:G29) | H26: =SUM(H27:H29)
B27: TDS deduction for aggrigators | C27: ='D1W1'!AH4 | D27: ='D1W2'!AH4 | E27: ='D1W3'!AH4 | F27: ='D1W4'!AH4 | G27: ='D1W5'!AH4 | H27: =SUM(C27:G27)
B28: TCS | C28: ='D1W1'!AF4+'D1W1'!AG4 | D28: ='D1W2'!AF4+'D1W2'!AG4 | E28: ='D1W3'!AF4+'D1W3'!AG4 | F28: ='D1W4'!AF4+'D1W4'!AG4 | G28: ='D1W5'!AF4+'D1W5'!AG4 | H28: =SUM(C28:G28)
A29: 7 | B29: GST collected and paid by Zomato | C29: ='D1W1'!AI4 | D29: ='D1W2'!AI4 | E29: ='D1W3'!AI4 | F29: ='D1W4'!AI4 | G29: ='D1W5'!AI4 | H29: =SUM(C29:G29)
B30: Expected Receipts | C30: =C25-C27-C28-C34 | D30: =D25-D27-D28-D34 | E30: =E25-E27-E28-E34 | F30: =F25-F27-F28-F34 | G30: =G25-G27-G28-G34 | H30: =H25-H27-H28-H34
B31: Service Fee Reversal | C31: 0 | D31: 0 | E31: 0 | F31: 0 | G31: 0 | H31: =SUM(C31:G31)
B32: Interim payments | C32: 0 | D32: 0 | E32: 0 | F32: 0 | G32: 0 | H32: =SUM(C32:G32)
B33: Opening Week Adjustments | C33: 0 | D33: 0 | E33: 0 | F33: 0 | G33: 0 | H33: =SUM(C33:G33)
B34: Following Week Adjustments | C34: 0 | D34: 0 | E34: 0 | F34: 0 | G34: 0 | H34: =SUM(C34:G34)
B35: Closing Week Adjustments | C35: 0 | D35: 0 | E35: 0 | F35: 0 | G35: 0 | H35: =SUM(C35:G35)
B36: Zomato hyperpure Payment Adjustments | C36: 0 | D36: 0 | E36: 0 | F36: 0 | G36: 0 | H36: =SUM(C36:G36)
B37: EMI Loan deductions | C37: 0 | D37: 0 | E37: 0 | F37: 0 | G37: 0 | H37: =SUM(C37:G37)
A38: 8 | B38: Actual receipts | C38: 0 | D38: 0 | E38: 0 | F38: 0 | G38: 0 | H38: =SUM(C38:G38)
B39: Difference | C39: =C30-C38-C36+C33+C35 | D39: =D30-D38-D36-D33+D35 | E39: =E30-E38-E36-E33+E35 | F39: =F30-F38-F36-F33+F35-F34-F32 | G39: =G30-G38-G36-G33+G35 | H39: =H30-H38-H36+H33+H35-H34-H32
B41: Note :

Sheet Profit statement
A1: =Summary!B1
A2: Zomato Profit Statement - December - 2026
A4: Details | B4: =Summary!C4 | C4: =Summary!D4 | D4: =Summary!E4 | E4: =Summary!F4 | F4: =Summary!G4 | G4: =Summary!H4
A5: A. Net Sales
A6: Total Income | B6: =Cashflow!C5+Cashflow!C6+Cashflow!C9-Cashflow!C8-Cashflow!C29 | C6: =Cashflow!D5+Cashflow!D6+Cashflow!D9-Cashflow!D8-Cashflow!D29 | D6: =Cashflow!E5+Cashflow!E6+Cashflow!E9-Cashflow!E8-Cashflow!E29 | E6: =Cashflow!F5+Cashflow!F6+Cashflow!F9-Cashflow!F8-Cashflow!F29 | F6: =Cashflow!G5+Cashflow!G6+Cashflow!G9-Cashflow!G8-Cashflow!G29 | G6: =SUM(B6:F6)
A7: Add- Adjust: Cancelled orders (By Zomato) | B7: =Cashflow!C7 | C7: =Cashflow!D7 | D7: =Cashflow!E7 | E7: =Cashflow!F7 | F7: =Cashflow!G7 | G7: =SUM(B7:F7)
A8: Net Sales (Number that you see on Numerize app) | B8: =B6+B7 | C8: =C6+C7 | D8: =D6+D7 | E8: =E6+E7 | F8: =F6+F7 | G8: =G6+G7
A10: B. Less:- Commission | B10: =Cashflow!C11 | C10: =Cashflow!D11 | D10: =Cashflow!E11 | E10: =Cashflow!F11 | F10: =Cashflow!G11 | G10: =SUM(B10:F10)
A12: C. Less:- Marketing & Ads | B12: =Cashflow!C21 | C12: =Cashflow!D21 | D12: =Cashflow!E21 | E12: =Cashflow!F21 | F12: =Cashflow!G21 | G12: =SUM(B12:F12)
A14: D. Less:- Refund on disputed orders | B14: =Cashflow!C18 | C14: =Cashflow!D18 | D14: =Cashflow!E18 | E14: =Cashflow!F18 | F14: =Cashflow!G18 | G14: =SUM(B14:F14)
A16: E. Other charges | B16: =Cashflow!C13 | C16: =Cashflow!D13 | D16: =Cashflow!E13 | E16: =Cashflow!F13 | F16: =Cashflow!G13 | G16: =SUM(B16:F16)
A18: F. Profit | B18: =B8-B10-B12-B14-B16 | C18: =C8-C10-C12-C14-C16 | D18: =D8-D10-D12-D14-D16 | E18: =E8-E10-E12-E14-E16 | F18: =F8-F10-F12-F14-F16 | G18: =G8-G10-G12-G14-G16
A19: Percentage | B19: =IFERROR(B18/B8,0) | C19: =IFERROR(C18/C8,0) | D19: =IFERROR(D18/D8,0) | E19: =IFERROR(E18/E8,0) | F19: =IFERROR(F18/F8,0) | G19: =G18/G8

Sheet Discrepancies
A1: =Summary!B1
A2: Zomato Discrepancies - December - 2026
A4: Details | B4: =Summary!C4 | C4: =Summary!D4 | D4: =Summary!E4 | E4: =Summary!F4 | F4: =Summary!G4 | G4: =Summary!H4
A5: A. POS discrepancies
A6: Sales as per Zomato | B6: =Cashflow!C10 | C6: =Cashflow!D10 | D6: =Cashflow!E10 | E6: =Cashflow!F10 | F6: =Cashflow!G10 | G6: =SUM(B6:F6)
A7: Sale as per POS | G7: =SUM(B7:F7)
A8: Difference | B8: =B7-B6 | C8: =C7-C6 | D8: =D7-D6 | E8: =E7-E6 | F8: =F7-F6 | G8: =G7-G6
B9: =IFERROR(B8/B6,) | C9: =IFERROR(C8/C6,0) | D9: =IFERROR(D8/D6,0) | E9: =IFERROR(E8/E6,0) | F9: =IFERROR(F8/F6,0) | G9: =IFERROR(G8/G6,0)
A11: B. Order discrepancies
A12: No.of delivered orders for which payment isn't received | B12: 0 | C12: 0 | D12: 0 | E12: 0 | F12: 0 | G12: =SUM(B12:F12)
A13: Value of such orders | B13: 0 | C13: 0 | D13: 0 | E13: 0 | F13: 0 | G13: =SUM(B13:F13)
A16: C. Payment discrepancies
A17: Expected receipts in the bank account | B17: =Cashflow!C30 | C17: =Cashflow!D30 | D17: =Cashflow!E30 | E17: =Cashflow!F30 | F17: =Cashflow!G30 | G17: =SUM(B17:F17)
A18: Investment in Hyperpure | B18: =Cashflow!C36 | C18: =Cashflow!D36 | D18: =Cashflow!E36 | E18: =Cashflow!F36 | F18: =Cashflow!G36 | G18: =SUM(B18:F18)
A19: Following Week Adjustment | B19: =Cashflow!C34 | C19: =Cashflow!D34 | D19: =Cashflow!E34 | E19: =Cashflow!F34 | F19: =Cashflow!G34 | G19: =SUM(B19:F19)
A20: Opening Week Adjustment | B20: =Cashflow!C33 | C20: =Cashflow!D33 | D20: =Cashflow!E33 | E20: =Cashflow!F33 | F20: 0 | G20: =SUM(B20:F20)
A21: Closing Week Adjustment | B21: =Cashflow!C35 | C21: =Cashflow!D35 | D21: =Cashflow!E35 | E21: =Cashflow!F35 | F21: =Cashflow!G35 | G21: =SUM(B21:F21)
A22: Actual receipts in the bank | B22: =Cashflow!C38 | C22: =Cashflow!D38 | D22: =Cashflow!E38 | E22: =Cashflow!F38 | F22: =Cashflow!G38 | G22: =SUM(B22:F22)
A23: Difference | B23: =B17-B22-B18+B20 | C23: =C17-C22-C18 | D23: =D17-D22-D18 | E23: =E17-E22-E18-E19 | F23: =F17-F22-F18+F21 | G23: =G17-G22-G18+G20-G19
A25: Note:

Sheet POS

Sheet BANK
B5: 1 | C5: 2 | D5: 3 | E5: 4 | F5: 5
A10: Date | B10: Narration | C10: Chq./Ref.No. | D10: Value Dt | E10: Withdrawal Amt. | F10: Deposit Amt. | G10: Closing Balance
A11: 01/10/25 | B11: NEFT CR-YESB0000001-ONE 97 COMMUNICATIONS LIMITED SETTL-ROCKTAIL HOSPITALITY SERVICES-YESBN12025100101816795 | C11: YESBN12025100101816795 | D11: 01/10/25 | F11: 28308.11 | G11: 369938.81
A12: 01/10/25 | B12: NEFT CR-RATN0000999-PINE LABS LIMITED-ROCKTAIL HOSPITALITY SERVICES-RATNN52025100142548753 | C12: RATNN52025100142548753 | D12: 01/10/25 | F12: 988.02 | G12: 370926.83
A13: 01/10/25 | B13: 42552394TERMINAL 1 CARDS SETTL. 01/10/25 | C13: 000000000000000 | D13: 01/10/25 | F13: 4135.06 | G13: 375061.89
A14: 01/10/25 | B14: UPI-8978287178PTYES-8978287178@PTYES-UBIN0813567-564035906635-UPI | C14: 0000564035906635 | D14: 01/10/25 | E14: 165 | G14: 374896.89
A15: 01/10/25 | B15: 50200069817641-TPT-NBLCVTK6KLDPDJXS-WOLFFPACK VENTURES PRIVATE LIMITED | C15: 0000000223256296 | D15: 01/10/25 | F15: 200000 | G15: 574896.89
A16: 01/10/25 | B16: VENDOR PAYMENTS - ROCKTAIL HOSPITALITY DR - 57500000326520 - NEFT TRANSITORY ACCOUNT | C16: 0000000000000188 | D16: 01/10/25 | E16: 390734 | G16: 184162.89
A17: 01/10/25 | B17: UPI-SHREY SINGH-SHREYSINGH0501-1@OKHDFCBANK-HDFC0004216-564012927870-REGISTRATION | C17: 0000564012927870 | D17: 01/10/25 | E17: 8700 | G17: 175462.89
A18: 01/10/25 | B18: NEFT RETURN-INCORRECT ACCOUNT NUMBER-LAXMI AGENCIES-IBKLN92025100194760959 | C18: HDFCN52025100104276617 | D18: 01/10/25 | F18: 8322 | G18: 183784.89
A19: 01/10/25 | B19: NEFT RETURN-INCORRECT ACCOUNT NUMBER-LAXMI AGENCIES-IBKLN92025100194760962 | C19: HDFCN52025100104276606 | D19: 01/10/25 | F19: 8316 | G19: 192100.89
A20: 01/10/25 | B20: NEFT CR-CITI0000002-ETERNAL LIMITED-ROCKTAIL HOSPITALITY SERVICES-CITIN52025100134584901 | C20: CITIN52025100134584901 | D20: 01/10/25 | F20: 22470.51 | G20: 214571.4
A21: 01/10/25 | B21: NEFT CR-UTIB0000052-BUNDL TECHNOLOGIES PRIVATE LIMITED-ROCKTAIL HOSPITALITY SERVICES-UTIBN62025100172850989 | C21: UTIBN62025100172850989 | D21: 01/10/25 | F21: 28624.05 | G21: 243195.45
A22: 01/10/25 | B22: FT - DR - 50200086201346 - SRI CHAKRA ENTERPRISES | C22: 0000000000000187 | D22: 01/10/25 | E22: 68400 | G22: 174795.45
A23: 01/10/25 | B23: CQ NO-000187 AMOUNT-100323 TRANSFERS 4 DR - 50200088485779 - NSP ENTERPRISES | C23: 000000000000000 | D23: 01/10/25 | E23: 12843 | G23: 161952.45
A24: 01/10/25 | B24: CQ NO-000187 AMOUNT-100323 TRANSFERS 4 DR - 50200082063860 - AAMODHA ENTERPRISES | C24: 000000000000000 | D24: 01/10/25 | E24: 16560 | G24: 145392.45
A25: 01/10/25 | B25: CQ NO-000187 AMOUNT-100323 TRANSFERS 4 DR - 50200034371828 - SRIHITHA DISTRIBUTORS | C25: 000000000000000 | D25: 01/10/25 | E25: 2520 | G25: 142872.45
A26: 01/10/25 | B26: UPI-SRI LAXMI CHENNAKESA-Q560982817@YBL-YESB0YBLUPI-112039563850-POOJA | C26: 0000112039563850 | D26: 01/10/25 | E26: 1651 | G26: 141221.45
A27: 01/10/25 | B27: NEFT CR-YESB0000001-SWIGGY LIMITED-ROCKTAIL HOSPITALITY SERVICES-YESBN12025100106534132 | C27: YESBN12025100106534132 | D27: 01/10/25 | F27: 37494.72 | G27: 178716.17
A28: 02/10/25 | B28: NEFT CR-YESB0000001-ONE 97 COMMUNICATIONS LIMITED SETTL-ROCKTAIL HOSPITALITY SERVICES-YESBN12025100202440556 | C28: YESBN12025100202440556 | D28: 02/10/25 | F28: 28924.86 | G28: 207641.03
A29: 02/10/25 | B29: 42552394TERMINAL 1 CARDS SETTL. 02/10/25 | C29: 000000000000000 | D29: 02/10/25 | F29: 6676.28 | G29: 214317.31
A30: 03/10/25 | B30: NEFT CR-YESB0000001-ONE 97 COMMUNICATIONS LIMITED SETTL-ROCKTAIL HOSPITALITY SERVICES-YESBN12025100302342936 | C30: YESBN12025100302342936 | D30: 03/10/25 | F30: 38471.91 | G30: 252789.22
A31: 03/10/25 | B31: 42552394TERMINAL 1 CARDS SETTL. 03/10/25 | C31: 000000000000000 | D31: 03/10/25 | F31: 13411.99 | G31: 266201.21
A32: 03/10/25 | B32: UPI-BHANWRA RAM-BHANWARJATCHOUDHARY251@OKSBI-SBIN0011306-564239417166-FURNITURE | C32: 0000564239417166 | D32: 03/10/25 | E32: 35000 | G32: 231201.21
A33: 03/10/25 | B33: NEFT CR-UTIB0000052-BUNDL TECHNOLOGIES PRIVATE LIMITED-ROCKTAIL HOSPITALITY SERVICES-UTIBN62025100395892591 | C33: UTIBN62025100395892591 | D33: 03/10/25 | F33: 13038.51 | G33: 244239.72
A34: 04/10/25 | B34: NEFT CR-YESB0000001-ONE 97 COMMUNICATIONS LIMITED SETTL-ROCKTAIL HOSPITALITY SERVICES-YESBN12025100403632181 | C34: YESBN12025100403632181 | D34: 04/10/25 | F34: 53035 | G34: 297274.72
A35: 04/10/25 | B35: 42552394TERMINAL 1 CARDS SETTL. 04/10/25 | C35: 000000000000000 | D35: 04/10/25 | F35: 10812.69 | G35: 308087.41
A36: 04/10/25 | B36: UPI-SWIGGY LIMITED-SWIGGY.STORES@AXB-UTIB0000100-527751059928-PAY FOR INTENT | C36: 0000527751059928 | D36: 04/10/25 | E36: 856 | G36: 307231.41
A37: 05/10/25 | B37: NEFT CR-YESB0000001-ONE 97 COMMUNICATIONS LIMITED SETTL-ROCKTAIL HOSPITALITY SERVICES-YESBN12025100501829191 | C37: YESBN12025100501829191 | D37: 05/10/25 | F37: 72645.73 | G37: 379877.14
A38: 05/10/25 | B38: 42552394TERMINAL 1 CARDS SETTL. 05/10/25 | C38: 000000000000000 | D38: 05/10/25 | F38: 17370.83 | G38: 397247.97
A39: 05/10/25 | B39: SETTLEMENT CHARGE-SEP25-CPY597 | C39: 000000000000000 | D39: 05/10/25 | E39: 37.76 | G39: 397210.21
A40: 06/10/25 | B40: NEFT CR-YESB0000001-ONE 97 COMMUNICATIONS LIMITED SETTL-ROCKTAIL HOSPITALITY SERVICES-YESBN12025100601953902 | C40: YESBN12025100601953902 | D40: 06/10/25 | F40: 65856.98 | G40: 463067.19
A41: 06/10/25 | B41: EMI 162047443 CHQ S16204744314 1025162047443 | C41: 000000000000000 | D41: 06/10/25 | E41: 70666 | G41: 392401.19
A42: 06/10/25 | B42: 42552394TERMINAL 1 CARDS SETTL. 06/10/25 | C42: 000000000000000 | D42: 06/10/25 | F42: 1635.17 | G42: 394036.36
A43: 06/10/25 | B43: NEFT CR-CITI0000002-ETERNAL LIMITED-ROCKTAIL HOSPITALITY SERVICES-CITIN52025100636240957 | C43: CITIN52025100636240957 | D43: 06/10/25 | F43: 61201.16 | G43: 455237.52
A44: 07/10/25 | B44: NEFT CR-YESB0000001-ONE 97 COMMUNICATIONS LIMITED SETTL-ROCKTAIL HOSPITALITY SERVICES-YESBN12025100701113506 | C44: YESBN12025100701113506 | D44: 07/10/25 | F44: 24613.36 | G44: 479850.88
A45: 07/10/25 | B45: 42552394TERMINAL 1 CARDS SETTL. 07/10/25 | C45: 000000000000000 | D45: 07/10/25 | F45: 9641.79 | G45: 489492.67
A46: 07/10/25 | B46: NEFT CR-YESB0000001-SWIGGY LIMITED-ROCKTAIL HOSPITALITY SERVICES-YESBN12025100705709842 | C46: YESBN12025100705709842 | D46: 07/10/25 | F46: 83057.26 | G46: 572549.93
A47: 08/10/25 | B47: NEFT CR-YESB0000001-ONE 97 COMMUNICATIONS LIMITED SETTL-ROCKTAIL HOSPITALITY SERVICES-YESBN12025100800862936 | C47: YESBN12025100800862936 | D47: 08/10/25 | F47: 17786 | G47: 590335.93
A48: 08/10/25 | B48: 42552394TERMINAL 1 CARDS SETTL. 08/10/25 | C48: 000000000000000 | D48: 08/10/25 | F48: 5938.15 | G48: 596274.08
A49: 08/10/25 | B49: NEFT CR-UTIB0000052-BUNDL TECHNOLOGIES PRIVATE LIMITED-ROCKTAIL HOSPITALITY SERVICES-UTIBN62025100849523664 | C49: UTIBN62025100849523664 | D49: 08/10/25 | F49: 18504.91 | G49: 614778.99
A50: 08/10/25 | B50: NEFT CR-CITI0000002-ETERNAL LIMITED-ROCKTAIL HOSPITALITY SERVICES-CITIN52025100837147976 | C50: CITIN52025100837147976 | D50: 08/10/25 | F50: 50928.19 | G50: 665707.18
A51: 08/10/25 | B51: IMPS-528119960741-ASTRANOVA ENTERPRISES-HDFC-XXXXXXXXXX1166-REPAYMENT | C51: 0000528119960741 | D51: 08/10/25 | F51: 200000 | G51: 865707.18
A52: 09/10/25 | B52: NEFT CR-YESB0000001-ONE 97 COMMUNICATIONS LIMITED SETTL-ROCKTAIL HOSPITALITY SERVICES-YESBN12025100901044475 | C52: YESBN12025100901044475 | D52: 09/10/25 | F52: 21882 | G52: 887589.18
A53: 09/10/25 | B53: 42552394TERMINAL 1 CARDS SETTL. 09/10/25 | C53: 000000000000000 | D53: 09/10/25 | F53: 4616 | G53: 892205.18
A54: 09/10/25 | B54: UPI-HARISH RAGHAVENDRA-HARISH.RAGHAVENDRA26@OKHDFCBANK-ICIC0000069-528262186657-HARISH | C54: 0000528262186657 | D54: 09/10/25 | E54: 15000 | G54: 877205.18
A55: 10/10/25 | B55: NEFT CR-YESB0000001-ONE 97 COMMUNICATIONS LIMITED SETTL-ROCKTAIL HOSPITALITY SERVICES-YESBN12025101001357483 | C55: YESBN12025101001357483 | D55: 10/10/25 | F55: 26001.28 | G55: 903206.46
A56: 10/10/25 | B56: 42552394TERMINAL 1 CARDS SETTL. 10/10/25 | C56: 000000000000000 | D56: 10/10/25 | F56: 865 | G56: 904071.46
A57: 10/10/25 | B57: NEFT CR-YESB0000001-SWIGGY LIMITED-ROCKTAIL HOSPITALITY SERVICES-YESBN12025101005972616 | C57: YESBN12025101005972616 | D57: 10/10/25 | F57: 9952.07 | G57: 914023.53
A58: 11/10/25 | B58: NEFT CR-UTIB0001506-PHONEPE LIMITED-PAYMENT AGGREGATOR ESCROW ACCOUNT-ROCKTAIL HOSPITALITY-UTIBN62025101184068608 | C58: UTIBN62025101184068608 | D58: 11/10/25 | F58: 1526.84 | G58: 915550.37
A59: 11/10/25 | B59: NEFT CR-YESB0000001-ONE 97 COMMUNICATIONS LIMITED SETTL-ROCKTAIL HOSPITALITY SERVICES-YESBN12025101102528197 | C59: YESBN12025101102528197 | D59: 11/10/25 | F59: 27767.83 | G59: 943318.2
A60: 11/10/25 | B60: 42552394TERMINAL 1 CARDS SETTL. 11/10/25 | C60: 000000000000000 | D60: 11/10/25 | F60: 8196.67 | G60: 951514.87
A61: 11/10/25 | B61: UPI-SYED AITAF HUSSAIN-ALTAFHUSAINN123456789@OKICICI-ANDB0000031-565027520596-SOFA REPAIR | C61: 0000565027520596 | D61: 11/10/25 | E61: 5000 | G61: 946514.87
A62: 12/10/25 | B62: NEFT CR-YESB0000001-ONE 97 COMMUNICATIONS LIMITED SETTL-ROCKTAIL HOSPITALITY SERVICES-YESBN12025101202583652 | C62: YESBN12025101202583652 | D62: 12/10/25 | F62: 84506.26 | G62: 1031021.1
A63: 12/10/25 | B63: NEFT CR-UTIB0001506-PHONEPE LIMITED-PAYMENT AGGREGATOR ESCROW ACCOUNT-ROCKTAIL HOSPITALITY-UTIBN62025101294570095 | C63: UTIBN62025101294570095 | D63: 12/10/25 | F63: 2151.18 | G63: 1033172.3
A64: 12/10/25 | B64: 42552394TERMINAL 1 CARDS SETTL. 12/10/25 | C64: 000000000000000 | D64: 12/10/25 | F64: 15719.66 | G64: 1048892
A65: 12/10/25 | B65: UPI-GAMPA AMBA PRASAD-PRASADUCANMAIL@OKHDFCBANK-HDFC0004262-565118092224-MILK VENDOR | C65: 0000565118092224 | D65: 12/10/25 | E65: 4641 | G65: 1044251
A66: 12/10/25 | B66: UPI-Y KARUNAKAR-KARUNAKAR.YARLAGADDA1@YBL-DBSS0IN0136-112558585085-SIGN BOARD | C66: 0000112558585085 | D66: 12/10/25 | E66: 5000 | G66: 1039251
A67: 12/10/25 | B67: UPI-VORUGANTI BHAVANI KA-BHAVANI.KARTHIK1@YBL-CNRB0000033-304188751411-ADV | C67: 0000304188751411 | D67: 12/10/25 | E67: 10000 | G67: 1029251
A68: 13/10/25 | B68: NEFT CR-YESB0000001-ONE 97 COMMUNICATIONS LIMITED SETTL-ROCKTAIL HOSPITALITY SERVICES-YESBN12025101301912154 | C68: YESBN12025101301912154 | D68: 13/10/25 | F68: 58079.77 | G68: 1087330.7
A69: 13/10/25 | B69: NEFT CR-UTIB0001506-PHONEPE LIMITED-PAYMENT AGGREGATOR ESCROW ACCOUNT-ROCKTAIL HOSPITALITY-UTIBN62025101304389126 | C69: UTIBN62025101304389126 | D69: 13/10/25 | F69: 1257.29 | G69: 1088588
A70: 13/10/25 | B70: NEFT CR-SCBL0036001-AMERICAN EXPRESS BANKING CORP-ROCKTAIL HOSPITALITY SERVICES-SCBLN52025101300559815 | C70: SCBLN52025101300559815 | D70: 13/10/25 | F70: 1335.14 | G70: 1089923.2
A71: 13/10/25 | B71: 42552394TERMINAL 1 CARDS SETTL. 13/10/25 | C71: 000000000000000 | D71: 13/10/25 | F71: 8984.17 | G71: 1098907.3
A72: 13/10/25 | B72: SALARIES-ROCKTAIL HOSPITALITY SERVICES DR - 57500000326520 - NEFT TRANSITORY ACCOUNT | C72: 0000000000000190 | D72: 13/10/25 | E72: 519134 | G72: 579773.34
A73: 13/10/25 | B73: SALARIES-ROCKTAIL HOSPITALITY SERVICES DR - 05122990000036 - SALARY TRANSITORY ACCOUNT - 512 | C73: 0000000000000189 | D73: 13/10/25 | E73: 164400 | G73: 415373.34
A74: 13/10/25 | B74: NEFT CR-CITI0000002-ETERNAL LIMITED-ROCKTAIL HOSPITALITY SERVICES-CITIN52025101338860064 | C74: CITIN52025101338860064 | D74: 13/10/25 | F74: 42965.13 | G74: 458338.47
A75: 13/10/25 | B75: IMPS-528618159341-NAGILLA HARIKRISHNA-BARB-XXXXXXXXXX0258-S | C75: 0000528618159341 | D75: 13/10/25 | E75: 200000 | G75: 258338.47
A76: 13/10/25 | B76: IMPS-528618149756-NAGILLA HARIKRISHNA-BARB-XXXXXXXXXX2369-S | C76: 0000528618149756 | D76: 13/10/25 | E76: 200000 | G76: 58338.47
A77: 14/10/25 | B77: NEFT CR-UTIB0005040-TAITAI CREAMERY (OPC) PRIVATE LIMITED-ROCKTAIL HOSPITALITY SERVICES-UTIBN62025101417058455 | C77: UTIBN62025101417058455 | D77: 14/10/25 | F77: 75600 | G77: 133938.47
A78: 14/10/25 | B78: NEFT CR-UTIB0005040-TAITAI CREAMERY (OPC) PRIVATE LIMITED-ROCKTAIL HOSPITALITY SERVICES-UTIBN62025101417091876 | C78: UTIBN62025101417091876 | D78: 14/10/25 | F78: 27381 | G78: 161319.47
A79: 14/10/25 | B79: 42552394TERMINAL 1 CARDS SETTL. 14/10/25 | C79: 000000000000000 | D79: 14/10/25 | F79: 1475.19 | G79: 162794.66
A80: 14/10/25 | B80: NEFT CR-YESB0000001-ONE 97 COMMUNICATIONS LIMITED SETTL-ROCKTAIL HOSPITALITY SERVICES-YESBN12025101402196356 | C80: YESBN12025101402196356 | D80: 14/10/25 | F80: 69263.45 | G80: 232058.11
A81: 14/10/25 | B81: UPI-AIRTEL-AIRTEL.PAYU@AXISBANK-UTIB0003156-112638492793-AIRTELPOSTPAIDBILL | C81: 0000112638492793 | D81: 14/10/25 | E81: 211.94 | G81: 231846.17
A82: 14/10/25 | B82: UPI-MAHANKALI ANIL-CHANTIANI@YBL-UTIB0001454-112640653774-CARD SWIPE | C82: 0000112640653774 | D82: 14/10/25 | E82: 25000 | G82: 206846.17
A83: 14/10/25 | B83: UPI-BHANWRA RAM-BHANWARJATCHOUDHARY251@OKSBI-SBIN0011306-112645088978-FURNITURE | C83: 0000112645088978 | D83: 14/10/25 | E83: 33984 | G83: 172862.17
A84: 14/10/25 | B84: NEFT CR-YESB0000001-SWIGGY LIMITED-ROCKTAIL HOSPITALITY SERVICES-YESBN12025101406117243 | C84: YESBN12025101406117243 | D84: 14/10/25 | F84: 22017.22 | G84: 194879.39
A85: 15/10/25 | B85: NEFT CR-YESB0000001-ONE 97 COMMUNICATIONS LIMITED SETTL-ROCKTAIL HOSPITALITY SERVICES-YESBN12025101501310623 | C85: YESBN12025101501310623 | D85: 15/10/25 | F85: 30576.54 | G85: 225455.93
A86: 15/10/25 | B86: NEFT CR-UTIB0001506-PHONEPE LIMITED-PAYMENT AGGREGATOR ESCROW ACCOUNT-ROCKTAIL HOSPITALITY-UTIBN62025101529095027 | C86: UTIBN62025101529095027 | D86: 15/10/25 | F86: 24849.71 | G86: 250305.64
A87: 15/10/25 | B87: 42552394TERMINAL 1 CARDS SETTL. 15/10/25 | C87: 000000000000000 | D87: 15/10/25 | F87: 1403.68 | G87: 251709.32
A88: 15/10/25 | B88: UPI-I ANIL KUMAR-ANILTIGER9966@YBL-SBIN0008025-112678952262-UPI | C88: 0000112678952262 | D88: 15/10/25 | E88: 16650 | G88: 235059.32
A89: 15/10/25 | B89: NEFT CR-CITI0000002-ETERNAL LIMITED-ROCKTAIL HOSPITALITY SERVICES-CITIN52025101539958263 | C89: CITIN52025101539958263 | D89: 15/10/25 | F89: 54593.95 | G89: 289653.27
A90: 15/10/25 | B90: ACH D- PINE LABS PVT LTD-9YBBY0K45VFHTZ | C90: 0000003300258297 | D90: 15/10/25 | E90: 408 | G90: 289245.27
A91: 15/10/25 | B91: NEFT CR-UTIB0000052-BUNDL TECHNOLOGIES PRIVATE LIMITED-ROCKTAIL HOSPITALITY SERVICES-UTIBN62025101531694003 | C91: UTIBN62025101531694003 | D91: 15/10/25 | F91: 26065.61 | G91: 315310.88
A92: 16/10/25 | B92: NEFT CR-YESB0000001-ONE 97 COMMUNICATIONS LIMITED SETTL-ROCKTAIL HOSPITALITY SERVICES-YESBN12025101601861177 | C92: YESBN12025101601861177 | D92: 16/10/25 | F92: 26861.69 | G92: 342172.57
A93: 16/10/25 | B93: 42552394TERMINAL 1 CARDS SETTL. 16/10/25 | C93: 000000000000000 | D93: 16/10/25 | F93: 6184.19 | G93: 348356.76
A94: 17/10/25 | B94: NEFT CR-YESB0000001-ONE 97 COMMUNICATIONS LIMITED SETTL-ROCKTAIL HOSPITALITY SERVICES-YESBN12025101700504184 | C94: YESBN12025101700504184 | D94: 17/10/25 | F94: 18765.99 | G94: 367122.75
A95: 17/10/25 | B95: 42552394TERMINAL 1 CARDS SETTL. 17/10/25 | C95: 000000000000000 | D95: 17/10/25 | F95: 14392.76 | G95: 381515.51
A96: 17/10/25 | B96: NEFT CR-YESB0000001-SWIGGY LIMITED-ROCKTAIL HOSPITALITY SERVICES-YESBN12025101705389357 | C96: YESBN12025101705389357 | D96: 17/10/25 | F96: 24683.09 | G96: 406198.6
A97: 17/10/25 | B97: UPI-BHANWRA RAM-BHANWARJATCHOUDHARY251@OKSBI-SBIN0011306-565615784026-FURNITURE FNF | C97: 0000565615784026 | D97: 17/10/25 | E97: 16200 | G97: 389998.6
A98: 17/10/25 | B98: UPI-SYED ANSAR ALI-9735000703@YBL-SBIN0002106-565609682617-VALET | C98: 0000565609682617 | D98: 17/10/25 | E98: 24000 | G98: 365998.6
A99: 18/10/25 | B99: NEFT CR-YESB0000001-ONE 97 COMMUNICATIONS LIMITED SETTL-ROCKTAIL HOSPITALITY SERVICES-YESBN12025101802308425 | C99: YESBN12025101802308425 | D99: 18/10/25 | F99: 25752 | G99: 391750.6
A100: 18/10/25 | B100: 42552394TERMINAL 1 CARDS SETTL. 18/10/25 | C100: 000000000000000 | D100: 18/10/25 | F100: 8270.74 | G100: 400021.34
A101: 19/10/25 | B101: NEFT CR-YESB0000001-ONE 97 COMMUNICATIONS LIMITED SETTL-ROCKTAIL HOSPITALITY SERVICES-YESBN12025101901417601 | C101: YESBN12025101901417601 | D101: 19/10/25 | F101: 56196.84 | G101: 456218.18
A102: 19/10/25 | B102: NEFT CR-UTIB0001506-PHONEPE LIMITED-PAYMENT AGGREGATOR ESCROW ACCOUNT-ROCKTAIL HOSPITALITY-UTIBN62025101981036322 | C102: UTIBN62025101981036322 | D102: 19/10/25 | F102: 129.18 | G102: 456347.36
A103: 19/10/25 | B103: 42552394TERMINAL 1 CARDS SETTL. 19/10/25 | C103: 000000000000000 | D103: 19/10/25 | F103: 12533.1 | G103: 468880.46
A104: 20/10/25 | B104: NEFT CR-YESB0000001-ONE 97 COMMUNICATIONS LIMITED SETTL-ROCKTAIL HOSPITALITY SERVICES-YESBN12025102002252754 | C104: YESBN12025102002252754 | D104: 20/10/25 | F104: 56832.39 | G104: 525712.85
A105: 20/10/25 | B105: NEFT CR-UTIB0001506-PHONEPE LIMITED-PAYMENT AGGREGATOR ESCROW ACCOUNT-ROCKTAIL HOSPITALITY-UTIBN62025102091922015 | C105: UTIBN62025102091922015 | D105: 20/10/25 | F105: 342.18 | G105: 526055.03
A106: 20/10/25 | B106: NEFT CR-SCBL0036001-AMERICAN EXPRESS BANKING CORP-ROCKTAIL HOSPITALITY SERVICES-SCBLN52025102000534540 | C106: SCBLN52025102000534540 | D106: 20/10/25 | F106: 2527.06 | G106: 528582.09
A107: 20/10/25 | B107: 42552394TERMINAL 1 CARDS SETTL. 20/10/25 | C107: 000000000000000 | D107: 20/10/25 | F107: 21406.83 | G107: 549988.92
A108: 20/10/25 | B108: UPI-TIRUMALA SOUNDS AND -GPAY-11193304431@OKBIZAXIS-UTIB0000553-112946107359-MELA TENT HOUSE | C108: 0000112946107359 | D108: 20/10/25 | E108: 30000 | G108: 519988.92
...

Sheet D1W1
O1: 458 | P1: 0 | Q1: 0 | R1: 0 | S1: 0 | T1: 0 | U1: 0 | V1: 0 | W1: 458 | X1: 0 | Y1: 0 | Z1: 0 | AA1: 0 | AB1: 0 | AC1: 0 | AD1: 0 | AE1: 0 | AF1: 0 | AG1: 0 | AH1: 0 | AI1: 0 | AJ1: 0 | AK1: 0 | AL1: 0 | AM1: 0 | AN1: 0 | AO1: 0 | AP1: 0 | AQ1: 0 | AR1: 0 | AS1: 0 | AT1: 0 | AU1: 0 | AV1: 290.64 | AW1: 290.64 | AX1: 0 | AY1: 0 | AZ1: 0 | BA1: 0 | BB1: 0
O2: 104252 | P2: 1200.5 | Q2: 0 | R2: 14429.4 | S2: 40 | T2: 0 | U2: 206.1 | V2: 4539.87 | W2: 95316.87 | X2: 90777 | Y2: 6591.34 | Z2: 17387.15 | AA2: 1753.39 | AB2: 19140.54 | AC2: 3445.24 | AD2: 0 | AE2: 90777 | AF2: 0 | AG2: 0 | AH2: 90.41 | AI2: 4541.27 | AJ2: -1.4 | AK2: 8076.92 | AL2: 0 | AM2: 0 | AN2: 0 | AO2: 0 | AP2: 0 | AQ2: 0 | AR2: 0 | AS2: 0 | AT2: 0 | AU2: 27217.46 | AV2: 0 | AW2: 68099.41 | AX2: 0 | AY2: 0 | AZ2: 0 | BA2: 0 | BB2: 0
O3: 123017.36 | P3: 1416.59 | Q3: 0 | R3: 17026.692 | S3: 47.2 | T3: 0 | U3: 243.198 | V3: 5357.0466 | W3: 112473.91 | X3: 107116.86 | Y3: 7777.7812 | Z3: 20516.837 | AA3: 2069.0002 | AB3: 22585.837 | AC3: 4065.3832 | AD3: 0 | AE3: 107116.86 | AF3: 0 | AG3: 0 | AH3: 106.6838 | AI3: 5358.6986 | AJ3: -1.652 | AK3: 9530.7656 | AL3: 0 | AM3: 0 | AN3: 0 | AO3: 0 | AP3: 0 | AQ3: 0 | AR3: 0 | AS3: 0 | AT3: 0 | AU3: 32116.603 | AV3: 0 | AW3: 80357.304 | AX3: 0 | AY3: 0 | AZ3: 0 | BA3: 0 | BB3: 0
O4: 104710 | P4: 1200.5 | Q4: 0 | R4: 14429.4 | S4: 40 | T4: 0 | U4: 206.1 | V4: 4539.87 | W4: 95774.87 | X4: 90777 | Y4: 6591.34 | Z4: 17387.15 | AA4: 1753.39 | AB4: 19140.54 | AC4: 3445.24 | AD4: 0 | AE4: 90777 | AF4: 0 | AG4: 0 | AH4: 90.41 | AI4: 4541.27 | AJ4: -1.4 | AK4: 8076.92 | AL4: 0 | AM4: 0 | AN4: 0 | AO4: 0 | AP4: 0 | AQ4: 0 | AR4: 0 | AS4: 0 | AT4: 0 | AU4: 27217.46 | AV4: 290.64 | AW4: 68390.05 | AX4: 0 | AY4: 0 | AZ4: 0 | BA4: 0 | BB4: 0
A5: S.No. | B5: Order ID | C5: Order Date | D5: Week No. | E5: Res. name | F5: Res. ID | G5: Discount Construct | H5: Mode of payment | I5: Order status (Delivered/ Cancelled/ Rejected) | J5: Cancellation policy (% Amount refunded back to restaurant partner) | K5: Cancellation/ Rejection Reason | L5: Cancelled/ Rejected State (Order status at the time it was cancelled/ rejected) | M5: Order type | N5: Delivery State code | O5: Subtotal (items total) | P5: Packaging charge | Q5: Delivery charge for restaurants on self logistics | R5: Restaurant discount [Promo] | S5: Restaurant Discount [BOGO, Freebies, Gold, Brand pack & others] | T5: Brand pack subscription fee | U5: Delivery charge discount / Relisting discount | V5: Total GST collected from customers | W5: Net order value [(1) + (2) + (3) - (4) - (5) + (6) - (7) + (8)] | X5: Commissionable value (excludes customer GST) [(A) + (7) - (8) - (6) - (3)] | Y5: Service fees % | Z5: Service fee [ (9) * (10) ] | AA5: Payment mechanism fee | AB5: Service fee & payment mechanism fees [(11) + (12)] | AC5: Taxes on service & payment mechanism fees (B) * 18% | AD5: Applicable amount for TCS | AE5: Applicable amount for 9(5) | AF5: Tax collected at source | AG5: TCS IGST amount | AH5: TDS 194O amount | AI5: GST paid by Zomato on behalf of restaurant - under section 9(5) | AJ5: GST to be paid by Restaurant partner to Govt. | AK5: Government charges [(13) + (16) + (17) + (18) + (19)] | AL5: Customer Compensation/Recoupment | AM5: Delivery Charges Recovery | AN5: Amount received in cash (on self delivery orders) | AO5: Credit note/(Debit Note) adjustment | AP5: Promo recovery adjustment | AQ5: Extra Inventory Ads and Misc. (order level deduction) | AR5: Brand loyalty points redemption | AS5: Express Order Fee | AT5: Other order-level deductions [(21) + (22) + (23) + (24) + (25) + (26) + (27) + (28)] | AU5: Net Deductions (B) + (C) + (D) | AV5: Net Additions (cancellation refund for cancelled orders/Tip for Kitchen Staff for delivered orders) | AW5: Order level Payout (A) - (E) + (F) | AX5: Settlement status | AY5: Settlement date | AZ5: Bank UTR | BA5: Unsettled Amount | BB5: Customer ID
A6: 1 | B6: 7523134878 | C6: 2025-12-01 00:00:33 | D6: 49 | E6: Sha Sha - Shandaar Shawarma | F6: 18557902 | G6: 30% off upto ₹75 (2025-06-25 - 2031-01-01) | H6: ONLINE | I6: DELIVERED | J6: NA | K6: NA | L6: NA | M6: O2 | N6: 36 | O6: 448 | P6: 3.5 | Q6: 0 | R6: 75 | S6: 0 | T6: 0 | U6: 0 | V6: 18.83 | W6: 395.33 | X6: 376.5 | Y6: 19 | Z6: 71.54 | AA6: 7.27 | AB6: 78.81 | AC6: 14.19 | AD6: 0 | AE6: 376.5 | AF6: 0 | AG6: 0 | AH6: 0.38 | AI6: 18.83 | AJ6: 0 | AK6: 33.4 | AL6: 0 | AM6: 0 | AN6: 0 | AO6: 0 | AP6: 0 | AQ6: 0 | AR6: 0 | AS6: 0 | AT6: 0 | AU6: 112.21 | AV6: 0 | AW6: 283.12 | AX6: settled | AY6: 2025-12-10 05:30:00 | AZ6: CITIN25668288188 | BA6: 0 | BB6: 3c7b18817b075ea2002b7e560ced4dffa0f4e085ec4005bca773c48f7ecbde7a
A7: 2 | B7: 7535704376 | C7: 2025-12-01 00:23:15 | D7: 49 | E7: Sha Sha - Shandaar Shawarma | F7: 18557902 | G7: 30% off upto ₹75 (2025-06-25 - 2031-01-01) | H7: ONLINE | I7: DELIVERED | J7: NA | K7: NA | L7: NA | M7: O2 | N7: 36 | O7: 229 | P7: 3.5 | Q7: 0 | R7: 68.7 | S7: 0 | T7: 0 | U7: 0 | V7: 8.19 | W7: 171.99 | X7: 163.8 | Y7: 19 | Z7: 31.12 | AA7: 3.16 | AB7: 34.28 | AC7: 6.17 | AD7: 0 | AE7: 163.8 | AF7: 0 | AG7: 0 | AH7: 0.16 | AI7: 8.2 | AJ7: -0.01 | AK7: 14.53 | AL7: 0 | AM7: 0 | AN7: 0 | AO7: 0 | AP7: 0 | AQ7: 0 | AR7: 0 | AS7: 0 | AT7: 0 | AU7: 48.81 | AV7: 0 | AW7: 123.18 | AX7: settled | AY7: 2025-12-10 05:30:00 | AZ7: CITIN25668288188 | BA7: 0 | BB7: 72ef68e4765975864e58a76f2c277ef47e4abe3d2a4231de22a49722992400a9
A8: 3 | B8: 7515231648 | C8: 2025-12-01 00:26:39 | D8: 49 | E8: Sha Sha - Shandaar Shawarma | F8: 18557902 | G8: 30% off upto ₹75 (2025-06-25 - 2031-01-01) | H8: ONLINE | I8: DELIVERED | J8: NA | K8: NA | L8: NA | M8: O2 | N8: 36 | O8: 229 | P8: 3.5 | Q8: 0 | R8: 68.7 | S8: 0 | T8: 0 | U8: 0 | V8: 8.19 | W8: 171.99 | X8: 163.8 | Y8: 19 | Z8: 31.12 | AA8: 3.16 | AB8: 34.28 | AC8: 6.17 | AD8: 0 | AE8: 163.8 | AF8: 0 | AG8: 0 | AH8: 0.16 | AI8: 8.2 | AJ8: -0.01 | AK8: 14.53 | AL8: 0 | AM8: 0 | AN8: 0 | AO8: 0 | AP8: 0 | AQ8: 0 | AR8: 0 | AS8: 0 | AT8: 0 | AU8: 48.81 | AV8: 0 | AW8: 123.18 | AX8: settled | AY8: 2025-12-10 05:30:00 | AZ8: CITIN25668288188 | BA8: 0 | BB8: bf47ae751ca8467d78b11b367090fc90a9657cc0227743ffc7f0da4a03dc419c
A9: 4 | B9: 7536593090 | C9: 2025-12-01 00:46:43 | D9: 49 | E9: Sha Sha - Shandaar Shawarma | F9: 18557902 | G9: NA | H9: ONLINE | I9: DELIVERED | J9: NA | K9: NA | L9: NA | M9: O2 | N9: 36 | O9: 1374 | P9: 3.5 | Q9: 0 | R9: 0 | S9: 0 | T9: 0 | U9: 0 | V9: 68.88 | W9: 1446.38 | X9: 1377.5 | Y9: 19 | Z9: 261.72 | AA9: 26.61 | AB9: 288.33 | AC9: 51.9 | AD9: 0 | AE9: 1377.5 | AF9: 0 | AG9: 0 | AH9: 1.38 | AI9: 68.88 | AJ9: 0 | AK9: 122.16 | AL9: 0 | AM9: 0 | AN9: 0 | AO9: 0 | AP9: 0 | AQ9: 0 | AR9: 0 | AS9: 0 | AT9: 0 | AU9: 410.49 | AV9: 0 | AW9: 1035.89 | AX9: settled | AY9: 2025-12-10 05:30:00 | AZ9: CITIN25668288188 | BA9: 0 | BB9: d29f71c19578460377108dfed6916d0c048aafa7508783f7a0ea419e858c7197
A10: 5 | B10: 7537381153 | C10: 2025-12-01 00:50:25 | D10: 49 | E10: Sha Sha - Shandaar Shawarma | F10: 18557902 | G10: NA | H10: ONLINE | I10: DELIVERED | J10: NA | K10: NA | L10: NA | M10: O2 | N10: 36 | O10: 229 | P10: 3.5 | Q10: 0 | R10: 0 | S10: 0 | T10: 0 | U10: 0 | V10: 11.63 | W10: 244.13 | X10: 232.5 | Y10: 19 | Z10: 44.18 | AA10: 4.49 | AB10: 48.67 | AC10: 8.76 | AD10: 0 | AE10: 232.5 | AF10: 0 | AG10: 0 | AH10: 0.23 | AI10: 11.63 | AJ10: 0 | AK10: 20.62 | AL10: 0 | AM10: 0 | AN10: 0 | AO10: 0 | AP10: 0 | AQ10: 0 | AR10: 0 | AS10: 0 | AT10: 0 | AU10: 69.29 | AV10: 0 | AW10: 174.84 | AX10: settled | AY10: 2025-12-10 05:30:00 | AZ10: CITIN25668288188 | BA10: 0 | BB10: 185cbfdb59e6f39207e7e37bcf84de6ee7f820b378e5e9a0aa67fd000cc1960e
A11: 6 | B11: 7537590612 | C11: 2025-12-01 01:12:05 | D11: 49 | E11: Sha Sha - Shandaar Shawarma | F11: 18557902 | G11: 30% off upto ₹75 (2025-06-25 - 2031-01-01) | H11: ONLINE | I11: DELIVERED | J11: NA | K11: NA | L11: NA | M11: O2 | N11: 36 | O11: 229 | P11: 3.5 | Q11: 0 | R11: 68.7 | S11: 0 | T11: 0 | U11: 0 | V11: 8.19 | W11: 171.99 | X11: 163.8 | Y11: 19 | Z11: 31.12 | AA11: 3.16 | AB11: 34.28 | AC11: 6.17 | AD11: 0 | AE11: 163.8 | AF11: 0 | AG11: 0 | AH11: 0.16 | AI11: 8.2 | AJ11: -0.01 | AK11: 14.53 | AL11: 0 | AM11: 0 | AN11: 0 | AO11: 0 | AP11: 0 | AQ11: 0 | AR11: 0 | AS11: 0 | AT11: 0 | AU11: 48.81 | AV11: 0 | AW11: 123.18 | AX11: settled | AY11: 2025-12-10 05:30:00 | AZ11: CITIN25668288188 | BA11: 0 | BB11: a1949b2b3697426151581d6d1cf55e46dcc4a4479f63a994d6321a7e42eb5f24
A12: 7 | B12: 7531805344 | C12: 2025-12-01 01:48:54 | D12: 49 | E12: Sha Sha - Shandaar Shawarma | F12: 18557902 | G12: NA | H12: ONLINE | I12: DELIVERED | J12: NA | K12: NA | L12: NA | M12: O2 | N12: 36 | O12: 229 | P12: 3.5 | Q12: 0 | R12: 0 | S12: 0 | T12: 0 | U12: 0 | V12: 11.63 | W12: 244.13 | X12: 232.5 | Y12: 19 | Z12: 44.18 | AA12: 4.49 | AB12: 48.67 | AC12: 8.76 | AD12: 0 | AE12: 232.5 | AF12: 0 | AG12: 0 | AH12: 0.23 | AI12: 11.63 | AJ12: 0 | AK12: 20.62 | AL12: 0 | AM12: 0 | AN12: 0 | AO12: 0 | AP12: 0 | AQ12: 0 | AR12: 0 | AS12: 0 | AT12: 0 | AU12: 69.29 | AV12: 0 | AW12: 174.84 | AX12: settled | AY12: 2025-12-10 05:30:00 | AZ12: CITIN25668288188 | BA12: 0 | BB12: 78416b40b01f30cd5f938dae60baa5742d9c87092ebf3d82e2069986f7f51b14
A13: 8 | B13: 7536925636 | C13: 2025-12-01 01:53:13 | D13: 49 | E13: Sha Sha - Shandaar Shawarma | F13: 18557902 | G13: 30% off upto ₹75 (2025-06-25 - 2031-01-01) | H13: ONLINE | I13: DELIVERED | J13: NA | K13: NA | L13: NA | M13: O2 | N13: 36 | O13: 229 | P13: 3.5 | Q13: 0 | R13: 68.7 | S13: 0 | T13: 0 | U13: 0 | V13: 8.19 | W13: 171.99 | X13: 163.8 | Y13: 19 | Z13: 31.12 | AA13: 3.16 | AB13: 34.28 | AC13: 6.17 | AD13: 0 | AE13: 163.8 | AF13: 0 | AG13: 0 | AH13: 0.16 | AI13: 8.2 | AJ13: -0.01 | AK13: 14.53 | AL13: 0 | AM13: 0 | AN13: 0 | AO13: 0 | AP13: 0 | AQ13: 0 | AR13: 0 | AS13: 0 | AT13: 0 | AU13: 48.81 | AV13: 0 | AW13: 123.18 | AX13: settled | AY13: 2025-12-10 05:30:00 | AZ13: CITIN25668288188 | BA13: 0 | BB13: f965c705b5c4cac429aaa12fa644d2d6b611f69f55ef841ad3fea42d208be5e0
A14: 9 | B14: 7528565199 | C14: 2025-12-01 02:14:10 | D14: 49 | E14: Sha Sha - Shandaar Shawarma | F14: 18557902 | G14: 30% off upto ₹75 (2025-06-25 - 2031-01-01) | H14: ONLINE | I14: DELIVERED | J14: NA | K14: NA | L14: NA | M14: O2 | N14: 36 | O14: 229 | P14: 3.5 | Q14: 0 | R14: 68.7 | S14: 0 | T14: 0 | U14: 0 | V14: 8.19 | W14: 171.99 | X14: 163.8 | Y14: 19 | Z14: 31.12 | AA14: 3.16 | AB14: 34.28 | AC14: 6.17 | AD14: 0 | AE14: 163.8 | AF14: 0 | AG14: 0 | AH14: 0.16 | AI14: 8.2 | AJ14: -0.01 | AK14: 14.53 | AL14: 0 | AM14: 0 | AN14: 0 | AO14: 0 | AP14: 0 | AQ14: 0 | AR14: 0 | AS14: 0 | AT14: 0 | AU14: 48.81 | AV14: 0 | AW14: 123.18 | AX14: settled | AY14: 2025-12-10 05:30:00 | AZ14: CITIN25668288188 | BA14: 0 | BB14: db8cc3d58cc23f5e9e88ae7c8040f0ad24d725714a290a17d6822bd2564c992a
A15: 10 | B15: 7532984205 | C15: 2025-12-01 02:22:59 | D15: 49 | E15: Sha Sha - Shandaar Shawarma | F15: 18557902 | G15: 30% off upto ₹75 (2025-06-25 - 2031-01-01) | H15: ONLINE | I15: DELIVERED | J15: NA | K15: NA | L15: NA | M15: O2 | N15: 36 | O15: 229 | P15: 3.5 | Q15: 0 | R15: 68.7 | S15: 0 | T15: 0 | U15: 0 | V15: 8.19 | W15: 171.99 | X15: 163.8 | Y15: 19 | Z15: 31.12 | AA15: 3.16 | AB15: 34.28 | AC15: 6.17 | AD15: 0 | AE15: 163.8 | AF15: 0 | AG15: 0 | AH15: 0.16 | AI15: 8.2 | AJ15: -0.01 | AK15: 14.53 | AL15: 0 | AM15: 0 | AN15: 0 | AO15: 0 | AP15: 0 | AQ15: 0 | AR15: 0 | AS15: 0 | AT15: 0 | AU15: 48.81 | AV15: 0 | AW15: 123.18 | AX15: settled | AY15: 2025-12-10 05:30:00 | AZ15: CITIN25668288188 | BA15: 0 | BB15: a4a70e0e977a73da377b4f40475eaf264e2652e623d22ae3ef862491d5035f2f
A16: 11 | B16: 7536164921 | C16: 2025-12-01 02:27:36 | D16: 49 | E16: Sha Sha - Shandaar Shawarma | F16: 18557902 | G16: 30% off upto ₹75 (2025-06-25 - 2031-01-01) | H16: ONLINE | I16: DELIVERED | J16: NA | K16: NA | L16: NA | M16: O2 | N16: 36 | O16: 229 | P16: 3.5 | Q16: 0 | R16: 68.7 | S16: 0 | T16: 0 | U16: 0 | V16: 8.19 | W16: 171.99 | X16: 163.8 | Y16: 19 | Z16: 31.12 | AA16: 3.16 | AB16: 34.28 | AC16: 6.17 | AD16: 0 | AE16: 163.8 | AF16: 0 | AG16: 0 | AH16: 0.16 | AI16: 8.2 | AJ16: -0.01 | AK16: 14.53 | AL16: 0 | AM16: 0 | AN16: 0 | AO16: 0 | AP16: 0 | AQ16: 0 | AR16: 0 | AS16: 0 | AT16: 0 | AU16: 48.81 | AV16: 0 | AW16: 123.18 | AX16: settled | AY16: 2025-12-10 05:30:00 | AZ16: CITIN25668288188 | BA16: 0 | BB16: 218632630ad9fc43ae206c2932d5bf7ccd42ed4de1d3e430540e219cc9b72fc3
A17: 12 | B17: 7535091172 | C17: 2025-12-01 02:41:38 | D17: 49 | E17: Sha Sha - Shandaar Shawarma | F17: 18557902 | G17: 30% off upto ₹75 (2025-06-25 - 2031-01-01) | H17: ONLINE | I17: DELIVERED | J17: NA | K17: NA | L17: NA | M17: O2 | N17: 36 | O17: 229 | P17: 3.5 | Q17: 0 | R17: 68.7 | S17: 0 | T17: 0 | U17: 0 | V17: 8.19 | W17: 171.99 | X17: 163.8 | Y17: 19 | Z17: 31.12 | AA17: 3.16 | AB17: 34.28 | AC17: 6.17 | AD17: 0 | AE17: 163.8 | AF17: 0 | AG17: 0 | AH17: 0.16 | AI17: 8.2 | AJ17: -0.01 | AK17: 14.53 | AL17: 0 | AM17: 0 | AN17: 0 | AO17: 0 | AP17: 0 | AQ17: 0 | AR17: 0 | AS17: 0 | AT17: 0 | AU17: 48.81 | AV17: 0 | AW17: 123.18 | AX17: settled | AY17: 2025-12-10 05:30:00 | AZ17: CITIN25668288188 | BA17: 0 | BB17: 38165d7f703a46752ffe1a82bd95152a4fa7b2821454b1c805acb19a8e4bbb11
... A350: 345 | B350: 7552801794 | C350: 2025-12-07 23:36:17 | D350: 49 | E350: Sha Sha - Shandaar Shawarma | F350: 18557902 | G350: 30% off upto ₹75 (2025-06-25 - 2031-01-01) | H350: ONLINE | I350: DELIVERED | J350: NA | K350: NA | L350: NA | M350: O2 | N350: 36 | O350: 345 | P350: 3.5 | Q350: 0 | R350: 75 | S350: 0 | T350: 0 | U350: 0 | V350: 13.68 | W350: 287.18 | X350: 273.5 | Y350: 19 | Z350: 51.96 | AA350: 5.28 | AB350: 57.24 | AC350: 10.3 | AD350: 0 | AE350: 273.5 | AF350: 0 | AG350: 0 | AH350: 0.27 | AI350: 13.68 | AJ350: 0 | AK350: 24.25 | AL350: 0 | AM350: 0 | AN350: 0 | AO350: 0 | AP350: 0 | AQ350: 0 | AR350: 0 | AS350: 0 | AT350: 0 | AU350: 81.49 | AV350: 0 | AW350: 205.69 | AX350: settled | AY350: 2025-12-10 05:30:00 | AZ350: CITIN25668288188 | BA350: 0 | BB350: 97b4133bde4eb0767e9ce68171387ff49f31d258169b1f78ae8f5981ef069b25

Sheet D1W2
O1: 667 | P1: 0 | Q1: 0 | R1: 0 | S1: 0 | T1: 0 | U1: 0 | V1: 0 | W1: 667 | X1: 0 | Y1: 0 | Z1: 0 | AA1: 0 | AB1: 0 | AC1: 0 | AD1: 0 | AE1: 0 | AF1: 0 | AG1: 0 | AH1: 0 | AI1: 0 | AJ1: 0 | AK1: 0 | AL1: 0 | AM1: 0 | AN1: 0 | AO1: 0 | AP1: 0 | AQ1: 0 | AR1: 0 | AS1: 0 | AT1: 0 | AU1: 0 | AV1: 398.78 | AW1: 398.78 | AX1: 0 | AY1: 0 | AZ1: 0 | BA1: 0 | BB1: 0
O2: 98939 | P2: 1193.5 | Q2: 0 | R2: 17483.1 | S2: 0 | T2: 0 | U2: 197.1 | V2: 4123.41 | W2: 86575.71 | X2: 82452.3 | Y2: 6553.34 | Z2: 15799.22 | AA2: 1592.43 | AB2: 17391.65 | AC2: 3130.46 | AD2: 0 | AE2: 82452.3 | AF2: 0 | AG2: 0 | AH2: 82.09 | AI2: 4125.24 | AJ2: -1.83 | AK2: 7337.79 | AL2: 0 | AM2: 0 | AN2: 0 | AO2: 0 | AP2: 0 | AQ2: 0 | AR2: 0 | AS2: 0 | AT2: 0 | AU2: 24729.44 | AV2: 0 | AW2: 61846.27 | AX2: 0 | AY2: 0 | AZ2: 0 | BA2: 0 | BB2: 0
O3: 116748.02 | P3: 1408.33 | Q3: 0 | R3: 20630.058 | S3: 0 | T3: 0 | U3: 232.578 | V3: 4865.6238 | W3: 102159.34 | X3: 97293.714 | Y3: 7732.9412 | Z3: 18643.08 | AA3: 1879.0674 | AB3: 20522.147 | AC3: 3693.9428 | AD3: 0 | AE3: 97293.714 | AF3: 0 | AG3: 0 | AH3: 96.8662 | AI3: 4867.7832 | AJ3: -2.1594 | AK3: 8658.5922 | AL3: 0 | AM3: 0 | AN3: 0 | AO3: 0 | AP3: 0 | AQ3: 0 | AR3: 0 | AS3: 0 | AT3: 0 | AU3: 29180.739 | AV3: 0 | AW3: 72978.599 | AX3: 0 | AY3: 0 | AZ3: 0 | BA3: 0 | BB3: 0
O4: 99606 | P4: 1193.5 | Q4: 0 | R4: 17483.1 | S4: 0 | T4: 0 | U4: 197.1 | V4: 4123.41 | W4: 87242.71 | X4: 82452.3 | Y4: 6553.34 | Z4: 15799.22 | AA4: 1592.43 | AB4: 17391.65 | AC4: 3130.46 | AD4: 0 | AE4: 82452.3 | AF4: 0 | AG4: 0 | AH4: 82.09 | AI4: 4125.24 | AJ4: -1.83 | AK4: 7337.79 | AL4: 0 | AM4: 0 | AN4: 0 | AO4: 0 | AP4: 0 | AQ4: 0 | AR4: 0 | AS4: 0 | AT4: 0 | AU4: 24729.44 | AV4: 398.78 | AW4: 62245.05 | AX4: 0 | AY4: 0 | AZ4: 0 | BA4: 0 | BB4: 0
A5: S.No. | B5: Order ID | C5: Order Date | D5: Week No. | E5: Res. name | F5: Res. ID | G5: Discount Construct | H5: Mode of payment | I5: Order status (Delivered/ Cancelled/ Rejected) | J5: Cancellation policy (% Amount refunded back to restaurant partner) | K5: Cancellation/ Rejection Reason | L5: Cancelled/ Rejected State (Order status at the time it was cancelled/ rejected) | M5: Order type | N5: Delivery State code | O5: Subtotal (items total) | P5: Packaging charge | Q5: Delivery charge for restaurants on self logistics | R5: Restaurant discount [Promo] | S5: Restaurant Discount [BOGO, Freebies, Gold, Brand pack & others] | T5: Brand pack subscription fee | U5: Delivery charge discount / Relisting discount | V5: Total GST collected from customers | W5: Net order value [(1) + (2) + (3) - (4) - (5) + (6) - (7) + (8)] | X5: Commissionable value (excludes customer GST) [(A) + (7) - (8) - (6) - (3)] | Y5: Service fees % | Z5: Service fee [ (9) * (10) ] | AA5: Payment mechanism fee | AB5: Service fee & payment mechanism fees [(11) + (12)] | AC5: Taxes on service & payment mechanism fees (B) * 18% | AD5: Applicable amount for TCS | AE5: Applicable amount for 9(5) | AF5: Tax collected at source | AG5: TCS IGST amount | AH5: TDS 194O amount | AI5: GST paid by Zomato on behalf of restaurant - under section 9(5) | AJ5: GST to be paid by Restaurant partner to Govt. | AK5: Government charges [(13) + (16) + (17) + (18) + (19)] | AL5: Customer Compensation/Recoupment | AM5: Delivery Charges Recovery | AN5: Amount received in cash (on self delivery orders) | AO5: Credit note/(Debit Note) adjustment | AP5: Promo recovery adjustment | AQ5: Extra Inventory Ads and Misc. (order level deduction) | AR5: Brand loyalty points redemption | AS5: Express Order Fee | AT5: Other order-level deductions [(21) + (22) + (23) + (24) + (25) + (26) + (27) + (28)] | AU5: Net Deductions (B) + (C) + (D) | AV5: Net Additions (cancellation refund for cancelled orders/Tip for Kitchen Staff for delivered orders) | AW5: Order level Payout (A) - (E) + (F) | AX5: Settlement status | AY5: Settlement date | AZ5: Bank UTR | BA5: Unsettled Amount | BB5: Customer ID
A6: 346 | B6: 7556082492 | C6: 2025-12-08 00:04:08 | D6: 50 | E6: Sha Sha - Shandaar Shawarma | F6: 18557902 | G6: 30% off upto ₹75 (2025-06-25 - 2031-01-01) | H6: ONLINE | I6: CANCELLED | J6: 100% | K6: Customer cancellation because they do not require order anymore | L6: Order picked up by rider | M6: O2 | N6: NA | O6: 438 | P6: 0 | Q6: 0 | R6: 0 | S6: 0 | T6: 0 | U6: 0 | V6: 0 | W6: 438 | X6: 0 | Y6: 0 | Z6: 0 | AA6: 0 | AB6: 0 | AC6: 0 | AD6: 0 | AE6: 0 | AF6: 0 | AG6: 0 | AH6: 0 | AI6: 0 | AJ6: 0 | AK6: 0 | AL6: 0 | AM6: 0 | AN6: 0 | AO6: 0 | AP6: 0 | AQ6: 0 | AR6: 0 | AS6: 0 | AT6: 0 | AU6: 0 | AV6: 275.6 | AW6: 275.6 | AX6: settled | AY6: 2025-12-17 05:30:00 | AZ6: CITIN25671113204 | BA6: 0 | BB6: NA
A7: 347 | B7: 7560132576 | C7: 2025-12-08 00:33:52 | D7: 50 | E7: Sha Sha - Shandaar Shawarma | F7: 18557902 | G7: NA | H7: ONLINE | I7: DELIVERED | J7: NA | K7: NA | L7: NA | M7: O2 | N7: 36 | O7: 584 | P7: 3.5 | Q7: 0 | R7: 0 | S7: 0 | T7: 0 | U7: 0 | V7: 29.38 | W7: 616.88 | X7: 587.5 | Y7: 19 | Z7: 111.62 | AA7: 11.35 | AB7: 122.97 | AC7: 22.13 | AD7: 0 | AE7: 587.5 | AF7: 0 | AG7: 0 | AH7: 0.59 | AI7: 29.38 | AJ7: 0 | AK7: 52.1 | AL7: 0 | AM7: 0 | AN7: 0 | AO7: 0 | AP7: 0 | AQ7: 0 | AR7: 0 | AS7: 0 | AT7: 0 | AU7: 175.07 | AV7: 0 | AW7: 441.81 | AX7: settled | AY7: 2025-12-17 05:30:00 | AZ7: CITIN25671113204 | BA7: 0 | BB7: 7b10bea75fb866894fe5984067f405026bfaa855061423ff4f1faabc6928ec68
A8: 348 | B8: 7560658992 | C8: 2025-12-08 00:39:57 | D8: 50 | E8: Sha Sha - Shandaar Shawarma | F8: 18557902 | G8: 30% off upto ₹75 (2025-06-25 - 2031-01-01) | H8: ONLINE | I8: DELIVERED | J8: NA | K8: NA | L8: NA | M8: O2 | N8: 36 | O8: 219 | P8: 3.5 | Q8: 0 | R8: 65.7 | S8: 0 | T8: 0 | U8: 0 | V8: 7.84 | W8: 164.64 | X8: 156.8 | Y8: 19 | Z8: 29.79 | AA8: 3.03 | AB8: 32.82 | AC8: 5.91 | AD8: 0 | AE8: 156.8 | AF8: 0 | AG8: 0 | AH8: 0.16 | AI8: 7.85 | AJ8: -0.01 | AK8: 13.92 | AL8: 0 | AM8: 0 | AN8: 0 | AO8: 0 | AP8: 0 | AQ8: 0 | AR8: 0 | AS8: 0 | AT8: 0 | AU8: 46.74 | AV8: 0 | AW8: 117.9 | AX8: settled | AY8: 2025-12-17 05:30:00 | AZ8: CITIN25671113204 | BA8: 0 | BB8: 4fca2ec57d8ed1589c858b823ae6864d487a9ecb476064b919cc80188e494dea
A9: 349 | B9: 7556658647 | C9: 2025-12-08 00:46:08 | D9: 50 | E9: Sha Sha - Shandaar Shawarma | F9: 18557902 | G9: NA | H9: ONLINE | I9: DELIVERED | J9: NA | K9: NA | L9: NA | M9: RELISTING | N9: 36 | O9: 438 | P9: 0 | Q9: 0 | R9: 0 | S9: 0 | T9: 0 | U9: 197.1 | V9: 12.05 | W9: 252.95 | X9: 240.9 | Y9: 74.34 | Z9: 179.09 | AA9: 4.65 | AB9: 183.74 | AC9: 33.08 | AD9: 0 | AE9: 240.9 | AF9: 0 | AG9: 0 | AH9: 0.24 | AI9: 12.05 | AJ9: 0 | AK9: 45.37 | AL9: 0 | AM9: 0 | AN9: 0 | AO9: 0 | AP9: 0 | AQ9: 0 | AR9: 0 | AS9: 0 | AT9: 0 | AU9: 229.11 | AV9: 0 | AW9: 23.84 | AX9: settled | AY9: 2025-12-17 05:30:00 | AZ9: CITIN25671113204 | BA9: 0 | BB9: a791fe3bf339d52c2b1ce45adf11573f69cc8e548489862a776aa2b9bbfdaf35
A10: 350 | B10: 7546175253 | C10: 2025-12-08 00:48:29 | D10: 50 | E10: Sha Sha - Shandaar Shawarma | F10: 18557902 | G10: NA | H10: ONLINE | I10: DELIVERED | J10: NA | K10: NA | L10: NA | M10: O2 | N10: 36 | O10: 229 | P10: 3.5 | Q10: 0 | R10: 0 | S10: 0 | T10: 0 | U10: 0 | V10: 11.63 | W10: 244.13 | X10: 232.5 | Y10: 19 | Z10: 44.18 | AA10: 4.49 | AB10: 48.67 | AC10: 8.76 | AD10: 0 | AE10: 232.5 | AF10: 0 | AG10: 0 | AH10: 0.23 | AI10: 11.63 | AJ10: 0 | AK10: 20.62 | AL10: 0 | AM10: 0 | AN10: 0 | AO10: 0 | AP10: 0 | AQ10: 0 | AR10: 0 | AS10: 0 | AT10: 0 | AU10: 69.29 | AV10: 0 | AW10: 174.84 | AX10: settled | AY10: 2025-12-17 05:30:00 | AZ10: CITIN25671113204 | BA10: 0 | BB10: dbfa5470f7ee44cad8b2e759129c93b51031c401a3a209593c35f6a6f2353a71
A11: 351 | B11: 7559932296 | C11: 2025-12-08 00:50:31 | D11: 50 | E11: Sha Sha - Shandaar Shawarma | F11: 18557902 | G11: 30% off upto ₹75 (2025-06-25 - 2031-01-01) | H11: ONLINE | I11: DELIVERED | J11: NA | K11: NA | L11: NA | M11: O2 | N11: 36 | O11: 229 | P11: 3.5 | Q11: 0 | R11: 68.7 | S11: 0 | T11: 0 | U11: 0 | V11: 8.19 | W11: 171.99 | X11: 163.8 | Y11: 19 | Z11: 31.12 | AA11: 3.16 | AB11: 34.28 | AC11: 6.17 | AD11: 0 | AE11: 163.8 | AF11: 0 | AG11: 0 | AH11: 0.16 | AI11: 8.2 | AJ11: -0.01 | AK11: 14.53 | AL11: 0 | AM11: 0 | AN11: 0 | AO11: 0 | AP11: 0 | AQ11: 0 | AR11: 0 | AS11: 0 | AT11: 0 | AU11: 48.81 | AV11: 0 | AW11: 123.18 | AX11: settled | AY11: 2025-12-17 05:30:00 | AZ11: CITIN25671113204 | BA11: 0 | BB11: cced21294a761e8e520d3f723af908adf3bedcfdce1f6051f03037bf5aa364a8
A12: 352 | B12: 7558559359 | C12: 2025-12-08 00:54:05 | D12: 50 | E12: Sha Sha - Shandaar Shawarma | F12: 18557902 | G12: NA | H12: ONLINE | I12: DELIVERED | J12: NA | K12: NA | L12: NA | M12: O2 | N12: 36 | O12: 229 | P12: 3.5 | Q12: 0 | R12: 0 | S12: 0 | T12: 0 | U12: 0 | V12: 11.63 | W12: 244.13 | X12: 232.5 | Y12: 19 | Z12: 44.18 | AA12: 4.49 | AB12: 48.67 | AC12: 8.76 | AD12: 0 | AE12: 232.5 | AF12: 0 | AG12: 0 | AH12: 0.23 | AI12: 11.63 | AJ12: 0 | AK12: 20.62 | AL12: 0 | AM12: 0 | AN12: 0 | AO12: 0 | AP12: 0 | AQ12: 0 | AR12: 0 | AS12: 0 | AT12: 0 | AU12: 69.29 | AV12: 0 | AW12: 174.84 | AX12: settled | AY12: 2025-12-17 05:30:00 | AZ12: CITIN25671113204 | BA12: 0 | BB12: c209c9b0746dcd6f8b312a760d64666ff4674f55242acca903d5ea4920a45d3a
A13: 353 | B13: 7561177524 | C13: 2025-12-08 01:16:47 | D13: 50 | E13: Sha Sha - Shandaar Shawarma | F13: 18557902 | G13: NA | H13: ONLINE | I13: DELIVERED | J13: NA | K13: NA | L13: NA | M13: O2 | N13: 36 | O13: 229 | P13: 3.5 | Q13: 0 | R13: 0 | S13: 0 | T13: 0 | U13: 0 | V13: 11.63 | W13: 244.13 | X13: 232.5 | Y13: 19 | Z13: 44.18 | AA13: 4.49 | AB13: 48.67 | AC13: 8.76 | AD13: 0 | AE13: 232.5 | AF13: 0 | AG13: 0 | AH13: 0.23 | AI13: 11.63 | AJ13: 0 | AK13: 20.62 | AL13: 0 | AM13: 0 | AN13: 0 | AO13: 0 | AP13: 0 | AQ13: 0 | AR13: 0 | AS13: 0 | AT13: 0 | AU13: 69.29 | AV13: 0 | AW13: 174.84 | AX13: settled | AY13: 2025-12-17 05:30:00 | AZ13: CITIN25671113204 | BA13: 0 | BB13: 6f50f06ce71dfc68133b8c94b871d26740019b5b19b1f5f7e668e511436cf3f7
A14: 354 | B14: 7555967751 | C14: 2025-12-08 01:22:39 | D14: 50 | E14: Sha Sha - Shandaar Shawarma | F14: 18557902 | G14: 30% off upto ₹75 (2025-06-25 - 2031-01-01) | H14: ONLINE | I14: DELIVERED | J14: NA | K14: NA | L14: NA | M14: O2 | N14: 36 | O14: 229 | P14: 3.5 | Q14: 0 | R14: 68.7 | S14: 0 | T14: 0 | U14: 0 | V14: 8.19 | W14: 171.99 | X14: 163.8 | Y14: 19 | Z14: 31.12 | AA14: 3.16 | AB14: 34.28 | AC14: 6.17 | AD14: 0 | AE14: 163.8 | AF14: 0 | AG14: 0 | AH14: 0.16 | AI14: 8.2 | AJ14: -0.01 | AK14: 14.53 | AL14: 0 | AM14: 0 | AN14: 0 | AO14: 0 | AP14: 0 | AQ14: 0 | AR14: 0 | AS14: 0 | AT14: 0 | AU14: 48.81 | AV14: 0 | AW14: 123.18 | AX14: settled | AY14: 2025-12-17 05:30:00 | AZ14: CITIN25671113204 | BA14: 0 | BB14: 8a33ea1d632a0474a585dab42902dce8d7d1418959cb3a7aa7bd7e8610233f0c
A15: 355 | B15: 7556896494 | C15: 2025-12-08 01:40:47 | D15: 50 | E15: Sha Sha - Shandaar Shawarma | F15: 18557902 | G15: NA | H15: ONLINE | I15: DELIVERED | J15: NA | K15: NA | L15: NA | M15: O2 | N15: 36 | O15: 229 | P15: 3.5 | Q15: 0 | R15: 0 | S15: 0 | T15: 0 | U15: 0 | V15: 11.63 | W15: 244.13 | X15: 232.5 | Y15: 19 | Z15: 44.18 | AA15: 4.49 | AB15: 48.67 | AC15: 8.76 | AD15: 0 | AE15: 232.5 | AF15: 0 | AG15: 0 | AH15: 0.23 | AI15: 11.63 | AJ15: 0 | AK15: 20.62 | AL15: 0 | AM15: 0 | AN15: 0 | AO15: 0 | AP15: 0 | AQ15: 0 | AR15: 0 | AS15: 0 | AT15: 0 | AU15: 69.29 | AV15: 0 | AW15: 174.84 | AX15: settled | AY15: 2025-12-17 05:30:00 | AZ15: CITIN25671113204 | BA15: 0 | BB15: 85b84745d698a9cb2f27c8c6690d18b8b2e4e4f21bbaa9a2d74ae81c62f0b34b
A16: 356 | B16: 7561216624 | C16: 2025-12-08 01:41:40 | D16: 50 | E16: Sha Sha - Shandaar Shawarma | F16: 18557902 | G16: 30% off upto ₹75 (2025-06-25 - 2031-01-01) | H16: ONLINE | I16: CANCELLED | J16: 100% | K16: Delivery partner cancellation | L16: Order picked up by rider | M16: O2 | N16: NA | O16: 229 | P16: 0 | Q16: 0 | R16: 0 | S16: 0 | T16: 0 | U16: 0 | V16: 0 | W16: 229 | X16: 0 | Y16: 0 | Z16: 0 | AA16: 0 | AB16: 0 | AC16: 0 | AD16: 0 | AE16: 0 | AF16: 0 | AG16: 0 | AH16: 0 | AI16: 0 | AJ16: 0 | AK16: 0 | AL16: 0 | AM16: 0 | AN16: 0 | AO16: 0 | AP16: 0 | AQ16: 0 | AR16: 0 | AS16: 0 | AT16: 0 | AU16: 0 | AV16: 123.18 | AW16: 123.18 | AX16: settled | AY16: 2025-12-17 05:30:00 | AZ16: CITIN25671113204 | BA16: 0 | BB16: NA
A17: 357 | B17: 7559484296 | C17: 2025-12-08 01:44:58 | D17: 50 | E17: Sha Sha - Shandaar Shawarma | F17: 18557902 | G17: 30% off upto ₹75 (2025-06-25 - 2031-01-01) | H17: ONLINE | I17: DELIVERED | J17: NA | K17: NA | L17: NA | M17: O2 | N17: 36 | O17: 458 | P17: 3.5 | Q17: 0 | R17: 75 | S17: 0 | T17: 0 | U17: 0 | V17: 19.33 | W17: 405.83 | X17: 386.5 | Y17: 19 | Z17: 73.44 | AA17: 7.47 | AB17: 80.91 | AC17: 14.56 | AD17: 0 | AE17: 386.5 | AF17: 0 | AG17: 0 | AH17: 0.39 | AI17: 19.33 | AJ17: 0 | AK17: 34.28 | AL17: 0 | AM17: 0 | AN17: 0 | AO17: 0 | AP17: 0 | AQ17: 0 | AR17: 0 | AS17: 0 | AT17: 0 | AU17: 115.19 | AV17: 0 | AW17: 290.64 | AX17: settled | AY17: 2025-12-17 05:30:00 | AZ17: CITIN25671113204 | BA17: 0 | BB17: f33bc7a038d5ab2635591df874bba2a8ff12c5b20565add1789ffe65ed9bd3ad
... A349: 689 | B349: 7584900397 | C349: 2025-12-14 23:43:40 | D349: 50 | E349: Sha Sha - Shandaar Shawarma | F349: 18557902 | G349: 30% off upto ₹75 (2025-06-25 - 2031-01-01) | H349: ONLINE | I349: DELIVERED | J349: NA | K349: NA | L349: NA | M349: O2 | N349: 36 | O349: 367 | P349: 3.5 | Q349: 0 | R349: 75 | S349: 0 | T349: 0 | U349: 0 | V349: 14.78 | W349: 310.28 | X349: 295.5 | Y349: 19 | Z349: 56.14 | AA349: 5.71 | AB349: 61.85 | AC349: 11.14 | AD349: 0 | AE349: 295.5 | AF349: 0 | AG349: 0 | AH349: 0.3 | AI349: 14.78 | AJ349: 0 | AK349: 26.22 | AL349: 0 | AM349: 0 | AN349: 0 | AO349: 0 | AP349: 0 | AQ349: 0 | AR349: 0 | AS349: 0 | AT349: 0 | AU349: 88.07 | AV349: 0 | AW349: 222.21 | AX349: settled | AY349: 2025-12-17 05:30:00 | AZ349: CITIN25671113204 | BA349: 0 | BB349: b0153e97325404c7b58a46be3cee32d0623a2bc45b2060c6376b838bd794e016

Sheet D1W3
O1: 229 | P1: 0 | Q1: 0 | R1: 0 | S1: 0 | T1: 0 | U1: 0 | V1: 0 | W1: 229 | X1: 0 | Y1: 0 | Z1: 0 | AA1: 0 | AB1: 0 | AC1: 0 | AD1: 0 | AE1: 0 | AF1: 0 | AG1: 0 | AH1: 0 | AI1: 0 | AJ1: 0 | AK1: 0 | AL1: 0 | AM1: 0 | AN1: 0 | AO1: 0 | AP1: 0 | AQ1: 0 | AR1: 0 | AS1: 0 | AT1: 0 | AU1: 0 | AV1: 174.84 | AW1: 174.84 | AX1: 0 | AY1: 0 | AZ1: 0 | BA1: 0 | BB1: 0
O2: 98038 | P2: 1204 | Q2: 0 | R2: 16947.3 | S2: 0 | T2: 0 | U2: 0 | V2: 4115.61 | W2: 86410.31 | X2: 82294.7 | Y2: 6610.34 | Z2: 15762.9 | AA2: 1589.38 | AB2: 17352.28 | AC2: 3123.28 | AD2: 0 | AE2: 82294.7 | AF2: 0 | AG2: 0 | AH2: 81.89 | AI2: 4117.3 | AJ2: -1.69 | AK2: 7322.47 | AL2: 0 | AM2: 0 | AN2: 0 | AO2: 0 | AP2: 0 | AQ2: 0 | AR2: 0 | AS2: 0 | AT2: 0 | AU2: 24674.75 | AV2: 0 | AW2: 61735.56 | AX2: 0 | AY2: 0 | AZ2: 0 | BA2: 0 | BB2: 0
O3: 115684.84 | P3: 1420.72 | Q3: 0 | R3: 19997.814 | S3: 0 | T3: 0 | U3: 0 | V3: 4856.4198 | W3: 101964.17 | X3: 97107.746 | Y3: 7800.2012 | Z3: 18600.222 | AA3: 1875.4684 | AB3: 20475.69 | AC3: 3685.4704 | AD3: 0 | AE3: 97107.746 | AF3: 0 | AG3: 0 | AH3: 96.6302 | AI3: 4858.414 | AJ3: -1.9942 | AK3: 8640.5146 | AL3: 0 | AM3: 0 | AN3: 0 | AO3: 0 | AP3: 0 | AQ3: 0 | AR3: 0 | AS3: 0 | AT3: 0 | AU3: 29116.205 | AV3: 0 | AW3: 72847.961 | AX3: 0 | AY3: 0 | AZ3: 0 | BA3: 0 | BB3: 0
O4: 98267 | P4: 1204 | Q4: 0 | R4: 16947.3 | S4: 0 | T4: 0 | U4: 0 | V4: 4115.61 | W4: 86639.31 | X4: 82294.7 | Y4: 6610.34 | Z4: 15762.9 | AA4: 1589.38 | AB4: 17352.28 | AC4: 3123.28 | AD4: 0 | AE4: 82294.7 | AF4: 0 | AG4: 0 | AH4: 81.89 | AI4: 4117.3 | AJ4: -1.69 | AK4: 7322.47 | AL4: 0 | AM4: 0 | AN4: 0 | AO4: 0 | AP4: 0 | AQ4: 0 | AR4: 0 | AS4: 0 | AT4: 0 | AU4: 24674.75 | AV4: 174.84 | AW4: 61910.4 | AX4: 0 | AY4: 0 | AZ4: 0 | BA4: 0 | BB4: 0
A5: S.No. | B5: Order ID | C5: Order Date | D5: Week No. | E5: Res. name | F5: Res. ID | G5: Discount Construct | H5: Mode of payment | I5: Order status (Delivered/ Cancelled/ Rejected) | J5: Cancellation policy (% Amount refunded back to restaurant partner) | K5: Cancellation/ Rejection Reason | L5: Cancelled/ Rejected State (Order status at the time it was cancelled/ rejected) | M5: Order type | N5: Delivery State code | O5: Subtotal (items total) | P5: Packaging charge | Q5: Delivery charge for restaurants on self logistics | R5: Restaurant discount [Promo] | S5: Restaurant Discount [BOGO, Freebies, Gold, Brand pack & others] | T5: Brand pack subscription fee | U5: Delivery charge discount / Relisting discount | V5: Total GST collected from customers | W5: Net order value [(1) + (2) + (3) - (4) - (5) + (6) - (7) + (8)] | X5: Commissionable value (excludes customer GST) [(A) + (7) - (8) - (6) - (3)] | Y5: Service fees % | Z5: Service fee [ (9) * (10) ] | AA5: Payment mechanism fee | AB5: Service fee & payment mechanism fees [(11) + (12)] | AC5: Taxes on service & payment mechanism fees (B) * 18% | AD5: Applicable amount for TCS | AE5: Applicable amount for 9(5) | AF5: Tax collected at source | AG5: TCS IGST amount | AH5: TDS 194O amount | AI5: GST paid by Zomato on behalf of restaurant - under section 9(5) | AJ5: GST to be paid by Restaurant partner to Govt. | AK5: Government charges [(13) + (16) + (17) + (18) + (19)] | AL5: Customer Compensation/Recoupment | AM5: Delivery Charges Recovery | AN5: Amount received in cash (on self delivery orders) | AO5: Credit note/(Debit Note) adjustment | AP5: Promo recovery adjustment | AQ5: Extra Inventory Ads and Misc. (order level deduction) | AR5: Brand loyalty points redemption | AS5: Express Order Fee | AT5: Other order-level deductions [(21) + (22) + (23) + (24) + (25) + (26) + (27) + (28)] | AU5: Net Deductions (B) + (C) + (D) | AV5: Net Additions (cancellation refund for cancelled orders/Tip for Kitchen Staff for delivered orders) | AW5: Order level Payout (A) - (E) + (F) | AX5: Settlement status | AY5: Settlement date | AZ5: Bank UTR | BA5: Unsettled Amount | BB5: Customer ID
A6: 690 | B6: 7584074658 | C6: 2025-12-15 00:14:24 | D6: 51 | E6: Sha Sha - Shandaar Shawarma | F6: 18557902 | G6: 30% off upto ₹75 (2025-06-25 - 2031-01-01) | H6: ONLINE | I6: DELIVERED | J6: NA | K6: NA | L6: NA | M6: O2 | N6: 36 | O6: 355 | P6: 3.5 | Q6: 0 | R6: 75 | S6: 0 | T6: 0 | U6: 0 | V6: 14.18 | W6: 297.68 | X6: 283.5 | Y6: 19 | Z6: 53.86 | AA6: 5.48 | AB6: 59.34 | AC6: 10.68 | AD6: 0 | AE6: 283.5 | AF6: 0 | AG6: 0 | AH6: 0.28 | AI6: 14.18 | AJ6: 0 | AK6: 25.14 | AL6: 0 | AM6: 0 | AN6: 0 | AO6: 0 | AP6: 0 | AQ6: 0 | AR6: 0 | AS6: 0 | AT6: 0 | AU6: 84.48 | AV6: 0 | AW6: 213.2 | AX6: settled | AY6: NA | AZ6: NA | BA6: 0 | BB6: ca2073d82db9e89f4a26732742a23f8dc42cbadc0d57d6b416fdcd9d6a851df1
A7: 691 | B7: 7585018723 | C7: 2025-12-15 00:18:10 | D7: 51 | E7: Sha Sha - Shandaar Shawarma | F7: 18557902 | G7: NA | H7: ONLINE | I7: DELIVERED | J7: NA | K7: NA | L7: NA | M7: O2 | N7: 36 | O7: 229 | P7: 3.5 | Q7: 0 | R7: 0 | S7: 0 | T7: 0 | U7: 0 | V7: 11.63 | W7: 244.13 | X7: 232.5 | Y7: 19 | Z7: 44.18 | AA7: 4.49 | AB7: 48.67 | AC7: 8.76 | AD7: 0 | AE7: 232.5 | AF7: 0 | AG7: 0 | AH7: 0.23 | AI7: 11.63 | AJ7: 0 | AK7: 20.62 | AL7: 0 | AM7: 0 | AN7: 0 | AO7: 0 | AP7: 0 | AQ7: 0 | AR7: 0 | AS7: 0 | AT7: 0 | AU7: 69.29 | AV7: 0 | AW7: 174.84 | AX7: settled | AY7: NA | AZ7: NA | BA7: 0 | BB7: d0bddad9a77b4332b4608b9ba1ef6aa4763ae219357859d94d940c5b77839fb1
A8: 692 | B8: 7581454492 | C8: 2025-12-15 00:19:25 | D8: 51 | E8: Sha Sha - Shandaar Shawarma | F8: 18557902 | G8: 30% off upto ₹75 (2025-06-25 - 2031-01-01) | H8: ONLINE | I8: DELIVERED | J8: NA | K8: NA | L8: NA | M8: O2 | N8: 36 | O8: 229 | P8: 3.5 | Q8: 0 | R8: 68.7 | S8: 0 | T8: 0 | U8: 0 | V8: 8.19 | W8: 171.99 | X8: 163.8 | Y8: 19 | Z8: 31.12 | AA8: 3.16 | AB8: 34.28 | AC8: 6.17 | AD8: 0 | AE8: 163.8 | AF8: 0 | AG8: 0 | AH8: 0.16 | AI8: 8.2 | AJ8: -0.01 | AK8: 14.53 | AL8: 0 | AM8: 0 | AN8: 0 | AO8: 0 | AP8: 0 | AQ8: 0 | AR8: 0 | AS8: 0 | AT8: 0 | AU8: 48.81 | AV8: 0 | AW8: 123.18 | AX8: settled | AY8: NA | AZ8: NA | BA8: 0 | BB8: 8eb1500490d159665e1c9c2563971d3da60a404e60c98029e37dcdb4b41ce11a
A9: 693 | B9: 7578310288 | C9: 2025-12-15 00:24:23 | D9: 51 | E9: Sha Sha - Shandaar Shawarma | F9: 18557902 | G9: 30% off upto ₹75 (2025-06-25 - 2031-01-01) | H9: ONLINE | I9: DELIVERED | J9: NA | K9: NA | L9: NA | M9: O2 | N9: 36 | O9: 355 | P9: 3.5 | Q9: 0 | R9: 75 | S9: 0 | T9: 0 | U9: 0 | V9: 14.18 | W9: 297.68 | X9: 283.5 | Y9: 19 | Z9: 53.86 | AA9: 5.48 | AB9: 59.34 | AC9: 10.68 | AD9: 0 | AE9: 283.5 | AF9: 0 | AG9: 0 | AH9: 0.28 | AI9: 14.18 | AJ9: 0 | AK9: 25.14 | AL9: 0 | AM9: 0 | AN9: 0 | AO9: 0 | AP9: 0 | AQ9: 0 | AR9: 0 | AS9: 0 | AT9: 0 | AU9: 84.48 | AV9: 0 | AW9: 213.2 | AX9: settled | AY9: NA | AZ9: NA | BA9: 0 | BB9: 2b257bde6a1496c706be6a8e1dee8ffa93d708f424242d32b01ec2d4cc6cb672
A10: 694 | B10: 7567158853 | C10: 2025-12-15 00:31:39 | D10: 51 | E10: Sha Sha - Shandaar Shawarma | F10: 18557902 | G10: NA | H10: ONLINE | I10: DELIVERED | J10: NA | K10: NA | L10: NA | M10: O2 | N10: 36 | O10: 219 | P10: 3.5 | Q10: 0 | R10: 0 | S10: 0 | T10: 0 | U10: 0 | V10: 11.13 | W10: 233.63 | X10: 222.5 | Y10: 19 | Z10: 42.28 | AA10: 4.3 | AB10: 46.58 | AC10: 8.38 | AD10: 0 | AE10: 222.5 | AF10: 0 | AG10: 0 | AH10: 0.22 | AI10: 11.13 | AJ10: 0 | AK10: 19.73 | AL10: 0 | AM10: 0 | AN10: 0 | AO10: 0 | AP10: 0 | AQ10: 0 | AR10: 0 | AS10: 0 | AT10: 0 | AU10: 66.31 | AV10: 0 | AW10: 167.32 | AX10: settled | AY10: NA | AZ10: NA | BA10: 0 | BB10: 1ca787e4afdeefa65c15f027ca25c4794f41317f8a115aaa4460278ba14d5fca
A11: 695 | B11: 7583610506 | C11: 2025-12-15 01:08:18 | D11: 51 | E11: Sha Sha - Shandaar Shawarma | F11: 18557902 | G11: NA | H11: ONLINE | I11: DELIVERED | J11: NA | K11: NA | L11: NA | M11: O2 | N11: 36 | O11: 229 | P11: 3.5 | Q11: 0 | R11: 0 | S11: 0 | T11: 0 | U11: 0 | V11: 11.63 | W11: 244.13 | X11: 232.5 | Y11: 19 | Z11: 44.18 | AA11: 4.49 | AB11: 48.67 | AC11: 8.76 | AD11: 0 | AE11: 232.5 | AF11: 0 | AG11: 0 | AH11: 0.23 | AI11: 11.63 | AJ11: 0 | AK11: 20.62 | AL11: 0 | AM11: 0 | AN11: 0 | AO11: 0 | AP11: 0 | AQ11: 0 | AR11: 0 | AS11: 0 | AT11: 0 | AU11: 69.29 | AV11: 0 | AW11: 174.84 | AX11: settled | AY11: NA | AZ11: NA | BA11: 0 | BB11: 30a433ebd7c0778a5392559abb419c2fae79ace8d8d336ad9d2742c07412cdf3
A12: 696 | B12: 7583284041 | C12: 2025-12-15 01:31:54 | D12: 51 | E12: Sha Sha - Shandaar Shawarma | F12: 18557902 | G12: 30% off upto ₹75 (2025-06-25 - 2031-01-01) | H12: ONLINE | I12: DELIVERED | J12: NA | K12: NA | L12: NA | M12: O2 | N12: 36 | O12: 199 | P12: 3.5 | Q12: 0 | R12: 59.7 | S12: 0 | T12: 0 | U12: 0 | V12: 7.14 | W12: 149.94 | X12: 142.8 | Y12: 19 | Z12: 27.13 | AA12: 2.76 | AB12: 29.89 | AC12: 5.38 | AD12: 0 | AE12: 142.8 | AF12: 0 | AG12: 0 | AH12: 0.14 | AI12: 7.15 | AJ12: -0.01 | AK12: 12.67 | AL12: 0 | AM12: 0 | AN12: 0 | AO12: 0 | AP12: 0 | AQ12: 0 | AR12: 0 | AS12: 0 | AT12: 0 | AU12: 42.56 | AV12: 0 | AW12: 107.38 | AX12: settled | AY12: NA | AZ12: NA | BA12: 0 | BB12: 32f8d18fed18aa541f4d8917de73fe54d981a0e4de136f7e867bb1840239f8a4
A13: 697 | B13: 7579932219 | C13: 2025-12-15 01:33:14 | D13: 51 | E13: Sha Sha - Shandaar Shawarma | F13: 18557902 | G13: 30% off upto ₹75 (2025-06-25 - 2031-01-01) | H13: ONLINE | I13: DELIVERED | J13: NA | K13: NA | L13: NA | M13: O2 | N13: 36 | O13: 229 | P13: 3.5 | Q13: 0 | R13: 68.7 | S13: 0 | T13: 0 | U13: 0 | V13: 8.19 | W13: 171.99 | X13: 163.8 | Y13: 19 | Z13: 31.12 | AA13: 3.16 | AB13: 34.28 | AC13: 6.17 | AD13: 0 | AE13: 163.8 | AF13: 0 | AG13: 0 | AH13: 0.16 | AI13: 8.2 | AJ13: -0.01 | AK13: 14.53 | AL13: 0 | AM13: 0 | AN13: 0 | AO13: 0 | AP13: 0 | AQ13: 0 | AR13: 0 | AS13: 0 | AT13: 0 | AU13: 48.81 | AV13: 0 | AW13: 123.18 | AX13: settled | AY13: NA | AZ13: NA | BA13: 0 | BB13: 7302b35900c76696417434d227f3e332eb9505b58da433feb8f904737c2a36b4
A14: 698 | B14: 7579831724 | C14: 2025-12-15 01:35:32 | D14: 51 | E14: Sha Sha - Shandaar Shawarma | F14: 18557902 | G14: 30% off upto ₹75 (2025-06-25 - 2031-01-01) | H14: ONLINE | I14: DELIVERED | J14: NA | K14: NA | L14: NA | M14: O2 | N14: 36 | O14: 229 | P14: 3.5 | Q14: 0 | R14: 68.7 | S14: 0 | T14: 0 | U14: 0 | V14: 8.19 | W14: 171.99 | X14: 163.8 | Y14: 19 | Z14: 31.12 | AA14: 3.16 | AB14: 34.28 | AC14: 6.17 | AD14: 0 | AE14: 163.8 | AF14: 0 | AG14: 0 | AH14: 0.16 | AI14: 8.2 | AJ14: -0.01 | AK14: 14.53 | AL14: 0 | AM14: 0 | AN14: 0 | AO14: 0 | AP14: 0 | AQ14: 0 | AR14: 0 | AS14: 0 | AT14: 0 | AU14: 48.81 | AV14: 0 | AW14: 123.18 | AX14: settled | AY14: NA | AZ14: NA | BA14: 0 | BB14: a4a70e0e977a73da377b4f40475eaf264e2652e623d22ae3ef862491d5035f2f
A15: 699 | B15: 7580883984 | C15: 2025-12-15 01:39:40 | D15: 51 | E15: Sha Sha - Shandaar Shawarma | F15: 18557902 | G15: 30% off upto ₹75 (2025-06-25 - 2031-01-01) | H15: ONLINE | I15: DELIVERED | J15: NA | K15: NA | L15: NA | M15: O2 | N15: 36 | O15: 229 | P15: 3.5 | Q15: 0 | R15: 68.7 | S15: 0 | T15: 0 | U15: 0 | V15: 8.19 | W15: 171.99 | X15: 163.8 | Y15: 19 | Z15: 31.12 | AA15: 3.16 | AB15: 34.28 | AC15: 6.17 | AD15: 0 | AE15: 163.8 | AF15: 0 | AG15: 0 | AH15: 0.16 | AI15: 8.2 | AJ15: -0.01 | AK15: 14.53 | AL15: 0 | AM15: 0 | AN15: 0 | AO15: 0 | AP15: 0 | AQ15: 0 | AR15: 0 | AS15: 0 | AT15: 0 | AU15: 48.81 | AV15: 0 | AW15: 123.18 | AX15: settled | AY15: NA | AZ15: NA | BA15: 0 | BB15: 18528381c17e329a6530557d09b880bdc3162cae145a2e6e6884d708a508ea76
A16: 700 | B16: 7585405063 | C16: 2025-12-15 02:01:43 | D16: 51 | E16: Sha Sha - Shandaar Shawarma | F16: 18557902 | G16: NA | H16: ONLINE | I16: DELIVERED | J16: NA | K16: NA | L16: NA | M16: O2 | N16: 36 | O16: 229 | P16: 3.5 | Q16: 0 | R16: 0 | S16: 0 | T16: 0 | U16: 0 | V16: 11.63 | W16: 244.13 | X16: 232.5 | Y16: 19 | Z16: 44.18 | AA16: 4.49 | AB16: 48.67 | AC16: 8.76 | AD16: 0 | AE16: 232.5 | AF16: 0 | AG16: 0 | AH16: 0.23 | AI16: 11.63 | AJ16: 0 | AK16: 20.62 | AL16: 0 | AM16: 0 | AN16: 0 | AO16: 0 | AP16: 0 | AQ16: 0 | AR16: 0 | AS16: 0 | AT16: 0 | AU16: 69.29 | AV16: 0 | AW16: 174.84 | AX16: settled | AY16: NA | AZ16: NA | BA16: 0 | BB16: ced35cad68c35fa8359a99da06789cbf3deac4d34f87bba6a9f6975a9c1179c9
A17: 701 | B17: 7584789093 | C17: 2025-12-15 03:11:02 | D17: 51 | E17: Sha Sha - Shandaar Shawarma | F17: 18557902 | G17: 30% off upto ₹75 (2025-06-25 - 2031-01-01) | H17: ONLINE | I17: DELIVERED | J17: NA | K17: NA | L17: NA | M17: O2 | N17: 36 | O17: 219 | P17: 3.5 | Q17: 0 | R17: 65.7 | S17: 0 | T17: 0 | U17: 0 | V17: 7.84 | W17: 164.64 | X17: 156.8 | Y17: 19 | Z17: 29.79 | AA17: 3.03 | AB17: 32.82 | AC17: 5.91 | AD17: 0 | AE17: 156.8 | AF17: 0 | AG17: 0 | AH17: 0.16 | AI17: 7.85 | AJ17: -0.01 | AK17: 13.92 | AL17: 0 | AM17: 0 | AN17: 0 | AO17: 0 | AP17: 0 | AQ17: 0 | AR17: 0 | AS17: 0 | AT17: 0 | AU17: 46.74 | AV17: 0 | AW17: 117.9 | AX17: settled | AY17: NA | AZ17: NA | BA17: 0 | BB17: e673f2ac60d1e0083216ae882954940ad02bddce9eaf8fe4c023acb44a23c5c0
... A351: 1035 | B351: 7608721845 | C351: 2025-12-21 23:56:21 | D351: 51 | E351: Sha Sha - Shandaar Shawarma | F351: 18557902 | G351: NA | H351: ONLINE | I351: DELIVERED | J351: NA | K351: NA | L351: NA | M351: O2 | N351: 36 | O351: 229 | P351: 3.5 | Q351: 0 | R351: 0 | S351: 0 | T351: 0 | U351: 0 | V351: 11.63 | W351: 244.13 | X351: 232.5 | Y351: 19 | Z351: 44.18 | AA351: 4.49 | AB351: 48.67 | AC351: 8.76 | AD351: 0 | AE351: 232.5 | AF351: 0 | AG351: 0 | AH351: 0.23 | AI351: 11.63 | AJ351: 0 | AK351: 20.62 | AL351: 0 | AM351: 0 | AN351: 0 | AO351: 0 | AP351: 0 | AQ351: 0 | AR351: 0 | AS351: 0 | AT351: 0 | AU351: 69.29 | AV351: 0 | AW351: 174.84 | AX351: settled | AY351: NA | AZ351: NA | BA351: 0 | BB351: aca3ea8829f35f32eeb9c617b1f572fd528973fe5d98cd8653b3eae979a66190

Sheet D1W4
O1: 289 | P1: 0 | Q1: 0 | R1: 0 | S1: 0 | T1: 0 | U1: 0 | V1: 0 | W1: 289 | X1: 0 | Y1: 0 | Z1: 0 | AA1: 0 | AB1: 0 | AC1: 0 | AD1: 0 | AE1: 0 | AF1: 0 | AG1: 0 | AH1: 0 | AI1: 0 | AJ1: 0 | AK1: 0 | AL1: 0 | AM1: 0 | AN1: 0 | AO1: 0 | AP1: 0 | AQ1: 0 | AR1: 0 | AS1: 0 | AT1: 0 | AU1: 0 | AV1: 163.56 | AW1: 163.56 | AX1: 0 | AY1: 0 | AZ1: 0 | BA1: 0 | BB1: 0
O2: 83954 | P2: 1022 | Q2: 0 | R2: 16789.8 | S2: 0 | T2: 0 | U2: 0 | V2: 3409.95 | W2: 71596.15 | X2: 68186.2 | Y2: 5548 | Z2: 12955.34 | AA2: 1316.8 | AB2: 14272.14 | AC2: 2568.9 | AD2: 0 | AE2: 68186.2 | AF2: 0 | AG2: 0 | AH2: 67.78 | AI2: 3411.59 | AJ2: -1.64 | AK2: 6048.27 | AL2: 0 | AM2: 0 | AN2: 0 | AO2: 0 | AP2: 0 | AQ2: 0 | AR2: 0 | AS2: 0 | AT2: 0 | AU2: 20320.41 | AV2: 0 | AW2: 51275.74 | AX2: 0 | AY2: 0 | AZ2: 0 | BA2: 0 | BB2: 0
O3: 99065.72 | P3: 1205.96 | Q3: 0 | R3: 19811.964 | S3: 0 | T3: 0 | U3: 0 | V3: 4023.741 | W3: 84483.457 | X3: 80459.716 | Y3: 6546.64 | Z3: 15287.301 | AA3: 1553.824 | AB3: 16841.125 | AC3: 3031.302 | AD3: 0 | AE3: 80459.716 | AF3: 0 | AG3: 0 | AH3: 79.9804 | AI3: 4025.6762 | AJ3: -1.9352 | AK3: 7136.9586 | AL3: 0 | AM3: 0 | AN3: 0 | AO3: 0 | AP3: 0 | AQ3: 0 | AR3: 0 | AS3: 0 | AT3: 0 | AU3: 23978.084 | AV3: 0 | AW3: 60505.373 | AX3: 0 | AY3: 0 | AZ3: 0 | BA3: 0 | BB3: 0
O4: 84243 | P4: 1022 | Q4: 0 | R4: 16789.8 | S4: 0 | T4: 0 | U4: 0 | V4: 3409.95 | W4: 71885.15 | X4: 68186.2 | Y4: 5548 | Z4: 12955.34 | AA4: 1316.8 | AB4: 14272.14 | AC4: 2568.9 | AD4: 0 | AE4: 68186.2 | AF4: 0 | AG4: 0 | AH4: 67.78 | AI4: 3411.59 | AJ4: -1.64 | AK4: 6048.27 | AL4: 0 | AM4: 0 | AN4: 0 | AO4: 0 | AP4: 0 | AQ4: 0 | AR4: 0 | AS4: 0 | AT4: 0 | AU4: 20320.41 | AV4: 163.56 | AW4: 51439.3 | AX4: 0 | AY4: 0 | AZ4: 0 | BA4: 0 | BB4: 0
A5: S.No. | B5: Order ID | C5: Order Date | D5: Week No. | E5: Res. name | F5: Res. ID | G5: Discount Construct | H5: Mode of payment | I5: Order status (Delivered/ Cancelled/ Rejected) | J5: Cancellation policy (% Amount refunded back to restaurant partner) | K5: Cancellation/ Rejection Reason | L5: Cancelled/ Rejected State (Order status at the time it was cancelled/ rejected) | M5: Order type | N5: Delivery State code | O5: Subtotal (items total) | P5: Packaging charge | Q5: Delivery charge for restaurants on self logistics | R5: Restaurant discount [Promo] | S5: Restaurant Discount [BOGO, Freebies, Gold, Brand pack & others] | T5: Brand pack subscription fee | U5: Delivery charge discount / Relisting discount | V5: Total GST collected from customers | W5: Net order value [(1) + (2) + (3) - (4) - (5) + (6) - (7) + (8)] | X5: Commissionable value (excludes customer GST) [(A) + (7) - (8) - (6) - (3)] | Y5: Service fees % | Z5: Service fee [ (9) * (10) ] | AA5: Payment mechanism fee | AB5: Service fee & payment mechanism fees [(11) + (12)] | AC5: Taxes on service & payment mechanism fees (B) * 18% | AD5: Applicable amount for TCS | AE5: Applicable amount for 9(5) | AF5: Tax collected at source | AG5: TCS IGST amount | AH5: TDS 194O amount | AI5: GST paid by Zomato on behalf of restaurant - under section 9(5) | AJ5: GST to be paid by Restaurant partner to Govt. | AK5: Government charges [(13) + (16) + (17) + (18) + (19)] | AL5: Customer Compensation/Recoupment | AM5: Delivery Charges Recovery | AN5: Amount received in cash (on self delivery orders) | AO5: Credit note/(Debit Note) adjustment | AP5: Promo recovery adjustment | AQ5: Extra Inventory Ads and Misc. (order level deduction) | AR5: Brand loyalty points redemption | AS5: Express Order Fee | AT5: Other order-level deductions [(21) + (22) + (23) + (24) + (25) + (26) + (27) + (28)] | AU5: Net Deductions (B) + (C) + (D) | AV5: Net Additions (cancellation refund for cancelled orders/Tip for Kitchen Staff for delivered orders) | AW5: Order level Payout (A) - (E) + (F) | AX5: Settlement status | AY5: Settlement date | AZ5: Bank UTR | BA5: Unsettled Amount | BB5: Customer ID
A6: 1036 | B6: 7608821644 | C6: 2025-12-22 00:31:15 | D6: 52 | E6: Sha Sha - Shandaar Shawarma | F6: 18557902 | G6: 30% off upto ₹75 (2025-06-25 - 2031-01-01) | H6: ONLINE | I6: DELIVERED | J6: NA | K6: NA | L6: NA | M6: O2 | N6: 36 | O6: 229 | P6: 3.5 | Q6: 0 | R6: 68.7 | S6: 0 | T6: 0 | U6: 0 | V6: 8.19 | W6: 171.99 | X6: 163.8 | Y6: 19 | Z6: 31.12 | AA6: 3.16 | AB6: 34.28 | AC6: 6.17 | AD6: 0 | AE6: 163.8 | AF6: 0 | AG6: 0 | AH6: 0.16 | AI6: 8.2 | AJ6: -0.01 | AK6: 14.53 | AL6: 0 | AM6: 0 | AN6: 0 | AO6: 0 | AP6: 0 | AQ6: 0 | AR6: 0 | AS6: 0 | AT6: 0 | AU6: 48.81 | AV6: 0 | AW6: 123.18 | AX6: settled | AY6: NA | AZ6: NA | BA6: 0 | BB6: 0e1676fc71ff5c54d5c9b60eac184326b3aabea3fecee680028b1ce0dd7f19af
A7: 1037 | B7: 7588185160 | C7: 2025-12-22 00:44:53 | D7: 52 | E7: Sha Sha - Shandaar Shawarma | F7: 18557902 | G7: NA | H7: ONLINE | I7: DELIVERED | J7: NA | K7: NA | L7: NA | M7: O2 | N7: 36 | O7: 458 | P7: 3.5 | Q7: 0 | R7: 0 | S7: 0 | T7: 0 | U7: 0 | V7: 23.08 | W7: 484.58 | X7: 461.5 | Y7: 19 | Z7: 87.68 | AA7: 8.92 | AB7: 96.6 | AC7: 17.39 | AD7: 0 | AE7: 461.5 | AF7: 0 | AG7: 0 | AH7: 0.46 | AI7: 23.08 | AJ7: 0 | AK7: 40.93 | AL7: 0 | AM7: 0 | AN7: 0 | AO7: 0 | AP7: 0 | AQ7: 0 | AR7: 0 | AS7: 0 | AT7: 0 | AU7: 137.53 | AV7: 0 | AW7: 347.05 | AX7: settled | AY7: NA | AZ7: NA | BA7: 0 | BB7: 44a6603e612fdb41821a80405edfd9e7d0f7f34af258f6acd38dd2d2837d0b05
A8: 1038 | B8: 7600034506 | C8: 2025-12-22 01:08:19 | D8: 52 | E8: Sha Sha - Shandaar Shawarma | F8: 18557902 | G8: 30% off upto ₹75 (2025-06-25 - 2031-01-01) | H8: ONLINE | I8: DELIVERED | J8: NA | K8: NA | L8: NA | M8: O2 | N8: 36 | O8: 219 | P8: 3.5 | Q8: 0 | R8: 65.7 | S8: 0 | T8: 0 | U8: 0 | V8: 7.84 | W8: 164.64 | X8: 156.8 | Y8: 19 | Z8: 29.79 | AA8: 3.03 | AB8: 32.82 | AC8: 5.91 | AD8: 0 | AE8: 156.8 | AF8: 0 | AG8: 0 | AH8: 0.16 | AI8: 7.85 | AJ8: -0.01 | AK8: 13.92 | AL8: 0 | AM8: 0 | AN8: 0 | AO8: 0 | AP8: 0 | AQ8: 0 | AR8: 0 | AS8: 0 | AT8: 0 | AU8: 46.74 | AV8: 0 | AW8: 117.9 | AX8: settled | AY8: NA | AZ8: NA | BA8: 0 | BB8: b3c490809c30d4adc248551bb5c555129fe021f80da970dd0271e91772e202fe
A9: 1039 | B9: 7605977918 | C9: 2025-12-22 01:27:42 | D9: 52 | E9: Sha Sha - Shandaar Shawarma | F9: 18557902 | G9: 30% off upto ₹75 (2025-06-25 - 2031-01-01) | H9: ONLINE | I9: DELIVERED | J9: NA | K9: NA | L9: NA | M9: O2 | N9: 36 | O9: 229 | P9: 3.5 | Q9: 0 | R9: 68.7 | S9: 0 | T9: 0 | U9: 0 | V9: 8.19 | W9: 171.99 | X9: 163.8 | Y9: 19 | Z9: 31.12 | AA9: 3.16 | AB9: 34.28 | AC9: 6.17 | AD9: 0 | AE9: 163.8 | AF9: 0 | AG9: 0 | AH9: 0.16 | AI9: 8.2 | AJ9: -0.01 | AK9: 14.53 | AL9: 0 | AM9: 0 | AN9: 0 | AO9: 0 | AP9: 0 | AQ9: 0 | AR9: 0 | AS9: 0 | AT9: 0 | AU9: 48.81 | AV9: 0 | AW9: 123.18 | AX9: settled | AY9: NA | AZ9: NA | BA9: 0 | BB9: 477fc7e9b7349b47e3ee3748b726e2cb8294b282b97a4f524483e4eb4e2c2f10
A10: 1040 | B10: 7604044822 | C10: 2025-12-22 01:47:56 | D10: 52 | E10: Sha Sha - Shandaar Shawarma | F10: 18557902 | G10: 30% off upto ₹75 (2025-06-25 - 2031-01-01) | H10: ONLINE | I10: DELIVERED | J10: NA | K10: NA | L10: NA | M10: O2 | N10: 36 | O10: 229 | P10: 3.5 | Q10: 0 | R10: 68.7 | S10: 0 | T10: 0 | U10: 0 | V10: 8.19 | W10: 171.99 | X10: 163.8 | Y10: 19 | Z10: 31.12 | AA10: 3.16 | AB10: 34.28 | AC10: 6.17 | AD10: 0 | AE10: 163.8 | AF10: 0 | AG10: 0 | AH10: 0.16 | AI10: 8.2 | AJ10: -0.01 | AK10: 14.53 | AL10: 0 | AM10: 0 | AN10: 0 | AO10: 0 | AP10: 0 | AQ10: 0 | AR10: 0 | AS10: 0 | AT10: 0 | AU10: 48.81 | AV10: 0 | AW10: 123.18 | AX10: settled | AY10: NA | AZ10: NA | BA10: 0 | BB10: 60b4964effebb9e3924a0053884646d670ec66ef7f7e9de0a96721ef4097a18e
A11: 1041 | B11: 7604688603 | C11: 2025-12-22 01:48:48 | D11: 52 | E11: Sha Sha - Shandaar Shawarma | F11: 18557902 | G11: NA | H11: ONLINE | I11: DELIVERED | J11: NA | K11: NA | L11: NA | M11: O2 | N11: 36 | O11: 229 | P11: 3.5 | Q11: 0 | R11: 0 | S11: 0 | T11: 0 | U11: 0 | V11: 11.63 | W11: 244.13 | X11: 232.5 | Y11: 19 | Z11: 44.18 | AA11: 4.49 | AB11: 48.67 | AC11: 8.76 | AD11: 0 | AE11: 232.5 | AF11: 0 | AG11: 0 | AH11: 0.23 | AI11: 11.63 | AJ11: 0 | AK11: 20.62 | AL11: 0 | AM11: 0 | AN11: 0 | AO11: 0 | AP11: 0 | AQ11: 0 | AR11: 0 | AS11: 0 | AT11: 0 | AU11: 69.29 | AV11: 0 | AW11: 174.84 | AX11: settled | AY11: NA | AZ11: NA | BA11: 0 | BB11: 6d5d06bd2869811be139efab28b7a1230220bc095533e2effc4e9c875f80f41a
A12: 1042 | B12: 7604707174 | C12: 2025-12-22 01:51:53 | D12: 52 | E12: Sha Sha - Shandaar Shawarma | F12: 18557902 | G12: 30% off upto ₹75 (2025-06-25 - 2031-01-01) | H12: ONLINE | I12: DELIVERED | J12: NA | K12: NA | L12: NA | M12: O2 | N12: 36 | O12: 229 | P12: 3.5 | Q12: 0 | R12: 68.7 | S12: 0 | T12: 0 | U12: 0 | V12: 8.19 | W12: 171.99 | X12: 163.8 | Y12: 19 | Z12: 31.12 | AA12: 3.16 | AB12: 34.28 | AC12: 6.17 | AD12: 0 | AE12: 163.8 | AF12: 0 | AG12: 0 | AH12: 0.16 | AI12: 8.2 | AJ12: -0.01 | AK12: 14.53 | AL12: 0 | AM12: 0 | AN12: 0 | AO12: 0 | AP12: 0 | AQ12: 0 | AR12: 0 | AS12: 0 | AT12: 0 | AU12: 48.81 | AV12: 0 | AW12: 123.18 | AX12: settled | AY12: NA | AZ12: NA | BA12: 0 | BB12: 3f3eca36291126911a81e571bcc06cf60d6a181a063728c0e7eb387a9c07b105
A13: 1043 | B13: 7603515432 | C13: 2025-12-22 01:56:38 | D13: 52 | E13: Sha Sha - Shandaar Shawarma | F13: 18557902 | G13: 30% off upto ₹75 (2025-06-25 - 2031-01-01) | H13: ONLINE | I13: DELIVERED | J13: NA | K13: NA | L13: NA | M13: O2 | N13: 36 | O13: 219 | P13: 3.5 | Q13: 0 | R13: 65.7 | S13: 0 | T13: 0 | U13: 0 | V13: 7.84 | W13: 164.64 | X13: 156.8 | Y13: 19 | Z13: 29.79 | AA13: 3.03 | AB13: 32.82 | AC13: 5.91 | AD13: 0 | AE13: 156.8 | AF13: 0 | AG13: 0 | AH13: 0.16 | AI13: 7.85 | AJ13: -0.01 | AK13: 13.92 | AL13: 0 | AM13: 0 | AN13: 0 | AO13: 0 | AP13: 0 | AQ13: 0 | AR13: 0 | AS13: 0 | AT13: 0 | AU13: 46.74 | AV13: 0 | AW13: 117.9 | AX13: settled | AY13: NA | AZ13: NA | BA13: 0 | BB13: e82088a00e2a518bad161c64de687890f1a58ab131ee0bc8971b4c79b3dd3b51
A14: 1044 | B14: 7594984882 | C14: 2025-12-22 02:46:04 | D14: 52 | E14: Sha Sha - Shandaar Shawarma | F14: 18557902 | G14: 30% off upto ₹75 (2025-06-25 - 2031-01-01) | H14: ONLINE | I14: DELIVERED | J14: NA | K14: NA | L14: NA | M14: O2 | N14: 36 | O14: 706 | P14: 3.5 | Q14: 0 | R14: 75 | S14: 0 | T14: 0 | U14: 0 | V14: 31.73 | W14: 666.23 | X14: 634.5 | Y14: 19 | Z14: 120.56 | AA14: 12.26 | AB14: 132.82 | AC14: 23.91 | AD14: 0 | AE14: 634.5 | AF14: 0 | AG14: 0 | AH14: 0.63 | AI14: 31.73 | AJ14: 0 | AK14: 56.27 | AL14: 0 | AM14: 0 | AN14: 0 | AO14: 0 | AP14: 0 | AQ14: 0 | AR14: 0 | AS14: 0 | AT14: 0 | AU14: 189.09 | AV14: 0 | AW14: 477.14 | AX14: settled | AY14: NA | AZ14: NA | BA14: 0 | BB14: 13e17be5b920c7b24d377b8b8a00ca1adfb27c465baecd78c92d0ed72ca4757a
A15: 1045 | B15: 7598183744 | C15: 2025-12-22 03:30:24 | D15: 52 | E15: Sha Sha - Shandaar Shawarma | F15: 18557902 | G15: 30% off upto ₹75 (2025-06-25 - 2031-01-01) | H15: ONLINE | I15: DELIVERED | J15: NA | K15: NA | L15: NA | M15: O2 | N15: 36 | O15: 345 | P15: 3.5 | Q15: 0 | R15: 75 | S15: 0 | T15: 0 | U15: 0 | V15: 13.68 | W15: 287.18 | X15: 273.5 | Y15: 19 | Z15: 51.96 | AA15: 5.28 | AB15: 57.24 | AC15: 10.3 | AD15: 0 | AE15: 273.5 | AF15: 0 | AG15: 0 | AH15: 0.27 | AI15: 13.68 | AJ15: 0 | AK15: 24.25 | AL15: 0 | AM15: 0 | AN15: 0 | AO15: 0 | AP15: 0 | AQ15: 0 | AR15: 0 | AS15: 0 | AT15: 0 | AU15: 81.49 | AV15: 0 | AW15: 205.69 | AX15: settled | AY15: NA | AZ15: NA | BA15: 0 | BB15: fd34baec042f8c9901250c28a136a72dad3b4949a0df2da1478a9c11a2198997
A16: 1046 | B16: 7607074874 | C16: 2025-12-22 09:06:50 | D16: 52 | E16: Sha Sha - Shandaar Shawarma | F16: 18557902 | G16: NA | H16: ONLINE | I16: DELIVERED | J16: NA | K16: NA | L16: NA | M16: O2 | N16: 36 | O16: 199 | P16: 3.5 | Q16: 0 | R16: 0 | S16: 0 | T16: 0 | U16: 0 | V16: 10.13 | W16: 212.63 | X16: 202.5 | Y16: 19 | Z16: 38.48 | AA16: 3.91 | AB16: 42.39 | AC16: 7.63 | AD16: 0 | AE16: 202.5 | AF16: 0 | AG16: 0 | AH16: 0.2 | AI16: 10.13 | AJ16: 0 | AK16: 17.96 | AL16: 0 | AM16: 0 | AN16: 0 | AO16: 0 | AP16: 0 | AQ16: 0 | AR16: 0 | AS16: 0 | AT16: 0 | AU16: 60.35 | AV16: 0 | AW16: 152.28 | AX16: settled | AY16: NA | AZ16: NA | BA16: 0 | BB16: 522872bc9605da27956eeab38110db4cbf11ceb5fed834d3d3349f882220d4ad
A17: 1047 | B17: 7600660993 | C17: 2025-12-22 12:13:10 | D17: 52 | E17: Sha Sha - Shandaar Shawarma | F17: 18557902 | G17: 30% off upto ₹75 (2025-06-25 - 2031-01-01) | H17: ONLINE | I17: DELIVERED | J17: NA | K17: NA | L17: NA | M17: O2 | N17: 36 | O17: 229 | P17: 3.5 | Q17: 0 | R17: 68.7 | S17: 0 | T17: 0 | U17: 0 | V17: 8.19 | W17: 171.99 | X17: 163.8 | Y17: 19 | Z17: 31.12 | AA17: 3.16 | AB17: 34.28 | AC17: 6.17 | AD17: 0 | AE17: 163.8 | AF17: 0 | AG17: 0 | AH17: 0.16 | AI17: 8.2 | AJ17: -0.01 | AK17: 14.53 | AL17: 0 | AM17: 0 | AN17: 0 | AO17: 0 | AP17: 0 | AQ17: 0 | AR17: 0 | AS17: 0 | AT17: 0 | AU17: 48.81 | AV17: 0 | AW17: 123.18 | AX17: settled | AY17: NA | AZ17: NA | BA17: 0 | BB17: e58b616b4f8bc9cb9068637c0c7cb0d4149bd91d2e1fe300b6a5c963f2ee9254
... A298: 1328 | B298: 7631973067 | C298: 2025-12-28 22:48:52 | D298: 52 | E298: Sha Sha - Shandaar Shawarma | F298: 18557902 | G298: 30% off upto ₹75 (2025-06-25 - 2031-01-01) | H298: ONLINE | I298: DELIVERED | J298: NA | K298: NA | L298: NA | M298: O2 | N298: 36 | O298: 229 | P298: 3.5 | Q298: 0 | R298: 68.7 | S298: 0 | T298: 0 | U298: 0 | V298: 8.19 | W298: 171.99 | X298: 163.8 | Y298: 19 | Z298: 31.12 | AA298: 3.16 | AB298: 34.28 | AC298: 6.17 | AD298: 0 | AE298: 163.8 | AF298: 0 | AG298: 0 | AH298: 0.16 | AI298: 8.2 | AJ298: -0.01 | AK298: 14.53 | AL298: 0 | AM298: 0 | AN298: 0 | AO298: 0 | AP298: 0 | AQ298: 0 | AR298: 0 | AS298: 0 | AT298: 0 | AU298: 48.81 | AV298: 0 | AW298: 123.18 | AX298: settled | AY298: NA | AZ298: NA | BA298: 0 | BB298: cced21294a761e8e520d3f723af908adf3bedcfdce1f6051f03037bf5aa364a8

Sheet D1W5
O1: 229 | P1: 0 | Q1: 0 | R1: 0 | S1: 0 | T1: 0 | U1: 0 | V1: 0 | W1: 229 | X1: 0 | Y1: 0 | Z1: 0 | AA1: 0 | AB1: 0 | AC1: 0 | AD1: 0 | AE1: 0 | AF1: 0 | AG1: 0 | AH1: 0 | AI1: 0 | AJ1: 0 | AK1: 0 | AL1: 0 | AM1: 0 | AN1: 0 | AO1: 0 | AP1: 0 | AQ1: 0 | AR1: 0 | AS1: 0 | AT1: 0 | AU1: 0 | AV1: 0 | AW1: 0 | AX1: 0 | AY1: 0 | AZ1: 0 | BA1: 0 | BB1: 0
O2: 33137 | P2: 399 | Q2: 0 | R2: 6757.8 | S2: 0 | T2: 0 | U2: 0 | V2: 1339.16 | W2: 28117.36 | X2: 26778.2 | Y2: 2166 | Z2: 5087.91 | AA2: 517.13 | AB2: 5605.04 | AC2: 1008.9 | AD2: 0 | AE2: 26778.2 | AF2: 0 | AG2: 0 | AH2: 26.67 | AI2: 1339.8 | AJ2: -0.64 | AK2: 2375.37 | AL2: 0 | AM2: 0 | AN2: 0 | AO2: 0 | AP2: 0 | AQ2: 0 | AR2: 0 | AS2: 0 | AT2: 0 | AU2: 7980.41 | AV2: 0 | AW2: 20136.95 | AX2: 0 | AY2: 0 | AZ2: 0 | BA2: 20136.95 | BB2: 0
O3: 39101.66 | P3: 470.82 | Q3: 0 | R3: 7974.204 | S3: 0 | T3: 0 | U3: 0 | V3: 1580.2088 | W3: 33178.485 | X3: 31598.276 | Y3: 2555.88 | Z3: 6003.7338 | AA3: 610.2134 | AB3: 6613.9472 | AC3: 1190.502 | AD3: 0 | AE3: 31598.276 | AF3: 0 | AG3: 0 | AH3: 31.4706 | AI3: 1580.964 | AJ3: -0.7552 | AK3: 2802.9366 | AL3: 0 | AM3: 0 | AN3: 0 | AO3: 0 | AP3: 0 | AQ3: 0 | AR3: 0 | AS3: 0 | AT3: 0 | AU3: 9416.8838 | AV3: 0 | AW3: 23761.601 | AX3: 0 | AY3: 0 | AZ3: 0 | BA3: 23761.601 | BB3: 0
O4: 33366 | P4: 399 | Q4: 0 | R4: 6757.8 | S4: 0 | T4: 0 | U4: 0 | V4: 1339.16 | W4: 28346.36 | X4: 26778.2 | Y4: 2166 | Z4: 5087.91 | AA4: 517.13 | AB4: 5605.04 | AC4: 1008.9 | AD4: 0 | AE4: 26778.2 | AF4: 0 | AG4: 0 | AH4: 26.67 | AI4: 1339.8 | AJ4: -0.64 | AK4: 2375.37 | AL4: 0 | AM4: 0 | AN4: 0 | AO4: 0 | AP4: 0 | AQ4: 0 | AR4: 0 | AS4: 0 | AT4: 0 | AU4: 7980.41 | AV4: 0 | AW4: 20136.95 | AX4: 0 | AY4: 0 | AZ4: 0 | BA4: 20136.95 | BB4: 0
A5: S.No. | B5: Order ID | C5: Order Date | D5: Week No. | E5: Res. name | F5: Res. ID | G5: Discount Construct | H5: Mode of payment | I5: Order status (Delivered/ Cancelled/ Rejected) | J5: Cancellation policy (% Amount refunded back to restaurant partner) | K5: Cancellation/ Rejection Reason | L5: Cancelled/ Rejected State (Order status at the time it was cancelled/ rejected) | M5: Order type | N5: Delivery State code | O5: Subtotal (items total) | P5: Packaging charge | Q5: Delivery charge for restaurants on self logistics | R5: Restaurant discount [Promo] | S5: Restaurant Discount [BOGO, Freebies, Gold, Brand pack & others] | T5: Brand pack subscription fee | U5: Delivery charge discount / Relisting discount | V5: Total GST collected from customers | W5: Net order value [(1) + (2) + (3) - (4) - (5) + (6) - (7) + (8)] | X5: Commissionable value (excludes customer GST) [(A) + (7) - (8) - (6) - (3)] | Y5: Service fees % | Z5: Service fee [ (9) * (10) ] | AA5: Payment mechanism fee | AB5: Service fee & payment mechanism fees [(11) + (12)] | AC5: Taxes on service & payment mechanism fees (B) * 18% | AD5: Applicable amount for TCS | AE5: Applicable amount for 9(5) | AF5: Tax collected at source | AG5: TCS IGST amount | AH5: TDS 194O amount | AI5: GST paid by Zomato on behalf of restaurant - under section 9(5) | AJ5: GST to be paid by Restaurant partner to Govt. | AK5: Government charges [(13) + (16) + (17) + (18) + (19)] | AL5: Customer Compensation/Recoupment | AM5: Delivery Charges Recovery | AN5: Amount received in cash (on self delivery orders) | AO5: Credit note/(Debit Note) adjustment | AP5: Promo recovery adjustment | AQ5: Extra Inventory Ads and Misc. (order level deduction) | AR5: Brand loyalty points redemption | AS5: Express Order Fee | AT5: Other order-level deductions [(21) + (22) + (23) + (24) + (25) + (26) + (27) + (28)] | AU5: Net Deductions (B) + (C) + (D) | AV5: Net Additions (cancellation refund for cancelled orders/Tip for Kitchen Staff for delivered orders) | AW5: Order level Payout (A) - (E) + (F) | AX5: Settlement status | AY5: Settlement date | AZ5: Bank UTR | BA5: Unsettled Amount | BB5: Customer ID
A6: 1329 | B6: 7627298348 | C6: 2025-12-29 00:06:11 | D6: 1 | E6: Sha Sha - Shandaar Shawarma | F6: 18557902 | G6: NA | H6: ONLINE | I6: DELIVERED | J6: NA | K6: NA | L6: NA | M6: O2 | N6: 36 | O6: 219 | P6: 3.5 | Q6: 0 | R6: 0 | S6: 0 | T6: 0 | U6: 0 | V6: 11.13 | W6: 233.63 | X6: 222.5 | Y6: 19 | Z6: 42.28 | AA6: 4.3 | AB6: 46.58 | AC6: 8.38 | AD6: 0 | AE6: 222.5 | AF6: 0 | AG6: 0 | AH6: 0.22 | AI6: 11.13 | AJ6: 0 | AK6: 19.73 | AL6: 0 | AM6: 0 | AN6: 0 | AO6: 0 | AP6: 0 | AQ6: 0 | AR6: 0 | AS6: 0 | AT6: 0 | AU6: 66.31 | AV6: 0 | AW6: 167.32 | AX6: pending | AY6: NA | AZ6: NA | BA6: 167.32 | BB6: b52ddd28365af5e1641ce5e51625d590f1230bddc6951aa4275cbae432b7e926
A7: 1330 | B7: 7630160197 | C7: 2025-12-29 00:07:55 | D7: 1 | E7: Sha Sha - Shandaar Shawarma | F7: 18557902 | G7: 30% off upto ₹75 (2025-06-25 - 2031-01-01) | H7: ONLINE | I7: DELIVERED | J7: NA | K7: NA | L7: NA | M7: O2 | N7: 36 | O7: 229 | P7: 3.5 | Q7: 0 | R7: 68.7 | S7: 0 | T7: 0 | U7: 0 | V7: 8.19 | W7: 171.99 | X7: 163.8 | Y7: 19 | Z7: 31.12 | AA7: 3.16 | AB7: 34.28 | AC7: 6.17 | AD7: 0 | AE7: 163.8 | AF7: 0 | AG7: 0 | AH7: 0.16 | AI7: 8.2 | AJ7: -0.01 | AK7: 14.53 | AL7: 0 | AM7: 0 | AN7: 0 | AO7: 0 | AP7: 0 | AQ7: 0 | AR7: 0 | AS7: 0 | AT7: 0 | AU7: 48.81 | AV7: 0 | AW7: 123.18 | AX7: pending | AY7: NA | AZ7: NA | BA7: 123.18 | BB7: a39817aeaee6a6991ce2fc31128c474079bf29eba06129b46137ecd1a333d03a
A8: 1331 | B8: 7631989950 | C8: 2025-12-29 00:33:27 | D8: 1 | E8: Sha Sha - Shandaar Shawarma | F8: 18557902 | G8: 30% off upto ₹75 (2025-06-25 - 2031-01-01) | H8: ONLINE | I8: DELIVERED | J8: NA | K8: NA | L8: NA | M8: O2 | N8: 36 | O8: 229 | P8: 3.5 | Q8: 0 | R8: 68.7 | S8: 0 | T8: 0 | U8: 0 | V8: 8.19 | W8: 171.99 | X8: 163.8 | Y8: 19 | Z8: 31.12 | AA8: 3.16 | AB8: 34.28 | AC8: 6.17 | AD8: 0 | AE8: 163.8 | AF8: 0 | AG8: 0 | AH8: 0.16 | AI8: 8.2 | AJ8: -0.01 | AK8: 14.53 | AL8: 0 | AM8: 0 | AN8: 0 | AO8: 0 | AP8: 0 | AQ8: 0 | AR8: 0 | AS8: 0 | AT8: 0 | AU8: 48.81 | AV8: 0 | AW8: 123.18 | AX8: pending | AY8: NA | AZ8: NA | BA8: 123.18 | BB8: 2c40b43811deeaf97d2c548ebed00f7f803f0783c19b9553f8c497ef6e0807dd
A9: 1332 | B9: 7622994587 | C9: 2025-12-29 01:09:24 | D9: 1 | E9: Sha Sha - Shandaar Shawarma | F9: 18557902 | G9: 30% off upto ₹75 (2025-06-25 - 2031-01-01) | H9: ONLINE | I9: DELIVERED | J9: NA | K9: NA | L9: NA | M9: O2 | N9: 36 | O9: 229 | P9: 3.5 | Q9: 0 | R9: 68.7 | S9: 0 | T9: 0 | U9: 0 | V9: 8.19 | W9: 171.99 | X9: 163.8 | Y9: 19 | Z9: 31.12 | AA9: 3.16 | AB9: 34.28 | AC9: 6.17 | AD9: 0 | AE9: 163.8 | AF9: 0 | AG9: 0 | AH9: 0.16 | AI9: 8.2 | AJ9: -0.01 | AK9: 14.53 | AL9: 0 | AM9: 0 | AN9: 0 | AO9: 0 | AP9: 0 | AQ9: 0 | AR9: 0 | AS9: 0 | AT9: 0 | AU9: 48.81 | AV9: 0 | AW9: 123.18 | AX9: pending | AY9: NA | AZ9: NA | BA9: 123.18 | BB9: d679fca97540551daf9f3e2bb04cd72951a2f400717a57f5577b54b547a167a2
A10: 1333 | B10: 7625704361 | C10: 2025-12-29 01:10:29 | D10: 1 | E10: Sha Sha - Shandaar Shawarma | F10: 18557902 | G10: 30% off upto ₹75 (2025-06-25 - 2031-01-01) | H10: ONLINE | I10: DELIVERED | J10: NA | K10: NA | L10: NA | M10: O2 | N10: 36 | O10: 229 | P10: 3.5 | Q10: 0 | R10: 68.7 | S10: 0 | T10: 0 | U10: 0 | V10: 8.19 | W10: 171.99 | X10: 163.8 | Y10: 19 | Z10: 31.12 | AA10: 3.16 | AB10: 34.28 | AC10: 6.17 | AD10: 0 | AE10: 163.8 | AF10: 0 | AG10: 0 | AH10: 0.16 | AI10: 8.2 | AJ10: -0.01 | AK10: 14.53 | AL10: 0 | AM10: 0 | AN10: 0 | AO10: 0 | AP10: 0 | AQ10: 0 | AR10: 0 | AS10: 0 | AT10: 0 | AU10: 48.81 | AV10: 0 | AW10: 123.18 | AX10: pending | AY10: NA | AZ10: NA | BA10: 123.18 | BB10: ee42452f84666edbcf2cececb10851ea580ca8fa2d3cb6b22b3017c75a81b044
A11: 1334 | B11: 7626489175 | C11: 2025-12-29 01:15:31 | D11: 1 | E11: Sha Sha - Shandaar Shawarma | F11: 18557902 | G11: 30% off upto ₹75 (2025-06-25 - 2031-01-01) | H11: ONLINE | I11: DELIVERED | J11: NA | K11: NA | L11: NA | M11: O2 | N11: 36 | O11: 438 | P11: 3.5 | Q11: 0 | R11: 75 | S11: 0 | T11: 0 | U11: 0 | V11: 18.33 | W11: 384.83 | X11: 366.5 | Y11: 19 | Z11: 69.64 | AA11: 7.08 | AB11: 76.72 | AC11: 13.81 | AD11: 0 | AE11: 366.5 | AF11: 0 | AG11: 0 | AH11: 0.37 | AI11: 18.33 | AJ11: 0 | AK11: 32.51 | AL11: 0 | AM11: 0 | AN11: 0 | AO11: 0 | AP11: 0 | AQ11: 0 | AR11: 0 | AS11: 0 | AT11: 0 | AU11: 109.23 | AV11: 0 | AW11: 275.6 | AX11: pending | AY11: NA | AZ11: NA | BA11: 275.6 | BB11: 3e4eb44acf84c199de0787b4ed5b5e9e3ca6b52894cbf9fa6eba67e7d1ef17bb
A12: 1335 | B12: 7627213659 | C12: 2025-12-29 01:21:28 | D12: 1 | E12: Sha Sha - Shandaar Shawarma | F12: 18557902 | G12: 30% off upto ₹75 (2025-06-25 - 2031-01-01) | H12: ONLINE | I12: DELIVERED | J12: NA | K12: NA | L12: NA | M12: O2 | N12: 36 | O12: 229 | P12: 3.5 | Q12: 0 | R12: 68.7 | S12: 0 | T12: 0 | U12: 0 | V12: 8.19 | W12: 171.99 | X12: 163.8 | Y12: 19 | Z12: 31.12 | AA12: 3.16 | AB12: 34.28 | AC12: 6.17 | AD12: 0 | AE12: 163.8 | AF12: 0 | AG12: 0 | AH12: 0.16 | AI12: 8.2 | AJ12: -0.01 | AK12: 14.53 | AL12: 0 | AM12: 0 | AN12: 0 | AO12: 0 | AP12: 0 | AQ12: 0 | AR12: 0 | AS12: 0 | AT12: 0 | AU12: 48.81 | AV12: 0 | AW12: 123.18 | AX12: pending | AY12: NA | AZ12: NA | BA12: 123.18 | BB12: f59205a6412cd5d8fe633658ae0da95767dd06ef0e84e3115f815110c4b1996e
A13: 1336 | B13: 7629180195 | C13: 2025-12-29 01:43:49 | D13: 1 | E13: Sha Sha - Shandaar Shawarma | F13: 18557902 | G13: 30% off upto ₹75 (2025-06-25 - 2031-01-01) | H13: ONLINE | I13: DELIVERED | J13: NA | K13: NA | L13: NA | M13: O2 | N13: 36 | O13: 229 | P13: 3.5 | Q13: 0 | R13: 68.7 | S13: 0 | T13: 0 | U13: 0 | V13: 8.19 | W13: 171.99 | X13: 163.8 | Y13: 19 | Z13: 31.12 | AA13: 3.16 | AB13: 34.28 | AC13: 6.17 | AD13: 0 | AE13: 163.8 | AF13: 0 | AG13: 0 | AH13: 0.16 | AI13: 8.2 | AJ13: -0.01 | AK13: 14.53 | AL13: 0 | AM13: 0 | AN13: 0 | AO13: 0 | AP13: 0 | AQ13: 0 | AR13: 0 | AS13: 0 | AT13: 0 | AU13: 48.81 | AV13: 0 | AW13: 123.18 | AX13: pending | AY13: NA | AZ13: NA | BA13: 123.18 | BB13: ac959b86336b04b06bbbb58e74886ff52a964329cfc7eafa2e6b99e2490579d1
A14: 1337 | B14: 7630075935 | C14: 2025-12-29 02:53:37 | D14: 1 | E14: Sha Sha - Shandaar Shawarma | F14: 18557902 | G14: 30% off upto ₹75 (2025-06-25 - 2031-01-01) | H14: ONLINE | I14: DELIVERED | J14: NA | K14: NA | L14: NA | M14: O2 | N14: 36 | O14: 458 | P14: 3.5 | Q14: 0 | R14: 75 | S14: 0 | T14: 0 | U14: 0 | V14: 19.33 | W14: 405.83 | X14: 386.5 | Y14: 19 | Z14: 73.44 | AA14: 7.47 | AB14: 80.91 | AC14: 14.56 | AD14: 0 | AE14: 386.5 | AF14: 0 | AG14: 0 | AH14: 0.39 | AI14: 19.33 | AJ14: 0 | AK14: 34.28 | AL14: 0 | AM14: 0 | AN14: 0 | AO14: 0 | AP14: 0 | AQ14: 0 | AR14: 0 | AS14: 0 | AT14: 0 | AU14: 115.19 | AV14: 0 | AW14: 290.64 | AX14: pending | AY14: NA | AZ14: NA | BA14: 290.64 | BB14: 945287452aa5ad11f87700251aaf0044c7c8a7c57c42b16a7c26635b23a5fde2
A15: 1338 | B15: 7629439072 | C15: 2025-12-29 02:55:48 | D15: 1 | E15: Sha Sha - Shandaar Shawarma | F15: 18557902 | G15: 30% off upto ₹75 (2025-06-25 - 2031-01-01) | H15: ONLINE | I15: DELIVERED | J15: NA | K15: NA | L15: NA | M15: O2 | N15: 36 | O15: 229 | P15: 3.5 | Q15: 0 | R15: 68.7 | S15: 0 | T15: 0 | U15: 0 | V15: 8.19 | W15: 171.99 | X15: 163.8 | Y15: 19 | Z15: 31.12 | AA15: 3.16 | AB15: 34.28 | AC15: 6.17 | AD15: 0 | AE15: 163.8 | AF15: 0 | AG15: 0 | AH15: 0.16 | AI15: 8.2 | AJ15: -0.01 | AK15: 14.53 | AL15: 0 | AM15: 0 | AN15: 0 | AO15: 0 | AP15: 0 | AQ15: 0 | AR15: 0 | AS15: 0 | AT15: 0 | AU15: 48.81 | AV15: 0 | AW15: 123.18 | AX15: pending | AY15: NA | AZ15: NA | BA15: 123.18 | BB15: 0979936789ebba9999edb062312bf8c5646a59a822925a3cbacce9ed536795de
A16: 1339 | B16: 7628657878 | C16: 2025-12-29 03:26:40 | D16: 1 | E16: Sha Sha - Shandaar Shawarma | F16: 18557902 | G16: 30% off upto ₹75 (2025-06-25 - 2031-01-01) | H16: ONLINE | I16: DELIVERED | J16: NA | K16: NA | L16: NA | M16: O2 | N16: 36 | O16: 219 | P16: 3.5 | Q16: 0 | R16: 65.7 | S16: 0 | T16: 0 | U16: 0 | V16: 7.84 | W16: 164.64 | X16: 156.8 | Y16: 19 | Z16: 29.79 | AA16: 3.03 | AB16: 32.82 | AC16: 5.91 | AD16: 0 | AE16: 156.8 | AF16: 0 | AG16: 0 | AH16: 0.16 | AI16: 7.85 | AJ16: -0.01 | AK16: 13.92 | AL16: 0 | AM16: 0 | AN16: 0 | AO16: 0 | AP16: 0 | AQ16: 0 | AR16: 0 | AS16: 0 | AT16: 0 | AU16: 46.74 | AV16: 0 | AW16: 117.9 | AX16: pending | AY16: NA | AZ16: NA | BA16: 117.9 | BB16: c9228306f109933681c677df6011aae6d5fb256da584108caf344dd62263fdb0
A17: 1340 | B17: 7632064206 | C17: 2025-12-29 03:56:37 | D17: 1 | E17: Sha Sha - Shandaar Shawarma | F17: 18557902 | G17: 30% off upto ₹75 (2025-06-25 - 2031-01-01) | H17: ONLINE | I17: DELIVERED | J17: NA | K17: NA | L17: NA | M17: O2 | N17: 36 | O17: 229 | P17: 3.5 | Q17: 0 | R17: 68.7 | S17: 0 | T17: 0 | U17: 0 | V17: 8.19 | W17: 171.99 | X17: 163.8 | Y17: 19 | Z17: 31.12 | AA17: 3.16 | AB17: 34.28 | AC17: 6.17 | AD17: 0 | AE17: 163.8 | AF17: 0 | AG17: 0 | AH17: 0.16 | AI17: 8.2 | AJ17: -0.01 | AK17: 14.53 | AL17: 0 | AM17: 0 | AN17: 0 | AO17: 0 | AP17: 0 | AQ17: 0 | AR17: 0 | AS17: 0 | AT17: 0 | AU17: 48.81 | AV17: 0 | AW17: 123.18 | AX17: pending | AY17: NA | AZ17: NA | BA17: 123.18 | BB17: 713847dc42b86d834f871ed63b57d3df368288e9f483ef6816a7f4ef3c55dd50
... A120: 1443 | B120: 7642581989 | C120: 2025-12-31 22:43:36 | D120: 1 | E120: Sha Sha - Shandaar Shawarma | F120: 18557902 | G120: 30% off upto ₹75 (2025-06-25 - 2031-01-01) | H120: ONLINE | I120: DELIVERED | J120: NA | K120: NA | L120: NA | M120: O2 | N120: 36 | O120: 229 | P120: 3.5 | Q120: 0 | R120: 68.7 | S120: 0 | T120: 0 | U120: 0 | V120: 8.19 | W120: 171.99 | X120: 163.8 | Y120: 19 | Z120: 31.12 | AA120: 3.16 | AB120: 34.28 | AC120: 6.17 | AD120: 0 | AE120: 163.8 | AF120: 0 | AG120: 0 | AH120: 0.16 | AI120: 8.2 | AJ120: -0.01 | AK120: 14.53 | AL120: 0 | AM120: 0 | AN120: 0 | AO120: 0 | AP120: 0 | AQ120: 0 | AR120: 0 | AS120: 0 | AT120: 0 | AU120: 48.81 | AV120: 0 | AW120: 123.18 | AX120: pending | AY120: NA | AZ120: NA | BA120: 123.18 | BB120: d9c66d8e5421768c50927802f531271325204d901af44f6a4188d21cc1bd5115
