Workbook
Name Summary: #REF!

Sheet Paytm Reconciliation
A1: Sumadhura Shandaar Foods
A2: Paytm Reconciliation - December - 2026
A4: S. No | B4: Particulars | C4: Amount (₹) | I4: Percentage (%)
C5: 1st to 7th | D5: 8th to 14th | E5: 15th to 21st | F5: 22nd to 28th | G5: 29th to 31st | H5: Total
A6: 1 | B6: Sales (exclusive of GST) before failed and reversed transactions | C6: ='Paytm Calculations'!G2 | D6: ='Paytm Calculations'!H2 | E6: ='Paytm Calculations'!I2 | F6: ='Paytm Calculations'!J2 | G6: ='Paytm Calculations'!K2 | H6: =SUM(C6:G6) | I6: =H6/$H$10 | K6: =J6*100/105
B7: Failed transctions | C7: 0 | D7: 0 | E7: 0 | F7: 0 | G7: 0 | H7: =SUM(C7:G7) | I7: =H7/$H$10
B8: Sales (Exclucive of GST) after failed and reversed transactions | C8: =C6-C7 | D8: =D6-D7 | E8: =E6-E7 | F8: =F6-F7 | G8: =G6-G7 | H8: =H6-H7 | I8: =H8/$H$10
B9: add: GST @5% | C9: =C8*5% | D9: =D8*5% | E9: =E8*5% | F9: =F8*5% | G9: =G8*5% | H9: =SUM(C9:G9) | I9: =H9/$H$10
B10: Sales (inclusive of GST) | C10: =C8+C9 | D10: =D8+D9 | E10: =E8+E9 | F10: =F8+F9 | G10: =G8+G9 | H10: =SUM(C10:G10) | I10: =H10/$H$10
B11: Sales as per POS (Inclusive of GST) | H11: =SUM(C11:G11) | I11: =H11/$H$10
B12: Difference in POS | C12: =C11-C10 | D12: =D11-D10 | E12: =E11-E10 | F12: =F11-F10 | G12: =G11-G10 | H12: =SUM(C12:G12) | I12: =H12/$H$10
A14: 2 | B14: Commission & other charges
B15: Commission (Inclusive of GST) | C15: ='Paytm Calculations'!G3 | D15: ='Paytm Calculations'!H3 | E15: ='Paytm Calculations'!I3 | F15: ='Paytm Calculations'!J3 | G15: ='Paytm Calculations'!K3 | H15: =SUM(C15:G15) | I15: =H15/$H$10
B16: Total Commission & other charges | C16: =C15 | D16: =D15 | E16: =E15 | F16: =F15 | G16: =G15 | H16: =SUM(C16:G16) | I16: =H16/$H$10
A18: 3 | B18: Expected receipt in Bank Statement | C18: =C10-C16 | D18: =D10-D16 | E18: =E10-E16 | F18: =F10-F16 | G18: =G10-G16 | H18: =SUM(C18:G18) | I18: =H18/$H$10
B19: Actual Receipt in Bank Statement | H19: =SUM(C19:G19) | I19: =H19/$H$10
B20: Difference | C20: =C19-C18 | D20: =D19-D18 | E20: =E19-E18 | F20: =F19-F18 | G20: =G19-G18 | H20: =SUM(C20:G20) | I20: =H20/$H$10
A22: Note:
A23: 1. Due to the absence of source for last week considered from bank.
A24: 3. There is a difference between Amex Actual receipts and Expected receipts.Rs. 1,572.71/- is more in expected receipts
A25: 4. There is a difference in Paytm Actual receipts and Expected receipts, Rs. 99/- is more in expected receipts.

Sheet Paytm Calculations
G1: Week 1 | H1: Week 2 | I1: Week 3 | J1: Week 4 | K1: Week 5
G2: 92680.952 | H2: 85201.905 | I2: 78261.905 | J2: 87553.333 | K2: 16800.952
G3: 208.7538 | H3: 197.4612 | I3: 298.717 | J3: 247.2926 | K3: 25.9836
A10: Transaction_ID | B10: Order_ID | C10: Merchant_Unique_Ref | D10: Merchant_Request_Id | E10: Transaction_Date | F10: Updated_Date | G10: Transaction_Type | H10: Status | I10: MID | J10: Merchant_Name | K10: Customer_ID | L10: Customer_Nickname | M10: Payment_Mobile_Number | N10: Payment_Email_Id | O10: Amount | P10: Commission | Q10: GST | R10: Merchant_Order_ID | S10: Payout_ID | T10: Channel | U10: UTR_No. | V10: Payout_Date | W10: Settled_Date | X10: Payment_Mode | Y10: Issuing_Bank | Z10: Reference_Transaction_ID | AA10: POS_ID | AB10: Merchant_Ref_ID | AC10: External_Serial_No | AD10: Commission_Rate | AE10: Product_Code | AF10: GMV_Tier | AG10: Transaction_Slab | AH10: Request_Type | AI10: Refund_Type | AJ10: Refund_Actor | AK10: Split_Flag | AL10: Split_MID | AM10: Split_Id | AN10: Is_Split_Refund | AO10: Link_Description | AP10: Payment_Reference_Number | AQ10: Is_PRN_Validated | AR10: PRN_Validate_Time | AS10: Credit/Debit_Card_Last_4_Digits | AT10: Bank_Transaction_ID | AU10: Promo_Code | AV10: Promo_Response | AW10: Settled_Amount | AX10: PCF | AY10: PCF_GST | AZ10: FS_Offer_Fee | BA10: FS_Offer_GST | BB10: Response_code | BC10: Customer_VPA | BD10: Card_BIN | BE10: Customer_Details | BF10: Link_Name | BG10: Link_Notes | BH10: Response_message | BI10: Promo_discount_type | BJ10: Promo_Amount | BK10: Original_txn_value_before_promo | BL10: Total_Bill_Amount | BM10: Instant_Discount | BN10: MLV_Amount | BO10: Auth_Code | BP10: RRN | BQ10: Prepaid_Card | BR10: AdditionalComments | BS10: Charge_Target | BT10: Fee_Factor | BU10: Bank/Gateway | BV10: Card_Scheme | BW10: ACQUIRING_SERVICE_FEE | BX10: ACQUIRING_SERVICE_TAX | BY10: PLATFORM_SERVICE_FEE | BZ10: PLATFORM_SERVICE_TAX | CA10: Promo_Cart_Amount | CB10: Reseller_ID | CC10: Reseller_Name | CD10: Employee_Id | CE10: Employee_Name | CF10: Employee_PhoneNo | CG10: Employee_Email | CH10: User_Expected_Credit_Date | CI10: Order_Reason | CJ10: Customer_Account_Number | CK10: Customer_BANK_IFSC | CL10: TEMPLATE_ID | CM10: TEMPLATE_NAME | CN10: Foreign_Currency | CO10: Foreign_Currency_Name | CP10: Foreign_Amount | CQ10: Exchange_Rate | CR10: User_Markup_Rate | CS10: Refund_Source | CT10: Sub_Order_Status | CU10: Refund_Reversal_Id | CV10: Refund_Reversal_Status | CW10: Refund_Reversal_TimeStamp | CX10: Capture_Id | CY10: Pos_Date | CZ10: Pos_Time | DA10: Add_Money_Type | DB10: ARN | DC10: Gateway_Response_Code | DD10: Gateway_Response_Message | DE10: ARN_AVAILABILITY | DF10: Split_Reference_Id | DG10: UDF2 | DH10: UDF3 | DI10: IS_REVERSAL | DJ10: Settle_Type | DK10: Merchant_Payment_Detail_1 | DL10: Settlement_Bundle_Id | DM10: Settle_Factors | DN10: Is_Dqr_True | DO10: Customer_Convenience_Fee
A11: '20251201111030000202045111744948209' | B11: 'PTM50153de570c845648d55547c97ec2ceb' | E11: '2025-12-01 00:18:07' | F11: '2025-12-01 00:18:08' | G11: 'ACQUIRING' | H11: 'SUCCESS' | I11: 'TYXysH23627954956290' | J11: 'SHA SHA SHANDAAR SHAWARMA' | O11: 130 | P11: 0 | Q11: 0 | S11: 'AWSPG202512010001216820000806612997973' | T11: 'WAP' | U11: 'YESAP53363716979' | V11: '2025-12-01 00:01:00' | W11: '2025-12-02 04:36:23' | X11: 'UPI' | AA11: 'POS23985176461' | AC11: '5120120077791047681' | AE11: '51051000100000000001' | AH11: 'SEAMLESS_3D_FORM' | AO11: 'POS23985176461' | AT11: '533591462832' | AW11: 130 | AX11: 0 | AY11: 0 | BB11: '01' | BC11: '6300374561@pthdfc' | BH11: 'Txn Success' | BK11: 130 | BP11: '533591462832' | BQ11: 'false' | BR11: 'NA' | BS11: 'RECEIVER' | BT11: 'UPI|UPIPUSH|QR|PPBL' | BU11: 'PPBL' | BW11: 0 | BX11: 0 | CH11: 'UPI:null' | DJ11: 'BW'
A12: '20251201011000000202044341028631625' | B12: 'ICI6d5c9a1d44144ae7a96ee928c5af4edb' | E12: '2025-12-01 00:15:03' | F12: '2025-12-01 00:15:04' | G12: 'ACQUIRING' | H12: 'SUCCESS' | I12: 'TYXysH23627954956290' | J12: 'SHA SHA SHANDAAR SHAWARMA' | O12: 150 | P12: 0 | Q12: 0 | S12: 'AWSPG202512010001216820000806612997973' | T12: 'WAP' | U12: 'YESAP53363716979' | V12: '2025-12-01 00:01:00' | W12: '2025-12-02 04:36:23' | X12: 'UPI' | AA12: 'POS23985176461' | AC12: '5120120064635003913' | AE12: '51051000100000000001' | AH12: 'SEAMLESS_3D_FORM' | AT12: '570153307474' | AW12: 150 | AX12: 0 | AY12: 0 | BB12: '01' | BC12: 'mirzaakbarbaig231-3@okicici' | BH12: 'Txn Success' | BK12: 150 | BP12: '570153307474' | BQ12: 'false' | BR12: 'UPI' | BS12: 'RECEIVER' | BT12: 'UPI|UPIPUSH|QR|PPBL' | BU12: 'PPBL' | BW12: 0 | BX12: 0 | CH12: 'UPI:null' | DJ12: 'BW'
A13: '20251201010810000202044249534505180' | B13: 'APLAP4fd87161aa087a960178420847df76' | E13: '2025-12-01 00:14:41' | F13: '2025-12-01 00:14:42' | G13: 'ACQUIRING' | H13: 'SUCCESS' | I13: 'TYXysH23627954956290' | J13: 'SHA SHA SHANDAAR SHAWARMA' | O13: 190 | P13: 0 | Q13: 0 | S13: 'AWSPG202512010001216820000806612997973' | T13: 'WAP' | U13: 'YESAP53363716979' | V13: '2025-12-01 00:01:00' | W13: '2025-12-02 04:36:23' | X13: 'UPI' | AA13: 'POS23985176461' | AC13: '5120120062959237121' | AE13: '51051000100000000001' | AH13: 'SEAMLESS_3D_FORM' | AO13: 'POS23985176461' | AT13: '533502396913' | AW13: 190 | AX13: 0 | AY13: 0 | BB13: '01' | BC13: '7995232555@apl' | BH13: 'Txn Success' | BK13: 190 | BP13: '533502396913' | BQ13: 'false' | BR13: 'UPI' | BS13: 'RECEIVER' | BT13: 'UPI|UPIPUSH|QR|PPBL' | BU13: 'PPBL' | BW13: 0 | BX13: 0 | CH13: 'UPI:null' | DJ13: 'BW'
A14: '20251201011070000202084585476095638' | B14: 'SBI53e2e8921ce2436b88fdda87c18e86f8' | E14: '2025-12-01 02:54:58' | F14: '2025-12-01 02:55:00' | G14: 'ACQUIRING' | H14: 'SUCCESS' | I14: 'TYXysH23627954956290' | J14: 'SHA SHA SHANDAAR SHAWARMA' | O14: 130 | P14: 0 | Q14: 0 | S14: 'AWSPG202512010001216820000806612997973' | T14: 'WAP' | U14: 'YESAP53363716979' | V14: '2025-12-01 00:01:00' | W14: '2025-12-02 04:36:23' | X14: 'UPI' | AA14: 'POS23985176461' | AC14: '5120120785588296713' | AE14: '51051000100000000001' | AH14: 'SEAMLESS_3D_FORM' | AT14: '533598369432' | AW14: 130 | AX14: 0 | AY14: 0 | BB14: '01' | BC14: 'krishna202014@oksbi' | BH14: 'Txn Success' | BK14: 130 | BP14: '533598369432' | BQ14: 'false' | BR14: 'UPI' | BS14: 'RECEIVER' | BT14: 'UPI|UPIPUSH|QR|PPBL' | BU14: 'PPBL' | BW14: 0 | BX14: 0 | CH14: 'UPI:null' | DJ14: 'BW'
A15: '20251201010800000202081385591031189' | B15: 'T2512010242128663702126' | E15: '2025-12-01 02:42:15' | F15: '2025-12-01 02:42:16' | G15: 'ACQUIRING' | H15: 'SUCCESS' | I15: 'TYXysH23627954956290' | J15: 'SHA SHA SHANDAAR SHAWARMA' | O15: 80 | P15: 0 | Q15: 0 | S15: 'AWSPG202512010001216820000806612997973' | T15: 'WAP' | U15: 'YESAP53363716979' | V15: '2025-12-01 00:01:00' | W15: '2025-12-02 04:36:23' | X15: 'UPI' | AA15: 'POS23985176461' | AC15: '5120120731229848577' | AE15: '51051000100000000001' | AH15: 'SEAMLESS_3D_FORM' | AT15: '099501640518' | AW15: 80 | AX15: 0 | AY15: 0 | BB15: '01' | BC15: '7760037134@axl' | BH15: 'Txn Success' | BK15: 80 | BP15: '099501640518' | BQ15: 'false' | BR15: 'Payment from PhonePe' | BS15: 'RECEIVER' | BT15: 'UPI|UPIPUSH|QR|PPBL' | BU15: 'PPBL' | BW15: 0 | BX15: 0 | CH15: 'UPI:null' | DJ15: 'BW'
A16: '20251201010930000202079816158738527' | B16: 'T2512010235589711857234' | E16: '2025-12-01 02:36:01' | F16: '2025-12-01 02:36:02' | G16: 'ACQUIRING' | H16: 'SUCCESS' | I16: 'TYXysH23627954956290' | J16: 'SHA SHA SHANDAAR SHAWARMA' | O16: 600 | P16: 0 | Q16: 0 | S16: 'AWSPG202512010001216820000806612997973' | T16: 'WAP' | U16: 'YESAP53363716979' | V16: '2025-12-01 00:01:00' | W16: '2025-12-02 04:36:23' | X16: 'UPI' | AA16: 'POS23985176461' | AC16: '5120120704450280453' | AE16: '51051000100000000001' | AH16: 'SEAMLESS_3D_FORM' | AT16: '265456750126' | AW16: 600 | AX16: 0 | AY16: 0 | BB16: '01' | BC16: '7760037134@ybl' | BH16: 'Txn Success' | BK16: 600 | BP16: '265456750126' | BQ16: 'false' | BR16: 'Payment from PhonePe' | BS16: 'RECEIVER' | BT16: 'UPI|UPIPUSH|QR|PPBL' | BU16: 'PPBL' | BW16: 0 | BX16: 0 | CH16: 'UPI:null' | DJ16: 'BW'
A17: '20251201111110000202079126387765020' | B17: 'T2512010233088017497476' | E17: '2025-12-01 02:33:17' | F17: '2025-12-01 02:33:18' | G17: 'ACQUIRING' | H17: 'SUCCESS' | I17: 'TYXysH23627954956290' | J17: 'SHA SHA SHANDAAR SHAWARMA' | O17: 160 | P17: 0 | Q17: 0 | S17: 'AWSPG202512010001216820000806612997973' | T17: 'WAP' | U17: 'YESAP53363716979' | V17: '2025-12-01 00:01:00' | W17: '2025-12-02 04:36:23' | X17: 'UPI' | AA17: 'POS23985176461' | AC17: '5120120692639733765' | AE17: '51051000100000000001' | AH17: 'SEAMLESS_3D_FORM' | AT17: '871135800951' | AW17: 160 | AX17: 0 | AY17: 0 | BB17: '01' | BC17: 'saicrazy9871@axl' | BH17: 'Txn Success' | BK17: 160 | BP17: '871135800951' | BQ17: 'false' | BR17: 'Payment from PhonePe' | BS17: 'RECEIVER' | BT17: 'UPI|UPIPUSH|QR|PPBL' | BU17: 'PPBL' | BW17: 0 | BX17: 0 | CH17: 'UPI:null' | DJ17: 'BW'
A18: '20251201110810000202076593653131174' | B18: 'SBIb149b0de4e754a308a82a5e450f71ac7' | E18: '2025-12-01 02:23:13' | F18: '2025-12-01 02:23:14' | G18: 'ACQUIRING' | H18: 'SUCCESS' | I18: 'TYXysH23627954956290' | J18: 'SHA SHA SHANDAAR SHAWARMA' | O18: 130 | P18: 0 | Q18: 0 | S18: 'AWSPG202512010001216820000806612997973' | T18: 'WAP' | U18: 'YESAP53363716979' | V18: '2025-12-01 00:01:00' | W18: '2025-12-02 04:36:23' | X18: 'UPI' | AA18: 'POS23985176461' | AC18: '5120120649424143381' | AE18: '51051000100000000001' | AH18: 'SEAMLESS_3D_FORM' | AT18: '533598337683' | AW18: 130 | AX18: 0 | AY18: 0 | BB18: '01' | BC18: 'atishkumardas695@oksbi' | BH18: 'Txn Success' | BK18: 130 | BP18: '533598337683' | BQ18: 'false' | BR18: 'UPI' | BS18: 'RECEIVER' | BT18: 'UPI|UPIPUSH|QR|PPBL' | BU18: 'PPBL' | BW18: 0 | BX18: 0 | CH18: 'UPI:null' | DJ18: 'BW'
A19: '20251201110930000202074859158293906' | B19: 'SMTXA7DOX3CTL1YUUB4PNU88CPTEPLN1XSL' | E19: '2025-12-01 02:16:19' | F19: '2025-12-01 02:16:20' | G19: 'ACQUIRING' | H19: 'SUCCESS' | I19: 'TYXysH23627954956290' | J19: 'SHA SHA SHANDAAR SHAWARMA' | O19: 260 | P19: 0 | Q19: 0 | S19: 'AWSPG202512010001216820000806612997973' | T19: 'WAP' | U19: 'YESAP53363716979' | V19: '2025-12-01 00:01:00' | W19: '2025-12-02 04:36:23' | X19: 'UPI' | AA19: 'POS23985176461' | AC19: '5120120619825860609' | AE19: '51051000100000000001' | AH19: 'SEAMLESS_3D_FORM' | AO19: 'POS23985176461' | AT19: '533516033492' | AW19: 260 | AX19: 0 | AY19: 0 | BB19: '01' | BC19: '9381813984@superyes' | BH19: 'Txn Success' | BK19: 260 | BP19: '533516033492' | BQ19: 'false' | BR19: 'Paid via SuperMoney UPI' | BS19: 'RECEIVER' | BT19: 'UPI|UPIPUSH|QR|PPBL' | BU19: 'PPBL' | BW19: 0 | BX19: 0 | CH19: 'UPI:null' | DJ19: 'BW'
A20: '20251201111000000202074763364020221' | B20: 'ICI5c260f42b603471dadf8a76d1a0fad54' | E20: '2025-12-01 02:15:57' | F20: '2025-12-01 02:15:57' | G20: 'ACQUIRING' | H20: 'SUCCESS' | I20: 'TYXysH23627954956290' | J20: 'SHA SHA SHANDAAR SHAWARMA' | O20: 130 | P20: 0 | Q20: 0 | S20: 'AWSPG202512010001216820000806612997973' | T20: 'WAP' | U20: 'YESAP53363716979' | V20: '2025-12-01 00:01:00' | W20: '2025-12-02 04:36:23' | X20: 'UPI' | AA20: 'POS23985176461' | AC20: '5120120618014133253' | AE20: '51051000100000000001' | AH20: 'SEAMLESS_3D_FORM' | AT20: '570129807603' | AW20: 130 | AX20: 0 | AY20: 0 | BB20: '01' | BC20: 'abbusher56@okicici' | BH20: 'Txn Success' | BK20: 130 | BP20: '570129807603' | BQ20: 'false' | BR20: 'UPI' | BS20: 'RECEIVER' | BT20: 'UPI|UPIPUSH|QR|PPBL' | BU20: 'PPBL' | BW20: 0 | BX20: 0 | CH20: 'UPI:null' | DJ20: 'BW'
A21: '20251201110900000202072296136376046' | B21: '533502752219' | E21: '2025-12-01 02:06:08' | F21: '2025-12-01 02:06:09' | G21: 'ACQUIRING' | H21: 'SUCCESS' | I21: 'TYXysH23627954956290' | J21: 'SHA SHA SHANDAAR SHAWARMA' | O21: 150 | P21: 0 | Q21: 0 | S21: 'AWSPG202512010001216820000806612997973' | T21: 'WAP' | U21: 'YESAP53363716979' | V21: '2025-12-01 00:01:00' | W21: '2025-12-02 04:36:23' | X21: 'UPI' | AA21: 'POS23985176461' | AC21: '5120120576074257433' | AE21: '51051000100000000001' | AH21: 'SEAMLESS_3D_FORM' | AO21: 'POS23985176461' | AT21: '533502752219' | AW21: 150 | AX21: 0 | AY21: 0 | BB21: '01' | BC21: '9676173003@kotak811' | BH21: 'Txn Success' | BK21: 150 | BP21: '533502752219' | BQ21: 'false' | BR21: 'UPI' | BS21: 'RECEIVER' | BT21: 'UPI|UPIPUSH|QR|PPBL' | BU21: 'PPBL' | BW21: 0 | BX21: 0 | CH21: 'UPI:null' | DJ21: 'BW'
A22: '20251201111020000202071006827746874' | B22: 'T2512010200579249516858' | E22: '2025-12-01 02:01:01' | F22: '2025-12-01 02:01:02' | G22: 'ACQUIRING' | H22: 'SUCCESS' | I22: 'TYXysH23627954956290' | J22: 'SHA SHA SHANDAAR SHAWARMA' | O22: 130 | P22: 0 | Q22: 0 | S22: 'AWSPG202512010001216820000806612997973' | T22: 'WAP' | U22: 'YESAP53363716979' | V22: '2025-12-01 00:01:00' | W22: '2025-12-02 04:36:23' | X22: 'UPI' | AA22: 'POS23985176461' | AC22: '5120120554129852421' | AE22: '51051000100000000001' | AH22: 'SEAMLESS_3D_FORM' | AT22: '448241477611' | AW22: 130 | AX22: 0 | AY22: 0 | BB22: '01' | BC22: '8184898815@ybl' | BH22: 'Txn Success' | BK22: 130 | BP22: '448241477611' | BQ22: 'false' | BR22: 'Payment from PhonePe' | BS22: 'RECEIVER' | BT22: 'UPI|UPIPUSH|QR|PPBL' | BU22: 'PPBL' | BW22: 0 | BX22: 0 | CH22: 'UPI:null' | DJ22: 'BW'
A23: '20251201010930000202067321951452168' | B23: 'PTM6bd74fe6f0c04cfbb5d33dcbe68a2e0b' | E23: '2025-12-01 01:46:22' | F23: '2025-12-01 01:46:24' | G23: 'ACQUIRING' | H23: 'SUCCESS' | I23: 'TYXysH23627954956290' | J23: 'SHA SHA SHANDAAR SHAWARMA' | O23: 130 | P23: 0 | Q23: 0 | S23: 'AWSPG202512010001216820000806612997973' | T23: 'WAP' | U23: 'YESAP53363716979' | V23: '2025-12-01 00:01:00' | W23: '2025-12-02 04:36:23' | X23: 'UPI' | AA23: 'POS23985176461' | AC23: '5120130473932899333' | AE23: '51051000100000000001' | AH23: 'SEAMLESS_3D_FORM' | AO23: 'POS23985176461' | AT23: '393092296018' | AW23: 130 | AX23: 0 | AY23: 0 | BB23: '01' | BC23: '9392032356@ptyes' | BH23: 'Txn Success' | BK23: 130 | BP23: '393092296018' | BQ23: 'false' | BR23: 'NA' | BS23: 'RECEIVER' | BT23: 'UPI|UPIPUSH|QR|PPBL' | BU23: 'PPBL' | BW23: 0 | BX23: 0 | CH23: 'UPI:null' | DJ23: 'BW'
A24: '20251201010930000202061357303047348' | B24: 'APYAP2818fdc815727fa8adff5758ebb573' | E24: '2025-12-01 01:22:40' | F24: '2025-12-01 01:22:41' | G24: 'ACQUIRING' | H24: 'SUCCESS' | I24: 'TYXysH23627954956290' | J24: 'SHA SHA SHANDAAR SHAWARMA' | O24: 560 | P24: 0 | Q24: 0 | S24: 'AWSPG202512010001216820000806612997973' | T24: 'WAP' | U24: 'YESAP53363716979' | V24: '2025-12-01 00:01:00' | W24: '2025-12-02 04:36:23' | X24: 'UPI' | AA24: 'POS23985176461' | AC24: '5120120372062494729' | AE24: '51051000100000000001' | AH24: 'SEAMLESS_3D_FORM' | AO24: 'POS23985176461' | AT24: '533532976604' | AW24: 560 | AX24: 0 | AY24: 0 | BB24: '01' | BC24: '9553675243@yapl' | BH24: 'Txn Success' | BK24: 560 | BP24: '533532976604' | BQ24: 'false' | BR24: 'UPI' | BS24: 'RECEIVER' | BT24: 'UPI|UPIPUSH|QR|PPBL' | BU24: 'PPBL' | BW24: 0 | BX24: 0 | CH24: 'UPI:null' | DJ24: 'BW'
A25: '20251201110980000202059987229568166' | B25: 'ICI08d5aa7dd0684d95925838802331df58' | E25: '2025-12-01 01:17:14' | F25: '2025-12-01 01:17:15' | G25: 'ACQUIRING' | H25: 'SUCCESS' | I25: 'TYXysH23627954956290' | J25: 'SHA SHA SHANDAAR SHAWARMA' | O25: 130 | P25: 0 | Q25: 0 | S25: 'AWSPG202512010001216820000806612997973' | T25: 'WAP' | U25: 'YESAP53363716979' | V25: '2025-12-01 00:01:00' | W25: '2025-12-02 04:36:23' | X25: 'UPI' | AA25: 'POS23985176461' | AC25: '5120120348841217025' | AE25: '51051000100000000001' | AH25: 'SEAMLESS_3D_FORM' | AT25: '533577494409' | AW25: 130 | AX25: 0 | AY25: 0 | BB25: '01' | BC25: 'swastikdudiwar04-1@okicici' | BH25: 'Txn Success' | BK25: 130 | BP25: '533577494409' | BQ25: 'false' | BR25: 'UPI' | BS25: 'RECEIVER' | BT25: 'UPI|UPIPUSH|QR|PPBL' | BU25: 'PPBL' | BW25: 0 | BX25: 0 | CH25: 'UPI:null' | DJ25: 'BW'
A26: '20251201111020000202059795113450612' | B26: 'T2512010116247364989867' | E26: '2025-12-01 01:16:28' | F26: '2025-12-01 01:16:29' | G26: 'ACQUIRING' | H26: 'SUCCESS' | I26: 'TYXysH23627954956290' | J26: 'SHA SHA SHANDAAR SHAWARMA' | O26: 150 | P26: 0 | Q26: 0 | S26: 'AWSPG202512010001216820000806612997973' | T26: 'WAP' | U26: 'YESAP53363716979' | V26: '2025-12-01 00:01:00' | W26: '2025-12-02 04:36:23' | X26: 'UPI' | AA26: 'POS23985176461' | AC26: '5120120345487832065' | AE26: '51051000100000000001' | AH26: 'SEAMLESS_3D_FORM' | AT26: '145783564866' | AW26: 150 | AX26: 0 | AY26: 0 | BB26: '01' | BC26: 'rakeshrao16@ybl' | BH26: 'Txn Success' | BK26: 150 | BP26: '145783564866' | BQ26: 'false' | BR26: 'Payment from PhonePe' | BS26: 'RECEIVER' | BT26: 'UPI|UPIPUSH|QR|PPBL' | BU26: 'PPBL' | BW26: 0 | BX26: 0 | CH26: 'UPI:null' | DJ26: 'BW'
A27: '20251201110930000202056517306916738' | B27: 'T2512010103234044989730' | E27: '2025-12-01 01:03:26' | F27: '2025-12-01 01:03:28' | G27: 'ACQUIRING' | H27: 'SUCCESS' | I27: 'TYXysH23627954956290' | J27: 'SHA SHA SHANDAAR SHAWARMA' | O27: 150 | P27: 0 | Q27: 0 | S27: 'AWSPG202512010001216820000806612997973' | T27: 'WAP' | U27: 'YESAP53363716979' | V27: '2025-12-01 00:01:00' | W27: '2025-12-02 04:36:23' | X27: 'UPI' | AA27: 'POS23985176461' | AC27: '5120130289518796825' | AE27: '51051000100000000001' | AH27: 'SEAMLESS_3D_FORM' | AT27: '206785215579' | AW27: 150 | AX27: 0 | AY27: 0 | BB27: '01' | BC27: 'lokeshrocky007@axl' | BH27: 'Txn Success' | BK27: 150 | BP27: '206785215579' | BQ27: 'false' | BR27: 'Payment from PhonePe' | BS27: 'RECEIVER' | BT27: 'UPI|UPIPUSH|QR|PPBL' | BU27: 'PPBL' | BW27: 0 | BX27: 0 | CH27: 'UPI:null' | DJ27: 'BW'
A28: '20251201111070000202056514530740086' | B28: 'SBId42358f9a120414e90714a8a9f3befed' | E28: '2025-12-01 01:03:26' | F28: '2025-12-01 01:03:27' | G28: 'ACQUIRING' | H28: 'SUCCESS' | I28: 'TYXysH23627954956290' | J28: 'SHA SHA SHANDAAR SHAWARMA' | O28: 250 | P28: 0 | Q28: 0 | S28: 'AWSPG202512010001216820000806612997973' | T28: 'WAP' | U28: 'YESAP53363716979' | V28: '2025-12-01 00:01:00' | W28: '2025-12-02 04:36:23' | X28: 'UPI' | AA28: 'POS23985176461' | AC28: '5120120289518154753' | AE28: '51051000100000000001' | AH28: 'SEAMLESS_3D_FORM' | AT28: '533598112288' | AW28: 250 | AX28: 0 | AY28: 0 | BB28: '01' | BC28: 'shaikomer70977@oksbi' | BH28: 'Txn Success' | BK28: 250 | BP28: '533598112288' | BQ28: 'false' | BR28: 'UPI' | BS28: 'RECEIVER' | BT28: 'UPI|UPIPUSH|QR|PPBL' | BU28: 'PPBL' | BW28: 0 | BX28: 0 | CH28: 'UPI:null' | DJ28: 'BW'
A29: '20251201010800000202055686167673128' | B29: 'T2512010100053809720941' | E29: '2025-12-01 01:00:08' | F29: '2025-12-01 01:00:09' | G29: 'ACQUIRING' | H29: 'SUCCESS' | I29: 'TYXysH23627954956290' | J29: 'SHA SHA SHANDAAR SHAWARMA' | O29: 120 | P29: 0 | Q29: 0 | S29: 'AWSPG202512010001216820000806612997973' | T29: 'WAP' | U29: 'YESAP53363716979' | V29: '2025-12-01 00:01:00' | W29: '2025-12-02 04:36:23' | X29: 'UPI' | AA29: 'POS23985176461' | AC29: '5120120275427011585' | AE29: '51051000100000000001' | AH29: 'SEAMLESS_3D_FORM' | AT29: '384415721810' | AW29: 120 | AX29: 0 | AY29: 0 | BB29: '01' | BC29: 'ashraygolu@axl' | BH29: 'Txn Success' | BK29: 120 | BP29: '384415721810' | BQ29: 'false' | BR29: 'Payment from PhonePe' | BS29: 'RECEIVER' | BT29: 'UPI|UPIPUSH|QR|PPBL' | BU29: 'PPBL' | BW29: 0 | BX29: 0 | CH29: 'UPI:null' | DJ29: 'BW'
A30: '20251201110870000202051238309956537' | B30: 'PTM398e4c0a5bb54ac0aebfd8b114f8b71c' | E30: '2025-12-01 00:42:28' | F30: '2025-12-01 00:42:29' | G30: 'ACQUIRING' | H30: 'SUCCESS' | I30: 'TYXysH23627954956290' | J30: 'SHA SHA SHANDAAR SHAWARMA' | O30: 130 | P30: 0 | Q30: 0 | S30: 'AWSPG202512010001216820000806612997973' | T30: 'WAP' | U30: 'YESAP53363716979' | V30: '2025-12-01 00:01:00' | W30: '2025-12-02 04:36:23' | X30: 'UPI_LITE' | AA30: 'POS23985176461' | AC30: '5120120182277944325' | AE30: '51051000100000000001' | AH30: 'SEAMLESS_3D_FORM' | AO30: 'POS23985176461' | AT30: '393092069508' | AW30: 130 | AX30: 0 | AY30: 0 | BB30: '01' | BC30: '9553850189@ptyes' | BH30: 'Txn Success' | BK30: 130 | BP30: '393092069508' | BQ30: 'false' | BR30: 'NA' | BS30: 'RECEIVER' | BT30: 'UPI|UPIPUSH|QR|UPI_LITE|PPBL' | BU30: 'PPBL' | BW30: 0 | BX30: 0 | CH30: 'UPI:null' | DJ30: 'BW'
A31: '20251201110980000202048066783087738' | B31: 'T2512010029488609291803' | E31: '2025-12-01 00:29:52' | F31: '2025-12-01 00:29:53' | G31: 'ACQUIRING' | H31: 'SUCCESS' | I31: 'TYXysH23627954956290' | J31: 'SHA SHA SHANDAAR SHAWARMA' | O31: 150 | P31: 0 | Q31: 0 | S31: 'AWSPG202512010001216820000806612997973' | T31: 'WAP' | U31: 'YESAP53363716979' | V31: '2025-12-01 00:01:00' | W31: '2025-12-02 04:36:23' | X31: 'UPI' | AA31: 'POS23985176461' | AC31: '5120120128053679105' | AE31: '51051000100000000001' | AH31: 'SEAMLESS_3D_FORM' | AT31: '732375943494' | AW31: 150 | AX31: 0 | AY31: 0 | BB31: '01' | BC31: '8475800314-4@ybl' | BH31: 'Txn Success' | BK31: 150 | BP31: '732375943494' | BQ31: 'false' | BR31: 'Payment from PhonePe' | BS31: 'RECEIVER' | BT31: 'UPI|UPIPUSH|QR|PPBL' | BU31: 'PPBL' | BW31: 0 | BX31: 0 | CH31: 'UPI:null' | DJ31: 'BW'
A32: '20251201110930000202048019151860293' | B32: 'PTM8a5044a515fc43299dc6bbfeefb7cbcd' | E32: '2025-12-01 00:29:40' | F32: '2025-12-01 00:29:43' | G32: 'ACQUIRING' | H32: 'SUCCESS' | I32: 'TYXysH23627954956290' | J32: 'SHA SHA SHANDAAR SHAWARMA' | O32: 130 | P32: 2.95 | Q32: 0.53 | S32: 'AWSPG202512010001216820000806612997973' | T32: 'WAP' | U32: 'YESAP53363716979' | V32: '2025-12-01 00:01:00' | W32: '2025-12-02 04:36:23' | X32: 'UPI_CREDIT_CARD' | AA32: 'POS23985176461' | AC32: '5120120127248055297' | AE32: '51051000100000000001' | AH32: 'SEAMLESS_3D_FORM' | AO32: 'POS23985176461' | AT32: '393092001067' | AW32: 126.52 | AX32: 0 | AY32: 0 | BB32: '01' | BC32: 'vinaytejauppada@ptyes' | BH32: 'Txn Success' | BK32: 130 | BP32: '393092001067' | BQ32: 'false' | BR32: 'NA' | BS32: 'RECEIVER' | BT32: 'UPI|UPIPUSH|QR|UPI_CREDIT_CARD|PPBL|Platinum|upiCc' | BU32: 'PPBL' | BW32: 2.95 | BX32: 0.53 | CH32: 'UPI:null' | DJ32: 'BW'
A33: '20251201110890000202047677421673281' | B33: 'T2512010028163267996878' | E33: '2025-12-01 00:28:19' | F33: '2025-12-01 00:28:20' | G33: 'ACQUIRING' | H33: 'SUCCESS' | I33: 'TYXysH23627954956290' | J33: 'SHA SHA SHANDAAR SHAWARMA' | O33: 150 | P33: 3.41 | Q33: 0.61 | S33: 'AWSPG202512010001216820000806612997973' | T33: 'WAP' | U33: 'YESAP53363716979' | V33: '2025-12-01 00:01:00' | W33: '2025-12-02 04:36:23' | X33: 'UPI_CREDIT_CARD' | AA33: 'POS23985176461' | AC33: '5120120121544119301' | AE33: '51051000100000000001' | AH33: 'SEAMLESS_3D_FORM' | AO33: 'POS23985176461' | AT33: '862735782198' | AW33: 145.98 | AX33: 0 | AY33: 0 | BB33: '01' | BC33: '7396916992-5@axl' | BH33: 'Txn Success' | BK33: 150 | BP33: '862735782198' | BQ33: 'false' | BR33: 'Payment from PhonePe' | BS33: 'RECEIVER' | BT33: 'UPI|UPIPUSH|QR|UPI_CREDIT_CARD|PPBL|JCB Platinum|upiCc' | BU33: 'PPBL' | BW33: 3.41 | BX33: 0.61 | CH33: 'UPI:null' | DJ33: 'BW'
A34: '20251201011070000202111174763109551' | B34: 'T2512010440323444241629' | E34: '2025-12-01 04:40:38' | F34: '2025-12-01 04:40:39' | G34: 'ACQUIRING' | H34: 'SUCCESS' | I34: 'TYXysH23627954956290' | J34: 'SHA SHA SHANDAAR SHAWARMA' | O34: 300 | P34: 0 | Q34: 0 | S34: 'AWSPG202512010001216820000806612997973' | T34: 'WAP' | U34: 'YESAP53363716979' | V34: '2025-12-01 00:01:00' | W34: '2025-12-02 04:36:23' | X34: 'UPI' | AA34: 'POS23985176461' | AC34: '5120131273870057473' | AE34: '51051000100000000001' | AH34: 'SEAMLESS_3D_FORM' | AT34: '615599481708' | AW34: 300 | AX34: 0 | AY34: 0 | BB34: '01' | BC34: '60021725120@ybl' | BH34: 'Txn Success' | BK34: 300 | BP34: '615599481708' | BQ34: 'false' | BR34: 'Payment from PhonePe' | BS34: 'RECEIVER' | BT34: 'UPI|UPIPUSH|QR|PPBL' | BU34: 'PPBL' | BW34: 0 | BX34: 0 | CH34: 'UPI:null' | DJ34: 'BW'
A35: '20251201011020000202106274964062649' | B35: 'SBI5308a2aeb94f4644857ca0ef42b1b4c8' | E35: '2025-12-01 04:21:09' | F35: '2025-12-01 04:21:11' | G35: 'ACQUIRING' | H35: 'SUCCESS' | I35: 'TYXysH23627954956290' | J35: 'SHA SHA SHANDAAR SHAWARMA' | O35: 520 | P35: 0 | Q35: 0 | S35: 'AWSPG202512010001216820000806612997973' | T35: 'WAP' | U35: 'YESAP53363716979' | V35: '2025-12-01 00:01:00' | W35: '2025-12-02 04:36:23' | X35: 'UPI' | AA35: 'POS23985176461' | AC35: '5120121190388898817' | AE35: '51051000100000000001' | AH35: 'SEAMLESS_3D_FORM' | AT35: '533598469718' | AW35: 520 | AX35: 0 | AY35: 0 | BB35: '01' | BC35: 'www.mohds9824@oksbi' | BH35: 'Txn Success' | BK35: 520 | BP35: '533598469718' | BQ35: 'false' | BR35: 'UPI' | BS35: 'RECEIVER' | BT35: 'UPI|UPIPUSH|QR|PPBL' | BU35: 'PPBL' | BW35: 0 | BX35: 0 | CH35: 'UPI:null' | DJ35: 'BW'
A36: '20251201110990000202256898070617275' | B36: 'ICI99b143cda7514aad98b1af3baa7596ca' | E36: '2025-12-01 14:19:41' | F36: '2025-12-01 14:19:42' | G36: 'ACQUIRING' | H36: 'SUCCESS' | I36: 'TYXysH23627954956290' | J36: 'SHA SHA SHANDAAR SHAWARMA' | O36: 180 | P36: 0 | Q36: 0 | S36: 'AWSPG202512010001216820000806612997973' | T36: 'WAP' | U36: 'YESAP53363716979' | V36: '2025-12-01 00:01:00' | W36: '2025-12-02 04:36:23' | X36: 'UPI' | AA36: 'POS23985176461' | AC36: '5120123932655588365' | AE36: '51051000100000000001' | AH36: 'SEAMLESS_3D_FORM' | AT36: '570176430602' | AW36: 180 | AX36: 0 | AY36: 0 | BB36: '01' | BC36: 'nandaandrajula@okicici' | BH36: 'Txn Success' | BK36: 180 | BP36: '570176430602' | BQ36: 'false' | BR36: 'UPI' | BS36: 'RECEIVER' | BT36: 'UPI|UPIPUSH|QR|PPBL' | BU36: 'PPBL' | BW36: 0 | BX36: 0 | CH36: 'UPI:null' | DJ36: 'BW'
A37: '20251201110950000202250950132980344' | B37: 'HDFff1520f87c5340749e6b743a7d7466d4' | E37: '2025-12-01 13:56:03' | F37: '2025-12-01 13:56:04' | G37: 'ACQUIRING' | H37: 'SUCCESS' | I37: 'TYXysH23627954956290' | J37: 'SHA SHA SHANDAAR SHAWARMA' | O37: 20 | P37: 0 | Q37: 0 | S37: 'AWSPG202512010001216820000806612997973' | T37: 'WAP' | U37: 'YESAP53363716979' | V37: '2025-12-01 00:01:00' | W37: '2025-12-02 04:36:23' | X37: 'UPI' | AA37: 'POS23985176461' | AC37: '5120123814140744729' | AE37: '51051000100000000001' | AH37: 'SEAMLESS_3D_FORM' | AT37: '114956415119' | AW37: 20 | AX37: 0 | AY37: 0 | BB37: '01' | BC37: 'finearttattoos8@okhdfcbank' | BH37: 'Txn Success' | BK37: 20 | BP37: '114956415119' | BQ37: 'false' | BR37: 'UPI' | BS37: 'RECEIVER' | BT37: 'UPI|UPIPUSH|QR|PPBL' | BU37: 'PPBL' | BW37: 0 | BX37: 0 | CH37: 'UPI:null' | DJ37: 'BW'
A38: '20251201011060000202250828543927587' | B38: 'HDF36f01acfb1864a45be2fbd9871642a7f' | E38: '2025-12-01 13:55:34' | F38: '2025-12-01 13:55:35' | G38: 'ACQUIRING' | H38: 'SUCCESS' | I38: 'TYXysH23627954956290' | J38: 'SHA SHA SHANDAAR SHAWARMA' | O38: 20 | P38: 0 | Q38: 0 | S38: 'AWSPG202512010001216820000806612997973' | T38: 'WAP' | U38: 'YESAP53363716979' | V38: '2025-12-01 00:01:00' | W38: '2025-12-02 04:36:23' | X38: 'UPI' | AA38: 'POS23985176461' | AC38: '5120123811929758738' | AE38: '51051000100000000001' | AH38: 'SEAMLESS_3D_FORM' | AT38: '114956384701' | AW38: 20 | AX38: 0 | AY38: 0 | BB38: '01' | BC38: 'finearttattoos8@okhdfcbank' | BH38: 'Txn Success' | BK38: 20 | BP38: '114956384701' | BQ38: 'false' | BR38: 'UPI' | BS38: 'RECEIVER' | BT38: 'UPI|UPIPUSH|QR|PPBL' | BU38: 'PPBL' | BW38: 0 | BX38: 0 | CH38: 'UPI:null' | DJ38: 'BW'
A39: '20251201111080000202250591414773655' | B39: 'HDFdee66926140e4e36abb782c3c5729e07' | E39: '2025-12-01 13:54:37' | F39: '2025-12-01 13:54:39' | G39: 'ACQUIRING' | H39: 'SUCCESS' | I39: 'TYXysH23627954956290' | J39: 'SHA SHA SHANDAAR SHAWARMA' | O39: 130 | P39: 0 | Q39: 0 | S39: 'AWSPG202512010001216820000806612997973' | T39: 'WAP' | U39: 'YESAP53363716979' | V39: '2025-12-01 00:01:00' | W39: '2025-12-02 04:36:23' | X39: 'UPI' | AA39: 'POS23985176461' | AC39: '5120123807834018873' | AE39: '51051000100000000001' | AH39: 'SEAMLESS_3D_FORM' | AT39: '114956337713' | AW39: 130 | AX39: 0 | AY39: 0 | BB39: '01' | BC39: 'finearttattoos8@okhdfcbank' | BH39: 'Txn Success' | BK39: 130 | BP39: '114956337713' | BQ39: 'false' | BR39: 'UPI' | BS39: 'RECEIVER' | BT39: 'UPI|UPIPUSH|QR|PPBL' | BU39: 'PPBL' | BW39: 0 | BX39: 0 | CH39: 'UPI:null' | DJ39: 'BW'
A40: '20251201010940000202250515963526313' | B40: 'PTM8df609a8c84a4f6dac029e9a8389e5df' | E40: '2025-12-01 13:54:19' | F40: '2025-12-01 13:54:20' | G40: 'ACQUIRING' | H40: 'SUCCESS' | I40: 'TYXysH23627954956290' | J40: 'SHA SHA SHANDAAR SHAWARMA' | O40: 300 | P40: 0 | Q40: 0 | S40: 'AWSPG202512010001216820000806612997973' | T40: 'WAP' | U40: 'YESAP53363716979' | V40: '2025-12-01 00:01:00' | W40: '2025-12-02 04:36:23' | X40: 'UPI' | AA40: 'POS23985176461' | AC40: '5120133806628014153' | AE40: '51051000100000000001' | AH40: 'SEAMLESS_3D_FORM' | AO40: 'POS23985176461' | AT40: '533596813615' | AW40: 300 | AX40: 0 | AY40: 0 | BB40: '01' | BC40: '9949457971@pthdfc' | BH40: 'Txn Success' | BK40: 300 | BP40: '533596813615' | BQ40: 'false' | BR40: 'NA' | BS40: 'RECEIVER' | BT40: 'UPI|UPIPUSH|QR|PPBL' | BU40: 'PPBL' | BW40: 0 | BX40: 0 | CH40: 'UPI:null' | DJ40: 'BW'
A41: '20251201110840000202249374894762661' | B41: 'HDF1d3b1d3e6a6d48f68ed4aebe6d110759' | E41: '2025-12-01 13:49:47' | F41: '2025-12-01 13:49:48' | G41: 'ACQUIRING' | H41: 'SUCCESS' | I41: 'TYXysH23627954956290' | J41: 'SHA SHA SHANDAAR SHAWARMA' | O41: 260 | P41: 0 | Q41: 0 | S41: 'AWSPG202512010001216820000806612997973' | T41: 'WAP' | U41: 'YESAP53363716979' | V41: '2025-12-01 00:01:00' | W41: '2025-12-02 04:36:23' | X41: 'UPI' | AA41: 'POS23985176461' | AC41: '5120123787031363649' | AE41: '51051000100000000001' | AH41: 'SEAMLESS_3D_FORM' | AT41: '114956051003' | AW41: 260 | AX41: 0 | AY41: 0 | BB41: '01' | BC41: 'finearttattoos8@okhdfcbank' | BH41: 'Txn Success' | BK41: 260 | BP41: '114956051003' | BQ41: 'false' | BR41: 'UPI' | BS41: 'RECEIVER' | BT41: 'UPI|UPIPUSH|QR|PPBL' | BU41: 'PPBL' | BW41: 0 | BX41: 0 | CH41: 'UPI:null' | DJ41: 'BW'
A42: '20251201110850000202367679483534279' | B42: 'SBI9caf6a0b073449a2b50d086f709ed944' | E42: '2025-12-01 21:39:53' | F42: '2025-12-01 21:39:54' | G42: 'ACQUIRING' | H42: 'SUCCESS' | I42: 'TYXysH23627954956290' | J42: 'SHA SHA SHANDAAR SHAWARMA' | O42: 870 | P42: 0 | Q42: 0 | S42: 'AWSPG202512010001216820000806612997973' | T42: 'WAP' | U42: 'YESAP53363716979' | V42: '2025-12-01 00:01:00' | W42: '2025-12-02 04:36:23' | X42: 'UPI' | AA42: 'POS23985176461' | AC42: '5120125943507969057' | AE42: '51051000100000000001' | AH42: 'SEAMLESS_3D_FORM' | AT42: '533533452465' | AW42: 870 | AX42: 0 | AY42: 0 | BB42: '01' | BC42: 'raveena.nandipati@oksbi' | BH42: 'Txn Success' | BK42: 870 | BP42: '533533452465' | BQ42: 'false' | BR42: 'UPI' | BS42: 'RECEIVER' | BT42: 'UPI|UPIPUSH|QR|PPBL' | BU42: 'PPBL' | BW42: 0 | BX42: 0 | CH42: 'UPI:null' | DJ42: 'BW'
A43: '20251201011060000202366822855773400' | B43: 'PTM9be65b3df9524b6ba4f019acee8d1809' | E43: '2025-12-01 21:36:29' | F43: '2025-12-01 21:36:30' | G43: 'ACQUIRING' | H43: 'SUCCESS' | I43: 'TYXysH23627954956290' | J43: 'SHA SHA SHANDAAR SHAWARMA' | O43: 220 | P43: 0 | Q43: 0 | S43: 'AWSPG202512010001216820000806612997973' | T43: 'WAP' | U43: 'YESAP53363716979' | V43: '2025-12-01 00:01:00' | W43: '2025-12-02 04:36:23' | X43: 'UPI' | AA43: 'POS23985176461' | AC43: '5120125929012923397' | AE43: '51051000100000000001' | AH43: 'SEAMLESS_3D_FORM' | AO43: 'POS23985176461' | AT43: '533551777081' | AW43: 220 | AX43: 0 | AY43: 0 | BB43: '01' | BC43: '9392032356@ptsbi' | BH43: 'Txn Success' | BK43: 220 | BP43: '533551777081' | BQ43: 'false' | BR43: 'NA' | BS43: 'RECEIVER' | BT43: 'UPI|UPIPUSH|QR|PPBL' | BU43: 'PPBL' | BW43: 0 | BX43: 0 | CH43: 'UPI:null' | DJ43: 'BW'
A44: '20251201111010000202366016429302701' | B44: 'T2512012133135608517748' | E44: '2025-12-01 21:33:17' | F44: '2025-12-01 21:33:18' | G44: 'ACQUIRING' | H44: 'SUCCESS' | I44: 'TYXysH23627954956290' | J44: 'SHA SHA SHANDAAR SHAWARMA' | O44: 170 | P44: 0 | Q44: 0 | S44: 'AWSPG202512010001216820000806612997973' | T44: 'WAP' | U44: 'YESAP53363716979' | V44: '2025-12-01 00:01:00' | W44: '2025-12-02 04:36:23' | X44: 'UPI' | AA44: 'POS23985176461' | AC44: '5120125915321282577' | AE44: '51051000100000000001' | AH44: 'SEAMLESS_3D_FORM' | AT44: '842712541093' | AW44: 170 | AX44: 0 | AY44: 0 | BB44: '01' | BC44: '9963961381-2@ybl' | BH44: 'Txn Success' | BK44: 170 | BP44: '842712541093' | BQ44: 'false' | BR44: 'Payment from PhonePe' | BS44: 'RECEIVER' | BT44: 'UPI|UPIPUSH|QR|PPBL' | BU44: 'PPBL' | BW44: 0 | BX44: 0 | CH44: 'UPI:null' | DJ44: 'BW'
A45: '20251201111090000202364159174831000' | B45: 'T2512012125507018484107' | E45: '2025-12-01 21:25:54' | F45: '2025-12-01 21:25:55' | G45: 'ACQUIRING' | H45: 'SUCCESS' | I45: 'TYXysH23627954956290' | J45: 'SHA SHA SHANDAAR SHAWARMA' | O45: 300 | P45: 0 | Q45: 0 | S45: 'AWSPG202512010001216820000806612997973' | T45: 'WAP' | U45: 'YESAP53363716979' | V45: '2025-12-01 00:01:00' | W45: '2025-12-02 04:36:23' | X45: 'UPI' | AA45: 'POS23985176461' | AC45: '5120125883443510293' | AE45: '51051000100000000001' | AH45: 'SEAMLESS_3D_FORM' | AT45: '135999309800' | AW45: 300 | AX45: 0 | AY45: 0 | BB45: '01' | BC45: 'mohammedsalman235@ybl' | BH45: 'Txn Success' | BK45: 300 | BP45: '135999309800' | BQ45: 'false' | BR45: 'Payment from PhonePe' | BS45: 'RECEIVER' | BT45: 'UPI|UPIPUSH|QR|PPBL' | BU45: 'PPBL' | BW45: 0 | BX45: 0 | CH45: 'UPI:null' | DJ45: 'BW'
A46: '20251201111070000202358331537649002' | B46: 'T2512012102396411246783' | E46: '2025-12-01 21:02:44' | F46: '2025-12-01 21:02:47' | G46: 'ACQUIRING' | H46: 'SUCCESS' | I46: 'TYXysH23627954956290' | J46: 'SHA SHA SHANDAAR SHAWARMA' | O46: 530 | P46: 0 | Q46: 0 | S46: 'AWSPG202512010001216820000806612997973' | T46: 'WAP' | U46: 'YESAP53363716979' | V46: '2025-12-01 00:01:00' | W46: '2025-12-02 04:36:23' | X46: 'UPI' | AA46: 'POS23985176461' | AC46: '5120135784056313869' | AE46: '51051000100000000001' | AH46: 'SEAMLESS_3D_FORM' | AT46: '856173107371' | AW46: 530 | AX46: 0 | AY46: 0 | BB46: '01' | BC46: '9634634534-2@axl' | BH46: 'Txn Success' | BK46: 530 | BP46: '856173107371' | BQ46: 'false' | BR46: 'Payment from PhonePe' | BS46: 'RECEIVER' | BT46: 'UPI|UPIPUSH|QR|PPBL' | BU46: 'PPBL' | BW46: 0 | BX46: 0 | CH46: 'UPI:null' | DJ46: 'BW'
A47: '20251201110910000202354003862720936' | B47: 'ICI745651064bad40bf9281dc376043dff4' | E47: '2025-12-01 20:45:33' | F47: '2025-12-01 20:45:34' | G47: 'ACQUIRING' | H47: 'SUCCESS' | I47: 'TYXysH23627954956290' | J47: 'SHA SHA SHANDAAR SHAWARMA' | O47: 260 | P47: 0 | Q47: 0 | S47: 'AWSPG202512010001216820000806612997973' | T47: 'WAP' | U47: 'YESAP53363716979' | V47: '2025-12-01 00:01:00' | W47: '2025-12-02 04:36:23' | X47: 'UPI' | AA47: 'POS23985176461' | AC47: '5120135693057302557' | AE47: '51051000100000000001' | AH47: 'SEAMLESS_3D_FORM' | AT47: '570160667914' | AW47: 260 | AX47: 0 | AY47: 0 | BB47: '01' | BC47: 'manunairccd-4@okicici' | BH47: 'Txn Success' | BK47: 260 | BP47: '570160667914' | BQ47: 'false' | BR47: 'UPI' | BS47: 'RECEIVER' | BT47: 'UPI|UPIPUSH|QR|PPBL' | BU47: 'PPBL' | BW47: 0 | BX47: 0 | CH47: 'UPI:null' | DJ47: 'BW'
A48: '20251201110910000202350744591163710' | B48: 'ACDb21a1b5ac03f4b459329ca6ce58cefdf' | E48: '2025-12-01 20:32:36' | F48: '2025-12-01 20:32:37' | G48: 'ACQUIRING' | H48: 'SUCCESS' | I48: 'TYXysH23627954956290' | J48: 'SHA SHA SHANDAAR SHAWARMA' | O48: 300 | P48: 0 | Q48: 0 | S48: 'AWSPG202512010001216820000806612997973' | T48: 'WAP' | U48: 'YESAP53363716979' | V48: '2025-12-01 00:01:00' | W48: '2025-12-02 04:36:23' | X48: 'UPI' | AA48: 'POS23985176461' | AC48: '5120125637422074889' | AE48: '51051000100000000001' | AH48: 'SEAMLESS_3D_FORM' | AT48: '533564348317' | AW48: 300 | AX48: 0 | AY48: 0 | BB48: '01' | BC48: '8498914347@axisb' | BH48: 'Txn Success' | BK48: 300 | BP48: '533564348317' | BQ48: 'false' | BR48: 'Paid via CRED' | BS48: 'RECEIVER' | BT48: 'UPI|UPIPUSH|QR|PPBL' | BU48: 'PPBL' | BW48: 0 | BX48: 0 | CH48: 'UPI:null' | DJ48: 'BW'
A49: '20251201111050000202349734892616886' | B49: 'YCD6D0BACD82CDE424DB2C71D2E95013F28' | E49: '2025-12-01 20:28:35' | F49: '2025-12-01 20:28:36' | G49: 'ACQUIRING' | H49: 'SUCCESS' | I49: 'TYXysH23627954956290' | J49: 'SHA SHA SHANDAAR SHAWARMA' | O49: 150 | P49: 0 | Q49: 0 | S49: 'AWSPG202512010001216820000806612997973' | T49: 'WAP' | U49: 'YESAP53363716979' | V49: '2025-12-01 00:01:00' | W49: '2025-12-02 04:36:23' | X49: 'UPI' | AA49: 'POS23985176461' | AC49: '5120125620178146321' | AE49: '51051000100000000001' | AH49: 'SEAMLESS_3D_FORM' | AO49: 'POS23985176461' | AT49: '570123394670' | AW49: 150 | AX49: 0 | AY49: 0 | BB49: '01' | BC49: '7396956624@yescred' | BH49: 'Txn Success' | BK49: 150 | BP49: '570123394670' | BQ49: 'false' | BR49: 'Paid via CRED' | BS49: 'RECEIVER' | BT49: 'UPI|UPIPUSH|QR|PPBL' | BU49: 'PPBL' | BW49: 0 | BX49: 0 | CH49: 'UPI:null' | DJ49: 'BW'
A50: '20251201111020000202348616803484426' | B50: 'T2512012024051503254679' | E50: '2025-12-01 20:24:08' | F50: '2025-12-01 20:24:10' | G50: 'ACQUIRING' | H50: 'SUCCESS' | I50: 'TYXysH23627954956290' | J50: 'SHA SHA SHANDAAR SHAWARMA' | O50: 150 | P50: 0 | Q50: 0 | S50: 'AWSPG202512010001216820000806612997973' | T50: 'WAP' | U50: 'YESAP53363716979' | V50: '2025-12-01 00:01:00' | W50: '2025-12-02 04:36:23' | X50: 'UPI' | AA50: 'POS23985176461' | AC50: '5120125601185459241' | AE50: '51051000100000000001' | AH50: 'SEAMLESS_3D_FORM' | AT50: '716519676910' | AW50: 150 | AX50: 0 | AY50: 0 | BB50: '01' | BC50: '8904517903@ybl' | BH50: 'Txn Success' | BK50: 150 | BP50: '716519676910' | BQ50: 'false' | BR50: 'Payment from PhonePe' | BS50: 'RECEIVER' | BT50: 'UPI|UPIPUSH|QR|PPBL' | BU50: 'PPBL' | BW50: 0 | BX50: 0 | CH50: 'UPI:null' | DJ50: 'BW'
A51: '20251201111030000202340113334825622' | B51: 'PTMc19ea9a428c64867ad205ca449ac1f39' | E51: '2025-12-01 19:50:21' | F51: '2025-12-01 19:50:22' | G51: 'ACQUIRING' | H51: 'SUCCESS' | I51: 'TYXysH23627954956290' | J51: 'SHA SHA SHANDAAR SHAWARMA' | O51: 130 | P51: 0 | Q51: 0 | S51: 'AWSPG202512010001216820000806612997973' | T51: 'WAP' | U51: 'YESAP53363716979' | V51: '2025-12-01 00:01:00' | W51: '2025-12-02 04:36:23' | X51: 'UPI' | AA51: 'POS23985176461' | AC51: '5120125438847468561' | AE51: '51051000100000000001' | AH51: 'SEAMLESS_3D_FORM' | AO51: 'POS23985176461' | AT51: '533502549484' | AW51: 130 | AX51: 0 | AY51: 0 | BB51: '01' | BC51: '6300374561@pthdfc' | BH51: 'Txn Success' | BK51: 130 | BP51: '533502549484' | BQ51: 'false' | BR51: 'NA' | BS51: 'RECEIVER' | BT51: 'UPI|UPIPUSH|QR|PPBL' | BU51: 'PPBL' | BW51: 0 | BX51: 0 | CH51: 'UPI:null' | DJ51: 'BW'
A52: '20251201111060000202337770388364474' | B52: 'T2512011941003462341144' | E52: '2025-12-01 19:41:02' | F52: '2025-12-01 19:41:04' | G52: 'ACQUIRING' | H52: 'SUCCESS' | I52: 'TYXysH23627954956290' | J52: 'SHA SHA SHANDAAR SHAWARMA' | O52: 150 | P52: 0 | Q52: 0 | S52: 'AWSPG202512010001216820000806612997973' | T52: 'WAP' | U52: 'YESAP53363716979' | V52: '2025-12-01 00:01:00' | W52: '2025-12-02 04:36:23' | X52: 'UPI' | AA52: 'POS23985176461' | AC52: '5120125398918955061' | AE52: '51051000100000000001' | AH52: 'SEAMLESS_3D_FORM' | AT52: '512100405887' | AW52: 150 | AX52: 0 | AY52: 0 | BB52: '01' | BC52: '8185867632@ybl' | BH52: 'Txn Success' | BK52: 150 | BP52: '512100405887' | BQ52: 'false' | BR52: 'Shavarma cty' | BS52: 'RECEIVER' | BT52: 'UPI|UPIPUSH|QR|PPBL' | BU52: 'PPBL' | BW52: 0 | BX52: 0 | CH52: 'UPI:null' | DJ52: 'BW'
A53: '20251201110870000202319901012971814' | B53: 'T2512011829589043658889' | E53: '2025-12-01 18:30:02' | F53: '2025-12-01 18:30:04' | G53: 'ACQUIRING' | H53: 'SUCCESS' | I53: 'TYXysH23627954956290' | J53: 'SHA SHA SHANDAAR SHAWARMA' | O53: 150 | P53: 0 | Q53: 0 | S53: 'AWSPG202512010001216820000806612997973' | T53: 'WAP' | U53: 'YESAP53363716979' | V53: '2025-12-01 00:01:00' | W53: '2025-12-02 04:36:23' | X53: 'UPI' | AA53: 'POS23985176461' | AC53: '5120125076796619809' | AE53: '51051000100000000001' | AH53: 'SEAMLESS_3D_FORM' | AT53: '425871337168' | AW53: 150 | AX53: 0 | AY53: 0 | BB53: '01' | BC53: '8897771312-2@ybl' | BH53: 'Txn Success' | BK53: 150 | BP53: '425871337168' | BQ53: 'false' | BR53: 'Payment from PhonePe' | BS53: 'RECEIVER' | BT53: 'UPI|UPIPUSH|QR|PPBL' | BU53: 'PPBL' | BW53: 0 | BX53: 0 | CH53: 'UPI:null' | DJ53: 'BW'
A54: '20251201110830000202315088779505920' | B54: 'T2512011810477665196994' | E54: '2025-12-01 18:10:55' | F54: '2025-12-01 18:10:56' | G54: 'ACQUIRING' | H54: 'SUCCESS' | I54: 'TYXysH23627954956290' | J54: 'SHA SHA SHANDAAR SHAWARMA' | O54: 260 | P54: 0 | Q54: 0 | S54: 'AWSPG202512010001216820000806612997973' | T54: 'WAP' | U54: 'YESAP53363716979' | V54: '2025-12-01 00:01:00' | W54: '2025-12-02 04:36:23' | X54: 'UPI' | AA54: 'POS23985176461' | AC54: '5120124994453868553' | AE54: '51051000100000000001' | AH54: 'SEAMLESS_3D_FORM' | AT54: '864023911571' | AW54: 260 | AX54: 0 | AY54: 0 | BB54: '01' | BC54: '9315749816@ybl' | BH54: 'Txn Success' | BK54: 260 | BP54: '864023911571' | BQ54: 'false' | BR54: 'Payment from PhonePe' | BS54: 'RECEIVER' | BT54: 'UPI|UPIPUSH|QR|PPBL' | BU54: 'PPBL' | BW54: 0 | BX54: 0 | CH54: 'UPI:null' | DJ54: 'BW'
A55: '20251201110950000202295420153064610' | B55: 'ICI71b966a452454cdfba6d71037e2aa2f4' | E55: '2025-12-01 16:52:45' | F55: '2025-12-01 16:52:46' | G55: 'ACQUIRING' | H55: 'SUCCESS' | I55: 'TYXysH23627954956290' | J55: 'SHA SHA SHANDAAR SHAWARMA' | O55: 130 | P55: 0 | Q55: 0 | S55: 'AWSPG202512010001216820000806612997973' | T55: 'WAP' | U55: 'YESAP53363716979' | V55: '2025-12-01 00:01:00' | W55: '2025-12-02 04:36:23' | X55: 'UPI' | AA55: 'POS23985176461' | AC55: '5120134624416800825' | AE55: '51051000100000000001' | AH55: 'SEAMLESS_3D_FORM' | AT55: '570135651483' | AW55: 130 | AX55: 0 | AY55: 0 | BB55: '01' | BC55: 'gowni06042002@okicici' | BH55: 'Txn Success' | BK55: 130 | BP55: '570135651483' | BQ55: 'false' | BR55: 'UPI' | BS55: 'RECEIVER' | BT55: 'UPI|UPIPUSH|QR|PPBL' | BU55: 'PPBL' | BW55: 0 | BX55: 0 | CH55: 'UPI:null' | DJ55: 'BW'
A56: '20251201011070000202290540512034826' | B56: 'T2512011633196135647644' | E56: '2025-12-01 16:33:22' | F56: '2025-12-01 16:33:23' | G56: 'ACQUIRING' | H56: 'SUCCESS' | I56: 'TYXysH23627954956290' | J56: 'SHA SHA SHANDAAR SHAWARMA' | O56: 130 | P56: 0 | Q56: 0 | S56: 'AWSPG202512010001216820000806612997973' | T56: 'WAP' | U56: 'YESAP53363716979' | V56: '2025-12-01 00:01:00' | W56: '2025-12-02 04:36:23' | X56: 'UPI' | AA56: 'POS23985176461' | AC56: '5120124541265361937' | AE56: '51051000100000000001' | AH56: 'SEAMLESS_3D_FORM' | AT56: '502419471748' | AW56: 130 | AX56: 0 | AY56: 0 | BB56: '01' | BC56: '9827718779@ibl' | BH56: 'Txn Success' | BK56: 130 | BP56: '502419471748' | BQ56: 'false' | BR56: 'Payment from PhonePe' | BS56: 'RECEIVER' | BT56: 'UPI|UPIPUSH|QR|PPBL' | BU56: 'PPBL' | BW56: 0 | BX56: 0 | CH56: 'UPI:null' | DJ56: 'BW'
A57: '20251201110840000202280630042841231' | B57: 'T2512011553538598300333' | E57: '2025-12-01 15:53:59' | F57: '2025-12-01 15:54:00' | G57: 'ACQUIRING' | H57: 'SUCCESS' | I57: 'TYXysH23627954956290' | J57: 'SHA SHA SHANDAAR SHAWARMA' | O57: 130 | P57: 0 | Q57: 0 | S57: 'AWSPG202512010001216820000806612997973' | T57: 'WAP' | U57: 'YESAP53363716979' | V57: '2025-12-01 00:01:00' | W57: '2025-12-02 04:36:23' | X57: 'UPI' | AA57: 'POS23985176461' | AC57: '5120124354771233837' | AE57: '51051000100000000001' | AH57: 'SEAMLESS_3D_FORM' | AT57: '459642728394' | AW57: 130 | AX57: 0 | AY57: 0 | BB57: '01' | BC57: '6303681473-3@ybl' | BH57: 'Txn Success' | BK57: 130 | BP57: '459642728394' | BQ57: 'false' | BR57: 'Payment from PhonePe' | BS57: 'RECEIVER' | BT57: 'UPI|UPIPUSH|QR|PPBL' | BU57: 'PPBL' | BW57: 0 | BX57: 0 | CH57: 'UPI:null' | DJ57: 'BW'
A58: '20251201111020000202280580994999259' | B58: 'TOTwd251201155346189395F6631B421994' | E58: '2025-12-01 15:53:47' | F58: '2025-12-01 15:53:48' | G58: 'ACQUIRING' | H58: 'SUCCESS' | I58: 'TYXysH23627954956290' | J58: 'SHA SHA SHANDAAR SHAWARMA' | O58: 150 | P58: 0 | Q58: 0 | S58: 'AWSPG202512010001216820000806612997973' | T58: 'WAP' | U58: 'YESAP53363716979' | V58: '2025-12-01 00:01:00' | W58: '2025-12-02 04:36:23' | X58: 'UPI_PPIWALLET' | AA58: 'POS23985176461' | AC58: '5120124353964653637' | AE58: '51051000100000000001' | AH58: 'SEAMLESS_3D_FORM' | AO58: 'POS23985176461' | AT58: '570118098908' | AW58: 150 | AX58: 0 | AY58: 0 | BB58: '01' | BC58: '8008470007@fam' | BH58: 'Txn Success' | BK58: 150 | BP58: '570118098908' | BQ58: 'false' | BR58: 'UPI Payment' | BS58: 'RECEIVER' | BT58: 'UPI|UPIPUSH|QR|UPI_PPIWALLET|PPBL' | BU58: 'PPBL' | BW58: 0 | BX58: 0 | CH58: 'UPI:null' | DJ58: 'BW'
A59: '20251201111000000202396859399130404' | B59: 'HDF308fdb40aa3b40f29696ba6babffadc6' | E59: '2025-12-01 23:35:50' | F59: '2025-12-01 23:35:51' | G59: 'ACQUIRING' | H59: 'SUCCESS' | I59: 'TYXysH23627954956290' | J59: 'SHA SHA SHANDAAR SHAWARMA' | O59: 20 | P59: 0 | Q59: 0 | S59: 'AWSPG202512010001216820000806612997973' | T59: 'WAP' | U59: 'YESAP53363716979' | V59: '2025-12-01 00:01:00' | W59: '2025-12-02 04:36:23' | X59: 'UPI' | AA59: 'POS23985176461' | AC59: '5120126475881532417' | AE59: '51051000100000000001' | AH59: 'SEAMLESS_3D_FORM' | AT59: '114987904532' | AW59: 20 | AX59: 0 | AY59: 0 | BB59: '01' | BC59: 'bhuwankantbhatti@okhdfcbank' | BH59: 'Txn Success' | BK59: 20 | BP59: '114987904532' | BQ59: 'false' | BR59: 'UPI' | BS59: 'RECEIVER' | BT59: 'UPI|UPIPUSH|QR|PPBL' | BU59: 'PPBL' | BW59: 0 | BX59: 0 | CH59: 'UPI:null' | DJ59: 'BW'
A60: '20251201111010000202396291763015071' | B60: 'HDFb88c6bbe181341c895641632ef587fd5' | E60: '2025-12-01 23:33:35' | F60: '2025-12-01 23:33:36' | G60: 'ACQUIRING' | H60: 'SUCCESS' | I60: 'TYXysH23627954956290' | J60: 'SHA SHA SHANDAAR SHAWARMA' | O60: 420 | P60: 0 | Q60: 0 | S60: 'AWSPG202512010001216820000806612997973' | T60: 'WAP' | U60: 'YESAP53363716979' | V60: '2025-12-01 00:01:00' | W60: '2025-12-02 04:36:23' | X60: 'UPI' | AA60: 'POS23985176461' | AC60: '5120126466285431813' | AE60: '51051000100000000001' | AH60: 'SEAMLESS_3D_FORM' | AT60: '114987865073' | AW60: 420 | AX60: 0 | AY60: 0 | BB60: '01' | BC60: 'bhuwankantbhatti@okhdfcbank' | BH60: 'Txn Success' | BK60: 420 | BP60: '114987865073' | BQ60: 'false' | BR60: 'UPI' | BS60: 'RECEIVER' | BT60: 'UPI|UPIPUSH|QR|PPBL' | BU60: 'PPBL' | BW60: 0 | BX60: 0 | CH60: 'UPI:null' | DJ60: 'BW'
A61: '20251201011090000202394532587612067' | B61: 'PTM37b572cc46d34a31b61afbee2950dabe' | E61: '2025-12-01 23:26:35' | F61: '2025-12-01 23:26:37' | G61: 'ACQUIRING' | H61: 'SUCCESS' | I61: 'TYXysH23627954956290' | J61: 'SHA SHA SHANDAAR SHAWARMA' | O61: 150 | P61: 0 | Q61: 0 | S61: 'AWSPG202512010001216820000806612997973' | T61: 'WAP' | U61: 'YESAP53363716979' | V61: '2025-12-01 00:01:00' | W61: '2025-12-02 04:36:23' | X61: 'UPI' | AA61: 'POS23985176461' | AC61: '5120136436287874049' | AE61: '51051000100000000001' | AH61: 'SEAMLESS_3D_FORM' | AO61: 'POS23985176461' | AT61: '393141331994' | AW61: 150 | AX61: 0 | AY61: 0 | BB61: '01' | BC61: '6304395762@ptyes' | BH61: 'Txn Success' | BK61: 150 | BP61: '393141331994' | BQ61: 'false' | BR61: 'NA' | BS61: 'RECEIVER' | BT61: 'UPI|UPIPUSH|QR|PPBL' | BU61: 'PPBL' | BW61: 0 | BX61: 0 | CH61: 'UPI:null' | DJ61: 'BW'
A62: '20251201111060000202392426749670553' | B62: 'YCDecf3df293fd74030b8048c701d5b1a15' | E62: '2025-12-01 23:18:13' | F62: '2025-12-01 23:18:15' | G62: 'ACQUIRING' | H62: 'SUCCESS' | I62: 'TYXysH23627954956290' | J62: 'SHA SHA SHANDAAR SHAWARMA' | O62: 150 | P62: 3.41 | Q62: 0.61 | S62: 'AWSPG202512010001216820000806612997973' | T62: 'WAP' | U62: 'YESAP53363716979' | V62: '2025-12-01 00:01:00' | W62: '2025-12-02 04:36:23' | X62: 'UPI_CREDIT_CARD' | AA62: 'POS23985176461' | AC62: '5120126400452801537' | AE62: '51051000100000000001' | AH62: 'SEAMLESS_3D_FORM' | AO62: 'POS23985176461' | AT62: '570120427310' | AW62: 145.98 | AX62: 0 | AY62: 0 | BB62: '01' | BC62: '9671260161-1@yescred' | BH62: 'Txn Success' | BK62: 150 | BP62: '570120427310' | BQ62: 'false' | BR62: 'Paid via CRED' | BS62: 'RECEIVER' | BT62: 'UPI|UPIPUSH|QR|UPI_CREDIT_CARD|PPBL|Platinum|upiCc' | BU62: 'PPBL' | BW62: 3.41 | BX62: 0.61 | CH62: 'UPI:null' | DJ62: 'BW'
A63: '20251201110880000202392419165865893' | B63: 'AXB20251201113203946335481110529000' | E63: '2025-12-01 23:18:12' | F63: '2025-12-01 23:18:13' | G63: 'ACQUIRING' | H63: 'SUCCESS' | I63: 'TYXysH23627954956290' | J63: 'SHA SHA SHANDAAR SHAWARMA' | O63: 110 | P63: 0 | Q63: 0 | S63: 'AWSPG202512010001216820000806612997973' | T63: 'WAP' | U63: 'YESAP53363716979' | V63: '2025-12-01 00:01:00' | W63: '2025-12-02 04:36:23' | X63: 'UPI' | AA63: 'POS23985176461' | AC63: '5120126400315871233' | AE63: '51051000100000000001' | AH63: 'SEAMLESS_3D_FORM' | AO63: 'POS23985176461' | AT63: '570197148010' | AW63: 110 | AX63: 0 | AY63: 0 | BB63: '01' | BC63: '9502639882@naviaxis' | BH63: 'Txn Success' | BK63: 110 | BP63: '570197148010' | BQ63: 'false' | BR63: 'Paid via Navi UPI' | BS63: 'RECEIVER' | BT63: 'UPI|UPIPUSH|QR|PPBL' | BU63: 'PPBL' | BW63: 0 | BX63: 0 | CH63: 'UPI:null' | DJ63: 'BW'
A64: '20251201111060000202391119628826050' | B64: 'T2512012312574090320955' | E64: '2025-12-01 23:13:02' | F64: '2025-12-01 23:13:03' | G64: 'ACQUIRING' | H64: 'SUCCESS' | I64: 'TYXysH23627954956290' | J64: 'SHA SHA SHANDAAR SHAWARMA' | O64: 130 | P64: 0 | Q64: 0 | S64: 'AWSPG202512010001216820000806612997973' | T64: 'WAP' | U64: 'YESAP53363716979' | V64: '2025-12-01 00:01:00' | W64: '2025-12-02 04:36:23' | X64: 'UPI' | AA64: 'POS23985176461' | AC64: '5120126378169218053' | AE64: '51051000100000000001' | AH64: 'SEAMLESS_3D_FORM' | AT64: '471870437159' | AW64: 130 | AX64: 0 | AY64: 0 | BB64: '01' | BC64: '9160656656-2@ybl' | BH64: 'Txn Success' | BK64: 130 | BP64: '471870437159' | BQ64: 'false' | BR64: 'Payment from PhonePe' | BS64: 'RECEIVER' | BT64: 'UPI|UPIPUSH|QR|PPBL' | BU64: 'PPBL' | BW64: 0 | BX64: 0 | CH64: 'UPI:null' | DJ64: 'BW'
A65: '20251201111090000202385484199706414' | B65: 'T2512012250360809697594' | E65: '2025-12-01 22:50:38' | F65: '2025-12-01 22:50:39' | G65: 'ACQUIRING' | H65: 'SUCCESS' | I65: 'TYXysH23627954956290' | J65: 'SHA SHA SHANDAAR SHAWARMA' | O65: 300 | P65: 0 | Q65: 0 | S65: 'AWSPG202512010001216820000806612997973' | T65: 'WAP' | U65: 'YESAP53363716979' | V65: '2025-12-01 00:01:00' | W65: '2025-12-02 04:36:23' | X65: 'UPI' | AA65: 'POS23985176461' | AC65: '5120126264624617485' | AE65: '51051000100000000001' | AH65: 'SEAMLESS_3D_FORM' | AT65: '148126719722' | AW65: 300 | AX65: 0 | AY65: 0 | BB65: '01' | BC65: '7799038973@ybl' | BH65: 'Txn Success' | BK65: 300 | BP65: '148126719722' | BQ65: 'false' | BR65: 'Payment from PhonePe' | BS65: 'RECEIVER' | BT65: 'UPI|UPIPUSH|QR|PPBL' | BU65: 'PPBL' | BW65: 0 | BX65: 0 | CH65: 'UPI:null' | DJ65: 'BW'
A66: '20251201110900000202384963639508981' | B66: 'T2512012248307537525557' | E66: '2025-12-01 22:48:34' | F66: '2025-12-01 22:48:35' | G66: 'ACQUIRING' | H66: 'SUCCESS' | I66: 'TYXysH23627954956290' | J66: 'SHA SHA SHANDAAR SHAWARMA' | O66: 20 | P66: 0 | Q66: 0 | S66: 'AWSPG202512010001216820000806612997973' | T66: 'WAP' | U66: 'YESAP53363716979' | V66: '2025-12-01 00:01:00' | W66: '2025-12-02 04:36:23' | X66: 'UPI' | AA66: 'POS23985176461' | AC66: '5120136255766075401' | AE66: '51051000100000000001' | AH66: 'SEAMLESS_3D_FORM' | AT66: '247264191949' | AW66: 20 | AX66: 0 | AY66: 0 | BB66: '01' | BC66: '7995250777@ibl' | BH66: 'Txn Success' | BK66: 20 | BP66: '247264191949' | BQ66: 'false' | BR66: 'Payment from PhonePe' | BS66: 'RECEIVER' | BT66: 'UPI|UPIPUSH|QR|PPBL' | BU66: 'PPBL' | BW66: 0 | BX66: 0 | CH66: 'UPI:null' | DJ66: 'BW'
A67: '20251201010810000202384820177804153' | B67: 'T2512012247561814239077' | E67: '2025-12-01 22:48:00' | F67: '2025-12-01 22:48:01' | G67: 'ACQUIRING' | H67: 'SUCCESS' | I67: 'TYXysH23627954956290' | J67: 'SHA SHA SHANDAAR SHAWARMA' | O67: 130 | P67: 0 | Q67: 0 | S67: 'AWSPG202512010001216820000806612997973' | T67: 'WAP' | U67: 'YESAP53363716979' | V67: '2025-12-01 00:01:00' | W67: '2025-12-02 04:36:23' | X67: 'UPI' | AA67: 'POS23985176461' | AC67: '5120136253482556429' | AE67: '51051000100000000001' | AH67: 'SEAMLESS_3D_FORM' | AT67: '054282944642' | AW67: 130 | AX67: 0 | AY67: 0 | BB67: '01' | BC67: '7995250777@ibl' | BH67: 'Txn Success' | BK67: 130 | BP67: '054282944642' | BQ67: 'false' | BR67: 'Payment from PhonePe' | BS67: 'RECEIVER' | BT67: 'UPI|UPIPUSH|QR|PPBL' | BU67: 'PPBL' | BW67: 0 | BX67: 0 | CH67: 'UPI:null' | DJ67: 'BW'
A68: '20251201010990000202377410364908069' | B68: 'PTM2833E92CDDD645CEBB70E24E619F8E7C' | E68: '2025-12-01 22:18:33' | F68: '2025-12-01 22:18:34' | G68: 'ACQUIRING' | H68: 'SUCCESS' | I68: 'TYXysH23627954956290' | J68: 'SHA SHA SHANDAAR SHAWARMA' | O68: 280 | P68: 0 | Q68: 0 | S68: 'AWSPG202512010001216820000806612997973' | T68: 'WAP' | U68: 'YESAP53363716979' | V68: '2025-12-01 00:01:00' | W68: '2025-12-02 04:36:23' | X68: 'UPI' | AA68: 'POS23985176461' | AC68: '5120126126848406545' | AE68: '51051000100000000001' | AH68: 'SEAMLESS_3D_FORM' | AO68: 'POS23985176461' | AT68: '533552013331' | AW68: 280 | AX68: 0 | AY68: 0 | BB68: '01' | BC68: '7728088559@ptsbi' | BH68: 'Txn Success' | BK68: 280 | BP68: '533552013331' | BQ68: 'false' | BR68: 'NA' | BS68: 'RECEIVER' | BT68: 'UPI|UPIPUSH|QR|PPBL' | BU68: 'PPBL' | BW68: 0 | BX68: 0 | CH68: 'UPI:null' | DJ68: 'BW'
A69: '20251201011040000202373405421247010' | B69: 'T2512012202355667702295' | E69: '2025-12-01 22:02:38' | F69: '2025-12-01 22:02:39' | G69: 'ACQUIRING' | H69: 'SUCCESS' | I69: 'TYXysH23627954956290' | J69: 'SHA SHA SHANDAAR SHAWARMA' | O69: 460 | P69: 0 | Q69: 0 | S69: 'AWSPG202512010001216820000806612997973' | T69: 'WAP' | U69: 'YESAP53363716979' | V69: '2025-12-01 00:01:00' | W69: '2025-12-02 04:36:23' | X69: 'UPI' | AA69: 'POS23985176461' | AC69: '5120126058466581517' | AE69: '51051000100000000001' | AH69: 'SEAMLESS_3D_FORM' | AT69: '620853805195' | AW69: 460 | AX69: 0 | AY69: 0 | BB69: '01' | BC69: '8434587473@ybl' | BH69: 'Txn Success' | BK69: 460 | BP69: '620853805195' | BQ69: 'false' | BR69: 'Payment from PhonePe' | BS69: 'RECEIVER' | BT69: 'UPI|UPIPUSH|QR|PPBL' | BU69: 'PPBL' | BW69: 0 | BX69: 0 | CH69: 'UPI:null' | DJ69: 'BW'
A70: '20251201110970000202372399393015060' | B70: 'T2512012158360243510238' | E70: '2025-12-01 21:58:38' | F70: '2025-12-01 21:58:40' | G70: 'ACQUIRING' | H70: 'SUCCESS' | I70: 'TYXysH23627954956290' | J70: 'SHA SHA SHANDAAR SHAWARMA' | O70: 300 | P70: 0 | Q70: 0 | S70: 'AWSPG202512010001216820000806612997973' | T70: 'WAP' | U70: 'YESAP53363716979' | V70: '2025-12-01 00:01:00' | W70: '2025-12-02 04:36:23' | X70: 'UPI' | AA70: 'POS23985176461' | AC70: '5120136024173640705' | AE70: '51051000100000000001' | AH70: 'SEAMLESS_3D_FORM' | AT70: '601551833983' | AW70: 300 | AX70: 0 | AY70: 0 | BB70: '01' | BC70: '7386184225@axl' | BH70: 'Txn Success' | BK70: 300 | BP70: '601551833983' | BQ70: 'false' | BR70: 'Payment from PhonePe' | BS70: 'RECEIVER' | BT70: 'UPI|UPIPUSH|QR|PPBL' | BU70: 'PPBL' | BW70: 0 | BX70: 0 | CH70: 'UPI:null' | DJ70: 'BW'
A71: '20251201111090000202371572356029038' | B71: '533521766693' | E71: '2025-12-01 21:55:21' | F71: '2025-12-01 21:55:22' | G71: 'ACQUIRING' | H71: 'SUCCESS' | I71: 'TYXysH23627954956290' | J71: 'SHA SHA SHANDAAR SHAWARMA' | O71: 150 | P71: 0 | Q71: 0 | S71: 'AWSPG202512010001216820000806612997973' | T71: 'WAP' | U71: 'YESAP53363716979' | V71: '2025-12-01 00:01:00' | W71: '2025-12-02 04:36:23' | X71: 'UPI' | AA71: 'POS23985176461' | AC71: '5120126010080079897' | AE71: '51051000100000000001' | AH71: 'SEAMLESS_3D_FORM' | AO71: 'POS23985176461' | AT71: '533521766693' | AW71: 150 | AX71: 0 | AY71: 0 | BB71: '01' | BC71: '8919491306@kotak811' | BH71: 'Txn Success' | BK71: 150 | BP71: '533521766693' | BQ71: 'false' | BR71: 'UPI' | BS71: 'RECEIVER' | BT71: 'UPI|UPIPUSH|QR|PPBL' | BU71: 'PPBL' | BW71: 0 | BX71: 0 | CH71: 'UPI:null' | DJ71: 'BW'
A72: '20251202110950000202440938543804269' | B72: 'T2512020230569249381937' | E72: '2025-12-02 02:30:59' | F72: '2025-12-02 02:31:01' | G72: 'ACQUIRING' | H72: 'SUCCESS' | I72: 'TYXysH23627954956290' | J72: 'SHA SHA SHANDAAR SHAWARMA' | O72: 170 | P72: 0 | Q72: 0 | S72: 'AWSPG202512020001216820000806612997973' | T72: 'WAP' | U72: 'YESAP53373551554' | V72: '2025-12-02 00:01:00' | W72: '2025-12-03 04:28:11' | X72: 'UPI' | AA72: 'POS23985176461' | AC72: '5120220682908732417' | AE72: '51051000100000000001' | AH72: 'SEAMLESS_3D_FORM' | AT72: '680749499573' | AW72: 170 | AX72: 0 | AY72: 0 | BB72: '01' | BC72: '7013169554@ybl' | BH72: 'Txn Success' | BK72: 170 | BP72: '680749499573' | BQ72: 'false' | BR72: 'Payment from PhonePe' | BS72: 'RECEIVER' | BT72: 'UPI|UPIPUSH|QR|PPBL' | BU72: 'PPBL' | BW72: 0 | BX72: 0 | CH72: 'UPI:null' | DJ72: 'BW'
A73: '20251202110930000202440677783579045' | B73: 'AXB20251202022953112824487362560000' | E73: '2025-12-02 02:29:57' | F73: '2025-12-02 02:29:59' | G73: 'ACQUIRING' | H73: 'SUCCESS' | I73: 'TYXysH23627954956290' | J73: 'SHA SHA SHANDAAR SHAWARMA' | O73: 130 | P73: 0 | Q73: 0 | S73: 'AWSPG202512020001216820000806612997973' | T73: 'WAP' | U73: 'YESAP53373551554' | V73: '2025-12-02 00:01:00' | W73: '2025-12-03 04:28:11' | X73: 'UPI' | AA73: 'POS23985176461' | AC73: '5120220678147430413' | AE73: '51051000100000000001' | AH73: 'SEAMLESS_3D_FORM' | AO73: 'POS23985176461' | AT73: '570297562190' | AW73: 130 | AX73: 0 | AY73: 0 | BB73: '01' | BC73: '8309482385@naviaxis' | BH73: 'Txn Success' | BK73: 130 | BP73: '570297562190' | BQ73: 'false' | BR73: 'Paid via Navi UPI' | BS73: 'RECEIVER' | BT73: 'UPI|UPIPUSH|QR|PPBL' | BU73: 'PPBL' | BW73: 0 | BX73: 0 | CH73: 'UPI:null' | DJ73: 'BW'
A74: '20251202011010000202440256122354892' | B74: 'AXB20251202022813121977191763968000' | E74: '2025-12-02 02:28:17' | F74: '2025-12-02 02:28:18' | G74: 'ACQUIRING' | H74: 'SUCCESS' | I74: 'TYXysH23627954956290' | J74: 'SHA SHA SHANDAAR SHAWARMA' | O74: 160 | P74: 0 | Q74: 0 | S74: 'AWSPG202512020001216820000806612997973' | T74: 'WAP' | U74: 'YESAP53373551554' | V74: '2025-12-02 00:01:00' | W74: '2025-12-03 04:28:11' | X74: 'UPI' | AA74: 'POS23985176461' | AC74: '5120230671166183425' | AE74: '51051000100000000001' | AH74: 'SEAMLESS_3D_FORM' | AO74: 'POS23985176461' | AT74: '570297560929' | AW74: 160 | AX74: 0 | AY74: 0 | BB74: '01' | BC74: 'abdulkk28579@naviaxis' | BH74: 'Txn Success' | BK74: 160 | BP74: '570297560929' | BQ74: 'false' | BR74: 'Paid via Navi UPI' | BS74: 'RECEIVER' | BT74: 'UPI|UPIPUSH|QR|PPBL' | BU74: 'PPBL' | BW74: 0 | BX74: 0 | CH74: 'UPI:null' | DJ74: 'BW'
A75: '20251202111030000202436221918387677' | B75: 'T2512020212121143313144' | E75: '2025-12-02 02:12:15' | F75: '2025-12-02 02:12:16' | G75: 'ACQUIRING' | H75: 'SUCCESS' | I75: 'TYXysH23627954956290' | J75: 'SHA SHA SHANDAAR SHAWARMA' | O75: 430 | P75: 0 | Q75: 0 | S75: 'AWSPG202512020001216820000806612997973' | T75: 'WAP' | U75: 'YESAP53373551554' | V75: '2025-12-02 00:01:00' | W75: '2025-12-03 04:28:11' | X75: 'UPI' | AA75: 'POS23985176461' | AC75: '5120220602313474057' | AE75: '51051000100000000001' | AH75: 'SEAMLESS_3D_FORM' | AT75: '398927257215' | AW75: 430 | AX75: 0 | AY75: 0 | BB75: '01' | BC75: 'saishekhar999992@axl' | BH75: 'Txn Success' | BK75: 430 | BP75: '398927257215' | BQ75: 'false' | BR75: 'Payment from PhonePe' | BS75: 'RECEIVER' | BT75: 'UPI|UPIPUSH|QR|PPBL' | BU75: 'PPBL' | BW75: 0 | BX75: 0 | CH75: 'UPI:null' | DJ75: 'BW'
A76: '20251202111070000202431239668803666' | B76: 'SBI9a09c1df27aa4fb8b8f46513815cd55d' | E76: '2025-12-02 01:52:27' | F76: '2025-12-02 01:52:28' | G76: 'ACQUIRING' | H76: 'SUCCESS' | I76: 'TYXysH23627954956290' | J76: 'SHA SHA SHANDAAR SHAWARMA' | O76: 180 | P76: 0 | Q76: 0 | S76: 'AWSPG202512020001216820000806612997973' | T76: 'WAP' | U76: 'YESAP53373551554' | V76: '2025-12-02 00:01:00' | W76: '2025-12-03 04:28:11' | X76: 'UPI' | AA76: 'POS23985176461' | AC76: '5120230500038690821' | AE76: '51051000100000000001' | AH76: 'SEAMLESS_3D_FORM' | AT76: '533636245468' | AW76: 180 | AX76: 0 | AY76: 0 | BB76: '01' | BC76: 'stockykp@oksbi' | BH76: 'Txn Success' | BK76: 180 | BP76: '533636245468' | BQ76: 'false' | BR76: 'UPI' | BS76: 'RECEIVER' | BT76: 'UPI|UPIPUSH|QR|PPBL' | BU76: 'PPBL' | BW76: 0 | BX76: 0 | CH76: 'UPI:null' | DJ76: 'BW'
A77: '20251202010950000202430189268264698' | B77: 'SMTXCR9BWNJ4POKDPXWQKHJW5U2NKK1YMPN' | E77: '2025-12-02 01:48:17' | F77: '2025-12-02 01:48:18' | G77: 'ACQUIRING' | H77: 'SUCCESS' | I77: 'TYXysH23627954956290' | J77: 'SHA SHA SHANDAAR SHAWARMA' | O77: 150 | P77: 0 | Q77: 0 | S77: 'AWSPG202512020001216820000806612997973' | T77: 'WAP' | U77: 'YESAP53373551554' | V77: '2025-12-02 00:01:00' | W77: '2025-12-03 04:28:11' | X77: 'UPI' | AA77: 'POS23985176461' | AC77: '5120220482189745165' | AE77: '51051000100000000001' | AH77: 'SEAMLESS_3D_FORM' | AO77: 'POS23985176461' | AT77: '533636869658' | AW77: 150 | AX77: 0 | AY77: 0 | BB77: '01' | BC77: '7981229697@superyes' | BH77: 'Txn Success' | BK77: 150 | BP77: '533636869658' | BQ77: 'false' | BR77: 'Paid via SuperMoney UPI' | BS77: 'RECEIVER' | BT77: 'UPI|UPIPUSH|QR|PPBL' | BU77: 'PPBL' | BW77: 0 | BX77: 0 | CH77: 'UPI:null' | DJ77: 'BW'
A78: '20251202010950000202427694819203858' | B78: 'T2512020138199728201230' | E78: '2025-12-02 01:38:22' | F78: '2025-12-02 01:38:23' | G78: 'ACQUIRING' | H78: 'SUCCESS' | I78: 'TYXysH23627954956290' | J78: 'SHA SHA SHANDAAR SHAWARMA' | O78: 500 | P78: 0 | Q78: 0 | S78: 'AWSPG202512020001216820000806612997973' | T78: 'WAP' | U78: 'YESAP53373551554' | V78: '2025-12-02 00:01:00' | W78: '2025-12-03 04:28:11' | X78: 'UPI' | AA78: 'POS23985176461' | AC78: '5120220439571636237' | AE78: '51051000100000000001' | AH78: 'SEAMLESS_3D_FORM' | AT78: '323593176278' | AW78: 500 | AX78: 0 | AY78: 0 | BB78: '01' | BC78: 'raiharsh29082002@ybl' | BH78: 'Txn Success' | BK78: 500 | BP78: '323593176278' | BQ78: 'false' | BR78: 'Payment from PhonePe' | BS78: 'RECEIVER' | BT78: 'UPI|UPIPUSH|QR|PPBL' | BU78: 'PPBL' | BW78: 0 | BX78: 0 | CH78: 'UPI:null' | DJ78: 'BW'
A79: '20251202110930000202425623034004853' | B79: 'ACDac32eadbd8224487871ded0d9e4cce65' | E79: '2025-12-02 01:30:08' | F79: '2025-12-02 01:30:09' | G79: 'ACQUIRING' | H79: 'SUCCESS' | I79: 'TYXysH23627954956290' | J79: 'SHA SHA SHANDAAR SHAWARMA' | O79: 180 | P79: 0 | Q79: 0 | S79: 'AWSPG202512020001216820000806612997973' | T79: 'WAP' | U79: 'YESAP53373551554' | V79: '2025-12-02 00:01:00' | W79: '2025-12-03 04:28:11' | X79: 'UPI' | AA79: 'POS23985176461' | AC79: '5120220404273983501' | AE79: '51051000100000000001' | AH79: 'SEAMLESS_3D_FORM' | AT79: '533664623652' | AW79: 180 | AX79: 0 | AY79: 0 | BB79: '01' | BC79: '9866399502@axisb' | BH79: 'Txn Success' | BK79: 180 | BP79: '533664623652' | BQ79: 'false' | BR79: 'Paid via CRED' | BS79: 'RECEIVER' | BT79: 'UPI|UPIPUSH|QR|PPBL' | BU79: 'PPBL' | BW79: 0 | BX79: 0 | CH79: 'UPI:null' | DJ79: 'BW'
A80: '20251202111080000202425089598158902' | B80: 'HDFef02fef70ea74555a3c267b124fae95f' | E80: '2025-12-02 01:28:01' | F80: '2025-12-02 01:28:02' | G80: 'ACQUIRING' | H80: 'SUCCESS' | I80: 'TYXysH23627954956290' | J80: 'SHA SHA SHANDAAR SHAWARMA' | O80: 340 | P80: 0 | Q80: 0 | S80: 'AWSPG202512020001216820000806612997973' | T80: 'WAP' | U80: 'YESAP53373551554' | V80: '2025-12-02 00:01:00' | W80: '2025-12-03 04:28:11' | X80: 'UPI' | AA80: 'POS23985176461' | AC80: '5120220395214997505' | AE80: '51051000100000000001' | AH80: 'SEAMLESS_3D_FORM' | AT80: '114988782591' | AW80: 340 | AX80: 0 | AY80: 0 | BB80: '01' | BC80: 'bikram.roy507-3@okhdfcbank' | BH80: 'Txn Success' | BK80: 340 | BP80: '114988782591' | BQ80: 'false' | BR80: 'UPI' | BS80: 'RECEIVER' | BT80: 'UPI|UPIPUSH|QR|PPBL' | BU80: 'PPBL' | BW80: 0 | BX80: 0 | CH80: 'UPI:null' | DJ80: 'BW'
A81: '20251202110840000202424821859008844' | B81: 'ACDa6bc317030294a5ea06d797f80e6e019' | E81: '2025-12-02 01:26:57' | F81: '2025-12-02 01:26:58' | G81: 'ACQUIRING' | H81: 'SUCCESS' | I81: 'TYXysH23627954956290' | J81: 'SHA SHA SHANDAAR SHAWARMA' | O81: 150 | P81: 0 | Q81: 0 | S81: 'AWSPG202512020001216820000806612997973' | T81: 'WAP' | U81: 'YESAP53373551554' | V81: '2025-12-02 00:01:00' | W81: '2025-12-03 04:28:11' | X81: 'UPI' | AA81: 'POS23985176461' | AC81: '5120220390384029713' | AE81: '51051000100000000001' | AH81: 'SEAMLESS_3D_FORM' | AT81: '533664623197' | AW81: 150 | AX81: 0 | AY81: 0 | BB81: '01' | BC81: '9866399502@axisb' | BH81: 'Txn Success' | BK81: 150 | BP81: '533664623197' | BQ81: 'false' | BR81: 'Paid via CRED' | BS81: 'RECEIVER' | BT81: 'UPI|UPIPUSH|QR|PPBL' | BU81: 'PPBL' | BW81: 0 | BX81: 0 | CH81: 'UPI:null' | DJ81: 'BW'
A82: '20251202110880000202423651509772404' | B82: 'T2512020122158194167999' | E82: '2025-12-02 01:22:18' | F82: '2025-12-02 01:22:19' | G82: 'ACQUIRING' | H82: 'SUCCESS' | I82: 'TYXysH23627954956290' | J82: 'SHA SHA SHANDAAR SHAWARMA' | O82: 160 | P82: 0 | Q82: 0 | S82: 'AWSPG202512020001216820000806612997973' | T82: 'WAP' | U82: 'YESAP53373551554' | V82: '2025-12-02 00:01:00' | W82: '2025-12-03 04:28:11' | X82: 'UPI' | AA82: 'POS23985176461' | AC82: '5120220370583724037' | AE82: '51051000100000000001' | AH82: 'SEAMLESS_3D_FORM' | AT82: '387839238215' | AW82: 160 | AX82: 0 | AY82: 0 | BB82: '01' | BC82: '7842340809@ybl' | BH82: 'Txn Success' | BK82: 160 | BP82: '387839238215' | BQ82: 'false' | BR82: 'Payment from PhonePe' | BS82: 'RECEIVER' | BT82: 'UPI|UPIPUSH|QR|PPBL' | BU82: 'PPBL' | BW82: 0 | BX82: 0 | CH82: 'UPI:null' | DJ82: 'BW'
A83: '20251202111050000202423349164094011' | B83: 'SBI5edfcc5c409e426c90abe1a1607b1611' | E83: '2025-12-02 01:21:06' | F83: '2025-12-02 01:21:07' | G83: 'ACQUIRING' | H83: 'SUCCESS' | I83: 'TYXysH23627954956290' | J83: 'SHA SHA SHANDAAR SHAWARMA' | O83: 160 | P83: 0 | Q83: 0 | S83: 'AWSPG202512020001216820000806612997973' | T83: 'WAP' | U83: 'YESAP53373551554' | V83: '2025-12-02 00:01:00' | W83: '2025-12-03 04:28:11' | X83: 'UPI' | AA83: 'POS23985176461' | AC83: '5120230365485418497' | AE83: '51051000100000000001' | AH83: 'SEAMLESS_3D_FORM' | AT83: '533636156407' | AW83: 160 | AX83: 0 | AY83: 0 | BB83: '01' | BC83: 'bk2094833@oksbi' | BH83: 'Txn Success' | BK83: 160 | BP83: '533636156407' | BQ83: 'false' | BR83: 'UPI' | BS83: 'RECEIVER' | BT83: 'UPI|UPIPUSH|QR|PPBL' | BU83: 'PPBL' | BW83: 0 | BX83: 0 | CH83: 'UPI:null' | DJ83: 'BW'
A84: '20251202111100000202422059901132808' | B84: 'T2512020115545826633197' | E84: '2025-12-02 01:15:58' | F84: '2025-12-02 01:16:00' | G84: 'ACQUIRING' | H84: 'SUCCESS' | I84: 'TYXysH23627954956290' | J84: 'SHA SHA SHANDAAR SHAWARMA' | O84: 660 | P84: 0 | Q84: 0 | S84: 'AWSPG202512020001216820000806612997973' | T84: 'WAP' | U84: 'YESAP53373551554' | V84: '2025-12-02 00:01:00' | W84: '2025-12-03 04:28:11' | X84: 'UPI' | AA84: 'POS23985176461' | AC84: '5120220343273689093' | AE84: '51051000100000000001' | AH84: 'SEAMLESS_3D_FORM' | AT84: '199660351837' | AW84: 660 | AX84: 0 | AY84: 0 | BB84: '01' | BC84: '9059496377-2@ybl' | BH84: 'Txn Success' | BK84: 660 | BP84: '199660351837' | BQ84: 'false' | BR84: 'Payment from PhonePe' | BS84: 'RECEIVER' | BT84: 'UPI|UPIPUSH|QR|PPBL' | BU84: 'PPBL' | BW84: 0 | BX84: 0 | CH84: 'UPI:null' | DJ84: 'BW'
A85: '20251202111000000202420646526110430' | B85: 'T2512020110176826904935' | E85: '2025-12-02 01:10:22' | F85: '2025-12-02 01:10:22' | G85: 'ACQUIRING' | H85: 'SUCCESS' | I85: 'TYXysH23627954956290' | J85: 'SHA SHA SHANDAAR SHAWARMA' | O85: 150 | P85: 0 | Q85: 0 | S85: 'AWSPG202512020001216820000806612997973' | T85: 'WAP' | U85: 'YESAP53373551554' | V85: '2025-12-02 00:01:00' | W85: '2025-12-03 04:28:11' | X85: 'UPI' | AA85: 'POS23985176461' | AC85: '5120220319312822273' | AE85: '51051000100000000001' | AH85: 'SEAMLESS_3D_FORM' | AT85: '713905406956' | AW85: 150 | AX85: 0 | AY85: 0 | BB85: '01' | BC85: '9381969521-2@axl' | BH85: 'Txn Success' | BK85: 150 | BP85: '713905406956' | BQ85: 'false' | BR85: 'Payment from PhonePe' | BS85: 'RECEIVER' | BT85: 'UPI|UPIPUSH|QR|PPBL' | BU85: 'PPBL' | BW85: 0 | BX85: 0 | CH85: 'UPI:null' | DJ85: 'BW'
A86: '20251202011090000202419641012568786' | B86: 'T2512020106088198426186' | E86: '2025-12-02 01:06:22' | F86: '2025-12-02 01:06:23' | G86: 'ACQUIRING' | H86: 'SUCCESS' | I86: 'TYXysH23627954956290' | J86: 'SHA SHA SHANDAAR SHAWARMA' | O86: 260 | P86: 0 | Q86: 0 | S86: 'AWSPG202512020001216820000806612997973' | T86: 'WAP' | U86: 'YESAP53373551554' | V86: '2025-12-02 00:01:00' | W86: '2025-12-03 04:28:11' | X86: 'UPI' | AA86: 'POS23985176461' | AC86: '5120220302135003141' | AE86: '51051000100000000001' | AH86: 'SEAMLESS_3D_FORM' | AT86: '921908517233' | AW86: 260 | AX86: 0 | AY86: 0 | BB86: '01' | BC86: 'debajitkalita109@axl' | BH86: 'Txn Success' | BK86: 260 | BP86: '921908517233' | BQ86: 'false' | BR86: 'Payment from PhonePe' | BS86: 'RECEIVER' | BT86: 'UPI|UPIPUSH|QR|PPBL' | BU86: 'PPBL' | BW86: 0 | BX86: 0 | CH86: 'UPI:null' | DJ86: 'BW'
A87: '20251202111050000202416957300624897' | B87: 'T2512020055308758183712' | E87: '2025-12-02 00:55:42' | F87: '2025-12-02 00:55:43' | G87: 'ACQUIRING' | H87: 'SUCCESS' | I87: 'TYXysH23627954956290' | J87: 'SHA SHA SHANDAAR SHAWARMA' | O87: 300 | P87: 0 | Q87: 0 | S87: 'AWSPG202512020001216820000806612997973' | T87: 'WAP' | U87: 'YESAP53373551554' | V87: '2025-12-02 00:01:00' | W87: '2025-12-03 04:28:11' | X87: 'UPI' | AA87: 'POS23985176461' | AC87: '5120220239051321353' | AE87: '51051000100000000001' | AH87: 'SEAMLESS_3D_FORM' | AT87: '180695117195' | AW87: 300 | AX87: 0 | AY87: 0 | BB87: '01' | BC87: '9963694850-2@axl' | BH87: 'Txn Success' | BK87: 300 | BP87: '180695117195' | BQ87: 'false' | BR87: 'Payment from PhonePe' | BS87: 'RECEIVER' | BT87: 'UPI|UPIPUSH|QR|PPBL' | BU87: 'PPBL' | BW87: 0 | BX87: 0 | CH87: 'UPI:null' | DJ87: 'BW'
A88: '20251202110880000202410520385461063' | B88: 'AXIff179ffa755d4c03836eebe38ddf6c77' | E88: '2025-12-02 00:30:07' | F88: '2025-12-02 00:30:09' | G88: 'ACQUIRING' | H88: 'SUCCESS' | I88: 'TYXysH23627954956290' | J88: 'SHA SHA SHANDAAR SHAWARMA' | O88: 300 | P88: 0 | Q88: 0 | S88: 'AWSPG202512020001216820000806612997973' | T88: 'WAP' | U88: 'YESAP53373551554' | V88: '2025-12-02 00:01:00' | W88: '2025-12-03 04:28:11' | X88: 'UPI' | AA88: 'POS23985176461' | AC88: '5120220129329207301' | AE88: '51051000100000000001' | AH88: 'SEAMLESS_3D_FORM' | AT88: '533654975812' | AW88: 300 | AX88: 0 | AY88: 0 | BB88: '01' | BC88: 'rohanrajveer8-1@okaxis' | BH88: 'Txn Success' | BK88: 300 | BP88: '533654975812' | BQ88: 'false' | BR88: 'UPI' | BS88: 'RECEIVER' | BT88: 'UPI|UPIPUSH|QR|PPBL' | BU88: 'PPBL' | BW88: 0 | BX88: 0 | CH88: 'UPI:null' | DJ88: 'BW'
A89: '20251202110970000202410031488998853' | B89: '002811016929' | E89: '2025-12-02 00:28:11' | F89: '2025-12-02 00:28:12' | G89: 'ACQUIRING' | H89: 'SUCCESS' | I89: 'TYXysH23627954956290' | J89: 'SHA SHA SHANDAAR SHAWARMA' | O89: 320 | P89: 0 | Q89: 0 | S89: 'AWSPG202512020001216820000806612997973' | T89: 'WAP' | U89: 'YESAP53373551554' | V89: '2025-12-02 00:01:00' | W89: '2025-12-03 04:28:11' | X89: 'UPI' | AA89: 'POS23985176461' | AC89: '5120220121007526917' | AE89: '51051000100000000001' | AH89: 'SEAMLESS_3D_FORM' | AT89: '002810996425' | AW89: 320 | AX89: 0 | AY89: 0 | BB89: '01' | BC89: 'mohammedkadheer@upi' | BH89: 'Txn Success' | BK89: 320 | BP89: '002810996425' | BQ89: 'false' | BR89: 'NO REMARKS' | BS89: 'RECEIVER' | BT89: 'UPI|UPIPUSH|QR|PPBL' | BU89: 'PPBL' | BW89: 0 | BX89: 0 | CH89: 'UPI:null' | DJ89: 'BW'
... A91: '20251202110900000202403963903827131' | B91: 'T2512020004017392546884' | E91: '2025-12-02 00:04:04' | F91: '2025-12-02 00:04:07' | G91: 'ACQUIRING' | H91: 'SUCCESS' | I91: 'TYXysH23627954956290' | J91: 'SHA SHA SHANDAAR SHAWARMA' | O91: 150 | P91: 0 | Q91: 0 | S91: 'AWSPG202512020001216820000806612997973' | T91: 'WAP' | U91: 'YESAP53373551554' | V91: '2025-12-02 00:01:00' | W91: '2025-12-03 04:28:11' | X91: 'UPI' | AA91: 'POS23985176461' | AC91: '5120220017458257925' | AE91: '51051000100000000001' | AH91: 'SEAMLESS_3D_FORM' | AT91: '050566747199' | AW91: 150 | AX91: 0 | AY91: 0 | BB91: '01' | BC91: 'rakeshgurakonda1@axl' | BH91: 'Txn Success' | BK91: 150 | BP91: '050566747199' | BQ91: 'false' | BR91: 'Payment from PhonePe' | BS91: 'RECEIVER' | BT91: 'UPI|UPIPUSH|QR|PPBL' | BU91: 'PPBL' | BW91: 0 | BX91: 0 | CH91: 'UPI:null' | DJ91: 'BW'
A92: '20251202111030000202467444883796204' | B92: 'SMTX6Z9GJNKP7MX41S1N78SW6KQ329COHFY' | E92: '2025-12-02 04:16:19' | F92: '2025-12-02 04:16:20' | G92: 'ACQUIRING' | H92: 'SUCCESS' | I92: 'TYXysH23627954956290' | J92: 'SHA SHA SHANDAAR SHAWARMA' | O92: 590 | P92: 0 | Q92: 0 | S92: 'AWSPG202512020001216820000806612997973' | T92: 'WAP' | U92: 'YESAP53373551554' | V92: '2025-12-02 00:01:00' | W92: '2025-12-03 04:28:11' | X92: 'UPI' | AA92: 'POS23985176461' | AC92: '5120221169514979341' | AE92: '51051000100000000001' | AH92: 'SEAMLESS_3D_FORM' | AO92: 'POS23985176461' | AT92: '533638625740' | AW92: 590 | AX92: 0 | AY92: 0 | BB92: '01' | BC92: '7288066619@superyes' | BH92: 'Txn Success' | BK92: 590 | BP92: '533638625740' | BQ92: 'false' | BR92: 'Paid via SuperMoney UPI' | BS92: 'RECEIVER' | BT92: 'UPI|UPIPUSH|QR|PPBL' | BU92: 'PPBL' | BW92: 0 | BX92: 0 | CH92: 'UPI:null' | DJ92: 'BW'
A93: '20251202111080000202459984374778877' | B93: 'T2512020346362594495751' | E93: '2025-12-02 03:46:40' | F93: '2025-12-02 03:46:42' | G93: 'ACQUIRING' | H93: 'SUCCESS' | I93: 'TYXysH23627954956290' | J93: 'SHA SHA SHANDAAR SHAWARMA' | O93: 130 | P93: 0 | Q93: 0 | S93: 'AWSPG202512020001216820000806612997973' | T93: 'WAP' | U93: 'YESAP53373551554' | V93: '2025-12-02 00:01:00' | W93: '2025-12-03 04:28:11' | X93: 'UPI' | AA93: 'POS23985176461' | AC93: '5120231024963825665' | AE93: '51051000100000000001' | AH93: 'SEAMLESS_3D_FORM' | AT93: '419230968877' | AW93: 130 | AX93: 0 | AY93: 0 | BB93: '01' | BC93: '9063068207@ibl' | BH93: 'Txn Success' | BK93: 130 | BP93: '419230968877' | BQ93: 'false' | BR93: 'Payment from PhonePe' | BS93: 'RECEIVER' | BT93: 'UPI|UPIPUSH|QR|PPBL' | BU93: 'PPBL' | BW93: 0 | BX93: 0 | CH93: 'UPI:null' | DJ93: 'BW'
A94: '20251202110870000202632541685792949' | B94: 'T2512021512191796428386' | E94: '2025-12-02 15:12:21' | F94: '2025-12-02 15:12:23' | G94: 'ACQUIRING' | H94: 'SUCCESS' | I94: 'TYXysH23627954956290' | J94: 'SHA SHA SHANDAAR SHAWARMA' | O94: 150 | P94: 0 | Q94: 0 | S94: 'AWSPG202512020001216820000806612997973' | T94: 'WAP' | U94: 'YESAP53373551554' | V94: '2025-12-02 00:01:00' | W94: '2025-12-03 04:28:11' | X94: 'UPI' | AA94: 'POS23985176461' | AC94: '5120224176128488513' | AE94: '51051000100000000001' | AH94: 'SEAMLESS_3D_FORM' | AT94: '372694179941' | AW94: 150 | AX94: 0 | AY94: 0 | BB94: '01' | BC94: '9381234862-6@ybl' | BH94: 'Txn Success' | BK94: 150 | BP94: '372694179941' | BQ94: 'false' | BR94: 'Payment from PhonePe' | BS94: 'RECEIVER' | BT94: 'UPI|UPIPUSH|QR|PPBL' | BU94: 'PPBL' | BW94: 0 | BX94: 0 | CH94: 'UPI:null' | DJ94: 'BW'
A95: '20251202111100000202624499422553525' | B95: 'ICI22ae7b2ac8e844258f87d61831f1693d' | E95: '2025-12-02 14:40:24' | F95: '2025-12-02 14:40:25' | G95: 'ACQUIRING' | H95: 'SUCCESS' | I95: 'TYXysH23627954956290' | J95: 'SHA SHA SHANDAAR SHAWARMA' | O95: 150 | P95: 0 | Q95: 0 | S95: 'AWSPG202512020001216820000806612997973' | T95: 'WAP' | U95: 'YESAP53373551554' | V95: '2025-12-02 00:01:00' | W95: '2025-12-03 04:28:11' | X95: 'UPI' | AA95: 'POS23985176461' | AC95: '5120234021711191077' | AE95: '51051000100000000001' | AH95: 'SEAMLESS_3D_FORM' | AT95: '533647718612' | AW95: 150 | AX95: 0 | AY95: 0 | BB95: '01' | BC95: 'asiya83411-2@okicici' | BH95: 'Txn Success' | BK95: 150 | BP95: '533647718612' | BQ95: 'false' | BR95: 'UPI' | BS95: 'RECEIVER' | BT95: 'UPI|UPIPUSH|QR|PPBL' | BU95: 'PPBL' | BW95: 0 | BX95: 0 | CH95: 'UPI:null' | DJ95: 'BW'
A96: '20251202110970000202623372123931893' | B96: 'T2512021435497624935546' | E96: '2025-12-02 14:35:55' | F96: '2025-12-02 14:35:57' | G96: 'ACQUIRING' | H96: 'SUCCESS' | I96: 'TYXysH23627954956290' | J96: 'SHA SHA SHANDAAR SHAWARMA' | O96: 150 | P96: 0 | Q96: 0 | S96: 'AWSPG202512020001216820000806612997973' | T96: 'WAP' | U96: 'YESAP53373551554' | V96: '2025-12-02 00:01:00' | W96: '2025-12-03 04:28:11' | X96: 'UPI' | AA96: 'POS23985176461' | AC96: '5120224002314346561' | AE96: '51051000100000000001' | AH96: 'SEAMLESS_3D_FORM' | AT96: '366199463145' | AW96: 150 | AX96: 0 | AY96: 0 | BB96: '01' | BC96: '9014622466-2@axl' | BH96: 'Txn Success' | BK96: 150 | BP96: '366199463145' | BQ96: 'false' | BR96: 'Payment from PhonePe' | BS96: 'RECEIVER' | BT96: 'UPI|UPIPUSH|QR|PPBL' | BU96: 'PPBL' | BW96: 0 | BX96: 0 | CH96: 'UPI:null' | DJ96: 'BW'
A97: '20251202110980000202620082338639147' | B97: 'PTMcef3ffcf49aa4889b698dc89fdda60ec' | E97: '2025-12-02 14:22:51' | F97: '2025-12-02 14:22:52' | G97: 'ACQUIRING' | H97: 'SUCCESS' | I97: 'TYXysH23627954956290' | J97: 'SHA SHA SHANDAAR SHAWARMA' | O97: 150 | P97: 0 | Q97: 0 | S97: 'AWSPG202512020001216820000806612997973' | T97: 'WAP' | U97: 'YESAP53373551554' | V97: '2025-12-02 00:01:00' | W97: '2025-12-03 04:28:11' | X97: 'UPI' | AA97: 'POS23985176461' | AC97: '5120233946212675621' | AE97: '51051000100000000001' | AH97: 'SEAMLESS_3D_FORM' | AO97: 'POS23985176461' | AT97: '393161295769' | AW97: 150 | AX97: 0 | AY97: 0 | BB97: '01' | BC97: '9032069306@ptyes' | BH97: 'Txn Success' | BK97: 150 | BP97: '393161295769' | BQ97: 'false' | BR97: 'NA' | BS97: 'RECEIVER' | BT97: 'UPI|UPIPUSH|QR|PPBL' | BU97: 'PPBL' | BW97: 0 | BX97: 0 | CH97: 'UPI:null' | DJ97: 'BW'
A98: '20251202110910000202730354965616101' | B98: 'T2512022140578488206402' | E98: '2025-12-02 21:41:02' | F98: '2025-12-02 21:41:03' | G98: 'ACQUIRING' | H98: 'SUCCESS' | I98: 'TYXysH23627954956290' | J98: 'SHA SHA SHANDAAR SHAWARMA' | O98: 150 | P98: 0 | Q98: 0 | S98: 'AWSPG202512020001216820000806612997973' | T98: 'WAP' | U98: 'YESAP53373551554' | V98: '2025-12-02 00:01:00' | W98: '2025-12-03 04:28:11' | X98: 'UPI' | AA98: 'POS23985176461' | AC98: '5120225948676442117' | AE98: '51051000100000000001' | AH98: 'SEAMLESS_3D_FORM' | AT98: '787210478508' | AW98: 150 | AX98: 0 | AY98: 0 | BB98: '01' | BC98: '9912414495@axl' | BH98: 'Txn Success' | BK98: 150 | BP98: '787210478508' | BQ98: 'false' | BR98: 'Payment from PhonePe' | BS98: 'RECEIVER' | BT98: 'UPI|UPIPUSH|QR|PPBL' | BU98: 'PPBL' | BW98: 0 | BX98: 0 | CH98: 'UPI:null' | DJ98: 'BW'
A99: '20251202110840000202730331124916106' | B99: 'ICIf7451195495b41ff904d2931d1616a89' | E99: '2025-12-02 21:40:56' | F99: '2025-12-02 21:40:57' | G99: 'ACQUIRING' | H99: 'SUCCESS' | I99: 'TYXysH23627954956290' | J99: 'SHA SHA SHANDAAR SHAWARMA' | O99: 310 | P99: 0 | Q99: 0 | S99: 'AWSPG202512020001216820000806612997973' | T99: 'WAP' | U99: 'YESAP53373551554' | V99: '2025-12-02 00:01:00' | W99: '2025-12-03 04:28:11' | X99: 'UPI' | AA99: 'POS23985176461' | AC99: '5120225948005282833' | AE99: '51051000100000000001' | AH99: 'SEAMLESS_3D_FORM' | AT99: '533663153838' | AW99: 310 | AX99: 0 | AY99: 0 | BB99: '01' | BC99: 'mirzaakbarbaig231-3@okicici' | BH99: 'Txn Success' | BK99: 310 | BP99: '533663153838' | BQ99: 'false' | BR99: 'UPI' | BS99: 'RECEIVER' | BT99: 'UPI|UPIPUSH|QR|PPBL' | BU99: 'PPBL' | BW99: 0 | BX99: 0 | CH99: 'UPI:null' | DJ99: 'BW'
A100: '20251202110980000202727232641485667' | B100: 'SBI2758e854fbf64a798efbbaf13c815553' | E100: '2025-12-02 21:28:37' | F100: '2025-12-02 21:28:39' | G100: 'ACQUIRING' | H100: 'SUCCESS' | I100: 'TYXysH23627954956290' | J100: 'SHA SHA SHANDAAR SHAWARMA' | O100: 320 | P100: 0 | Q100: 0 | S100: 'AWSPG202512020001216820000806612997973' | T100: 'WAP' | U100: 'YESAP53373551554' | V100: '2025-12-02 00:01:00' | W100: '2025-12-03 04:28:11' | X100: 'UPI' | AA100: 'POS23985176461' | AC100: '5120235895187968025' | AE100: '51051000100000000001' | AH100: 'SEAMLESS_3D_FORM' | AT100: '533677197092' | AW100: 320 | AX100: 0 | AY100: 0 | BB100: '01' | BC100: 'psai12696@oksbi' | BH100: 'Txn Success' | BK100: 320 | BP100: '533677197092' | BQ100: 'false' | BR100: 'UPI' | BS100: 'RECEIVER' | BT100: 'UPI|UPIPUSH|QR|PPBL' | BU100: 'PPBL' | BW100: 0 | BX100: 0 | CH100: 'UPI:null' | DJ100: 'BW'
A101: '20251202110880000202727138831970887' | B101: 'SBI63e139a8bfe64cd48c458939f06e5fb0' | E101: '2025-12-02 21:28:15' | F101: '2025-12-02 21:28:17' | G101: 'ACQUIRING' | H101: 'SUCCESS' | I101: 'TYXysH23627954956290' | J101: 'SHA SHA SHANDAAR SHAWARMA' | O101: 300 | P101: 0 | Q101: 0 | S101: 'AWSPG202512020001216820000806612997973' | T101: 'WAP' | U101: 'YESAP53373551554' | V101: '2025-12-02 00:01:00' | W101: '2025-12-03 04:28:11' | X101: 'UPI' | AA101: 'POS23985176461' | AC101: '5120225893713567757' | AE101: '51051000100000000001' | AH101: 'SEAMLESS_3D_FORM' | AT101: '533677188392' | AW101: 300 | AX101: 0 | AY101: 0 | BB101: '01' | BC101: 'sakshipanday964@oksbi' | BH101: 'Txn Success' | BK101: 300 | BP101: '533677188392' | BQ101: 'false' | BR101: 'UPI' | BS101: 'RECEIVER' | BT101: 'UPI|UPIPUSH|QR|PPBL' | BU101: 'PPBL' | BW101: 0 | BX101: 0 | CH101: 'UPI:null' | DJ101: 'BW'
A102: '20251202111030000202724589646488024' | B102: 'PTMf06ffe034ec24f558f8b7fb1dbea37e8' | E102: '2025-12-02 21:18:07' | F102: '2025-12-02 21:18:09' | G102: 'ACQUIRING' | H102: 'SUCCESS' | I102: 'TYXysH23627954956290' | J102: 'SHA SHA SHANDAAR SHAWARMA' | O102: 150 | P102: 0 | Q102: 0 | S102: 'AWSPG202512020001216820000806612997973' | T102: 'WAP' | U102: 'YESAP53373551554' | V102: '2025-12-02 00:01:00' | W102: '2025-12-03 04:28:11' | X102: 'UPI' | AA102: 'POS23985176461' | AC102: '5120225850224557073' | AE102: '51051000100000000001' | AH102: 'SEAMLESS_3D_FORM' | AO102: 'POS23985176461' | AT102: '533626973020' | AW102: 150 | AX102: 0 | AY102: 0 | BB102: '01' | BC102: 'vancynalluri35vk@ptaxis' | BH102: 'Txn Success' | BK102: 150 | BP102: '533626973020' | BQ102: 'false' | BR102: 'NA' | BS102: 'RECEIVER' | BT102: 'UPI|UPIPUSH|QR|PPBL' | BU102: 'PPBL' | BW102: 0 | BX102: 0 | CH102: 'UPI:null' | DJ102: 'BW'
A103: '20251202010900000202721217841982002' | B103: 'T2512022104400205019969' | E103: '2025-12-02 21:04:43' | F103: '2025-12-02 21:04:45' | G103: 'ACQUIRING' | H103: 'SUCCESS' | I103: 'TYXysH23627954956290' | J103: 'SHA SHA SHANDAAR SHAWARMA' | O103: 130 | P103: 0 | Q103: 0 | S103: 'AWSPG202512020001216820000806612997973' | T103: 'WAP' | U103: 'YESAP53373551554' | V103: '2025-12-02 00:01:00' | W103: '2025-12-03 04:28:11' | X103: 'UPI' | AA103: 'POS23985176461' | AC103: '5120235792511276081' | AE103: '51051000100000000001' | AH103: 'SEAMLESS_3D_FORM' | AT103: '370545919805' | AW103: 130 | AX103: 0 | AY103: 0 | BB103: '01' | BC103: '9492937839@ybl' | BH103: 'Txn Success' | BK103: 130 | BP103: '370545919805' | BQ103: 'false' | BR103: 'Payment from PhonePe' | BS103: 'RECEIVER' | BT103: 'UPI|UPIPUSH|QR|PPBL' | BU103: 'PPBL' | BW103: 0 | BX103: 0 | CH103: 'UPI:null' | DJ103: 'BW'
A104: '20251202011040000202718768867063413' | B104: 'AXI429ad682c2df4843b65c43a26835c435' | E104: '2025-12-02 20:54:59' | F104: '2025-12-02 20:55:01' | G104: 'ACQUIRING' | H104: 'SUCCESS' | I104: 'TYXysH23627954956290' | J104: 'SHA SHA SHANDAAR SHAWARMA' | O104: 180 | P104: 4.09 | Q104: 0.74 | S104: 'AWSPG202512020001216820000806612997973' | T104: 'WAP' | U104: 'YESAP53373551554' | V104: '2025-12-02 00:01:00' | W104: '2025-12-03 04:28:11' | X104: 'UPI_CREDIT_CARD' | AA104: 'POS23985176461' | AC104: '5120225733793911817' | AE104: '51051000100000000001' | AH104: 'SEAMLESS_3D_FORM' | AO104: 'POS23985176461' | AT104: '570202161230' | AW104: 175.17 | AX104: 0 | AY104: 0 | BB104: '01' | BC104: 'aritra.baur-1@okaxis' | BH104: 'Txn Success' | BK104: 180 | BP104: '570202161230' | BQ104: 'false' | BR104: 'UPI' | BS104: 'RECEIVER' | BT104: 'UPI|UPIPUSH|QR|UPI_CREDIT_CARD|PPBL|Platinum|upiCc' | BU104: 'PPBL' | BW104: 4.09 | BX104: 0.74 | CH104: 'UPI:null' | DJ104: 'BW'
A105: '20251202111100000202718589661145772' | B105: 'T2512022054114042540695' | E105: '2025-12-02 20:54:17' | F105: '2025-12-02 20:54:19' | G105: 'ACQUIRING' | H105: 'SUCCESS' | I105: 'TYXysH23627954956290' | J105: 'SHA SHA SHANDAAR SHAWARMA' | O105: 280 | P105: 0 | Q105: 0 | S105: 'AWSPG202512020001216820000806612997973' | T105: 'WAP' | U105: 'YESAP53373551554' | V105: '2025-12-02 00:01:00' | W105: '2025-12-03 04:28:11' | X105: 'UPI' | AA105: 'POS23985176461' | AC105: '5120225730639134733' | AE105: '51051000100000000001' | AH105: 'SEAMLESS_3D_FORM' | AT105: '329987770195' | AW105: 280 | AX105: 0 | AY105: 0 | BB105: '01' | BC105: '9959545750@axl' | BH105: 'Txn Success' | BK105: 280 | BP105: '329987770195' | BQ105: 'false' | BR105: 'Payment from PhonePe' | BS105: 'RECEIVER' | BT105: 'UPI|UPIPUSH|QR|PPBL' | BU105: 'PPBL' | BW105: 0 | BX105: 0 | CH105: 'UPI:null' | DJ105: 'BW'
A106: '20251202110960000202716712542613294' | B106: 'T2512022046464991380765' | E106: '2025-12-02 20:46:49' | F106: '2025-12-02 20:46:51' | G106: 'ACQUIRING' | H106: 'SUCCESS' | I106: 'TYXysH23627954956290' | J106: 'SHA SHA SHANDAAR SHAWARMA' | O106: 300 | P106: 0 | Q106: 0 | S106: 'AWSPG202512020001216820000806612997973' | T106: 'WAP' | U106: 'YESAP53373551554' | V106: '2025-12-02 00:01:00' | W106: '2025-12-03 04:28:11' | X106: 'UPI' | AA106: 'POS23985176461' | AC106: '5120225698424089629' | AE106: '51051000100000000001' | AH106: 'SEAMLESS_3D_FORM' | AT106: '381523901959' | AW106: 300 | AX106: 0 | AY106: 0 | BB106: '01' | BC106: '8292073362@axl' | BH106: 'Txn Success' | BK106: 300 | BP106: '381523901959' | BQ106: 'false' | BR106: 'Payment from PhonePe' | BS106: 'RECEIVER' | BT106: 'UPI|UPIPUSH|QR|PPBL' | BU106: 'PPBL' | BW106: 0 | BX106: 0 | CH106: 'UPI:null' | DJ106: 'BW'
A107: '20251202010870000202713403744233227' | B107: 'T2512022033375733885877' | E107: '2025-12-02 20:33:40' | F107: '2025-12-02 20:33:42' | G107: 'ACQUIRING' | H107: 'SUCCESS' | I107: 'TYXysH23627954956290' | J107: 'SHA SHA SHANDAAR SHAWARMA' | O107: 520 | P107: 0 | Q107: 0 | S107: 'AWSPG202512020001216820000806612997973' | T107: 'WAP' | U107: 'YESAP53373551554' | V107: '2025-12-02 00:01:00' | W107: '2025-12-03 04:28:11' | X107: 'UPI' | AA107: 'POS23985176461' | AC107: '5120225641986409497' | AE107: '51051000100000000001' | AH107: 'SEAMLESS_3D_FORM' | AT107: '014958185401' | AW107: 520 | AX107: 0 | AY107: 0 | BB107: '01' | BC107: 'subahan.sk1@axl' | BH107: 'Txn Success' | BK107: 520 | BP107: '014958185401' | BQ107: 'false' | BR107: 'Payment from PhonePe' | BS107: 'RECEIVER' | BT107: 'UPI|UPIPUSH|QR|PPBL' | BU107: 'PPBL' | BW107: 0 | BX107: 0 | CH107: 'UPI:null' | DJ107: 'BW'
...
